Workbook

Sheet Transaction
A1: TransactionID | B1: TransactionDate_Clean | C1: CustomerID_Check | D1: ProductID | E1: ProductID_Clean | F1: Region_Clean | G1: RegionClean_ | H1: BusinessUnit_Clean | I1: SalesChannelClean | J1: Quantity | K1: UnitPrice_Clean | L1: ListPrice | M1: GrossRevenue_Analytical | N1: DiscountAmount_Analytical | O1: NetRevenue_Analytical | P1: Currency | Q1: ContractType_Clean | R1: CustomerSegment | S1: ProductCategory | T1: CustumerType | U1: Column1
A2: TXN-10001 | B2: 45674 | C2: C-1006 | D2: =UPPER(Table1[[#This Row],[ProductID_Clean]]) -> P-SI-004 | E2: P-SI-004 | F2: N. AMERICA | G2: =TRIM(Table1[[#This Row],[Region_Clean]]) -> N. AMERICA | H2: Sensors & Instruments | I2: Direct | J2: 3 | K2: 2165.11 | L2: 2450 | M2: 7350 | N2: 854.67 | O2: 6495.33 | P2: USD | Q2: Frame Agreement | R2: Aerospace & Defense | S2: =TRIM(PROPER(_xlfn.XLOOKUP(Table1[[#This Row],[ProductID_Clean]],Table3[ProductID],Table3[Category],"Missing Value",0))) -> Instruments | T2: =_xlfn.XLOOKUP(Table1[[#This Row],[CustomerID_Check]],Table2[CustomerID],Table2[CustomerType],"Missing Value",0) -> Standard
A3: TXN-10002 | B3: 45762 | C3: C-1095 | D3: =UPPER(Table1[[#This Row],[ProductID_Clean]]) -> P-SI-002 | E3: P-SI-002 | F3: LATIN AMERICA | G3: =TRIM(Table1[[#This Row],[Region_Clean]]) -> LATIN AMERICA | H3: Sensors & Instruments | I3: Partner Portal | J3: 2 | K3: 601.3 | L3: 725 | M3: 1450 | N3: 247.4 | O3: 1202.6 | P3: USD | Q3: Standard PO | R3: Manufacturing | S3: =TRIM(PROPER(_xlfn.XLOOKUP(Table1[[#This Row],[ProductID_Clean]],Table3[ProductID],Table3[Category],"Missing Value",0))) -> Sensors | T3: =_xlfn.XLOOKUP(Table1[[#This Row],[CustomerID_Check]],Table2[CustomerID],Table2[CustomerType],"Missing Value",0) -> Strategic
A4: TXN-10003 | B4: 45796 | C4: C-1151 | D4: =UPPER(Table1[[#This Row],[ProductID_Clean]]) -> P-SI-003 | E4: P-SI-003 | F4: LATIN AMERICA | G4: =TRIM(Table1[[#This Row],[Region_Clean]]) -> LATIN AMERICA | H4: Sensors & Instruments | I4: Missing Value | J4: 1 | K4: 1649.98 | L4: 1890 | M4: 1890 | N4: 240.02 | O4: 1649.98 | P4: USD | Q4: Frame Agreement | R4: Manufacturing | S4: =TRIM(PROPER(_xlfn.XLOOKUP(Table1[[#This Row],[ProductID_Clean]],Table3[ProductID],Table3[Category],"Missing Value",0))) -> Instruments | T4: =_xlfn.XLOOKUP(Table1[[#This Row],[CustomerID_Check]],Table2[CustomerID],Table2[CustomerType],"Missing Value",0) -> Standard
A5: TXN-10004 | B5: 45764 | C5: C-1168 | D5: =UPPER(Table1[[#This Row],[ProductID_Clean]]) -> P-SI-006 | E5: P-SI-006 | F5: LATIN AMERICA | G5: =TRIM(Table1[[#This Row],[Region_Clean]]) -> LATIN AMERICA | H5: Sensors & Instruments | I5: Direct | J5: 2 | K5: 168.38 | L5: 215 | M5: 430 | N5: 93.24 | O5: 336.76 | P5: USD | Q5: Frame Agreement | R5: Energy & Utilities | S5: =TRIM(PROPER(_xlfn.XLOOKUP(Table1[[#This Row],[ProductID_Clean]],Table3[ProductID],Table3[Category],"Missing Value",0))) -> Sensors | T5: =_xlfn.XLOOKUP(Table1[[#This Row],[CustomerID_Check]],Table2[CustomerID],Table2[CustomerType],"Missing Value",0) -> Standard
A6: TXN-10005 | B6: 45710 | C6: C-1070 | D6: =UPPER(Table1[[#This Row],[ProductID_Clean]]) -> P-SI-004 | E6: P-SI-004 | F6: EMEA | G6: =TRIM(Table1[[#This Row],[Region_Clean]]) -> EMEA | H6: Sensors & Instruments | I6: Direct | J6: 2 | K6: 2012.7 | L6: 2450 | M6: 4900 | N6: 874.6 | O6: 4025.4 | P6: USD | Q6: Standard PO | R6: Process Industries | S6: =TRIM(PROPER(_xlfn.XLOOKUP(Table1[[#This Row],[ProductID_Clean]],Table3[ProductID],Table3[Category],"Missing Value",0))) -> Instruments | T6: =_xlfn.XLOOKUP(Table1[[#This Row],[CustomerID_Check]],Table2[CustomerID],Table2[CustomerType],"Missing Value",0) -> Strategic
A7: TXN-10006 | B7: 45757 | C7: C-1172 | D7: =UPPER(Table1[[#This Row],[ProductID_Clean]]) -> P-SA-003 | E7: P-SA-003 | F7: N. AMERICA | G7: =TRIM(Table1[[#This Row],[Region_Clean]]) -> N. AMERICA | H7: Software & Analytics | I7: Direct | J7: 1 | K7: 2753.57 | L7: 2750 | M7: 2750 | N7: -3.57 | O7: 2753.57 | P7: USD | Q7: Annual License | R7: Manufacturing | S7: =TRIM(PROPER(_xlfn.XLOOKUP(Table1[[#This Row],[ProductID_Clean]],Table3[ProductID],Table3[Category],"Missing Value",0))) -> Software | T7: =_xlfn.XLOOKUP(Table1[[#This Row],[CustomerID_Check]],Table2[CustomerID],Table2[CustomerType],"Missing Value",0) -> Standard
A8: TXN-10007 | B8: 45836 | C8: C-1108 | D8: =UPPER(Table1[[#This Row],[ProductID_Clean]]) -> P-SI-005 | E8: P-SI-005 | F8: APAC | G8: =TRIM(Table1[[#This Row],[Region_Clean]]) -> APAC | H8: Sensors & Instruments | I8: Direct | J8: 5 | K8: 980.55 | L8: 1120 | M8: 5600 | N8: 697.25 | O8: 4902.75 | P8: USD | Q8: Frame Agreement | R8: Research & Labs | S8: =TRIM(PROPER(_xlfn.XLOOKUP(Table1[[#This Row],[ProductID_Clean]],Table3[ProductID],Table3[Category],"Missing Value",0))) -> Sensors | T8: =_xlfn.XLOOKUP(Table1[[#This Row],[CustomerID_Check]],Table2[CustomerID],Table2[CustomerType],"Missing Value",0) -> Key Account
A9: TXN-10008 | B9: 45755 | C9: C-1045 | D9: =UPPER(Table1[[#This Row],[ProductID_Clean]]) -> P-SA-005 | E9: P-SA-005 | F9: EMEA | G9: =TRIM(Table1[[#This Row],[Region_Clean]]) -> EMEA | H9: Software & Analytics | I9: Direct | J9: 1 | K9: 2642.28 | L9: 3200 | M9: 3200 | N9: 557.72 | O9: 2642.28 | P9: USD | Q9: Annual License | R9: Process Industries | S9: =TRIM(PROPER(_xlfn.XLOOKUP(Table1[[#This Row],[ProductID_Clean]],Table3[ProductID],Table3[Category],"Missing Value",0))) -> Software / Integration | T9: =_xlfn.XLOOKUP(Table1[[#This Row],[CustomerID_Check]],Table2[CustomerID],Table2[CustomerType],"Missing Value",0) -> Strategic
A10: TXN-10009 | B10: 45659 | C10: C-1169 | D10: =UPPER(Table1[[#This Row],[ProductID_Clean]]) -> P-SI-002 | E10: P-SI-002 | F10: EMEA | G10: =TRIM(Table1[[#This Row],[Region_Clean]]) -> EMEA | H10: Sensors & Instruments | I10: Direct | J10: 12 | K10: 657.51 | L10: 725 | M10: 8700 | N10: 809.88 | O10: 7890.12 | P10: USD | Q10: Spot | R10: Manufacturing | S10: =TRIM(PROPER(_xlfn.XLOOKUP(Table1[[#This Row],[ProductID_Clean]],Table3[ProductID],Table3[Category],"Missing Value",0))) -> Sensors | T10: =_xlfn.XLOOKUP(Table1[[#This Row],[CustomerID_Check]],Table2[CustomerID],Table2[CustomerType],"Missing Value",0) -> Key Account
A11: TXN-10010 | B11: 45734 | C11: C-1145 | D11: =UPPER(Table1[[#This Row],[ProductID_Clean]]) -> P-SA-001 | E11: P-SA-001 | F11: N. AMERICA | G11: =TRIM(Table1[[#This Row],[Region_Clean]]) -> N. AMERICA | H11: Software & Analytics | I11: Direct | J11: 1 | K11: 3363.25 | L11: 4200 | M11: 4200 | N11: 836.75 | O11: 3363.25 | P11: USD | Q11: Annual License | R11: Research & Labs | S11: =TRIM(PROPER(_xlfn.XLOOKUP(Table1[[#This Row],[ProductID_Clean]],Table3[ProductID],Table3[Category],"Missing Value",0))) -> Software | T11: =_xlfn.XLOOKUP(Table1[[#This Row],[CustomerID_Check]],Table2[CustomerID],Table2[CustomerType],"Missing Value",0) -> Strategic
A12: TXN-10011 | B12: 45765 | C12: C-1174 | D12: =UPPER(Table1[[#This Row],[ProductID_Clean]]) -> P-SI-001 | E12: P-SI-001 | F12: N. AMERICA | G12: =TRIM(Table1[[#This Row],[Region_Clean]]) -> N. AMERICA | H12: Sensors & Instruments | I12: Direct | J12: 4 | K12: 417.01 | L12: 485 | M12: 1940 | N12: 271.96 | O12: 1668.04 | P12: USD | Q12: Spot | R12: Process Industries | S12: =TRIM(PROPER(_xlfn.XLOOKUP(Table1[[#This Row],[ProductID_Clean]],Table3[ProductID],Table3[Category],"Missing Value",0))) -> Sensors | T12: =_xlfn.XLOOKUP(Table1[[#This Row],[CustomerID_Check]],Table2[CustomerID],Table2[CustomerType],"Missing Value",0) -> Key Account
A13: TXN-10012 | B13: 45797 | C13: C-1126 | D13: =UPPER(Table1[[#This Row],[ProductID_Clean]]) -> P-SI-004 | E13: P-SI-004 | F13: EMEA | G13: =TRIM(Table1[[#This Row],[Region_Clean]]) -> EMEA | H13: Sensors & Instruments | I13: Partner Portal | J13: 10 | K13: 2036.06 | L13: 2450 | M13: 24500 | N13: 4139.4 | O13: 20360.6 | P13: USD | Q13: Frame Agreement | R13: Energy & Utilities | S13: =TRIM(PROPER(_xlfn.XLOOKUP(Table1[[#This Row],[ProductID_Clean]],Table3[ProductID],Table3[Category],"Missing Value",0))) -> Instruments | T13: =_xlfn.XLOOKUP(Table1[[#This Row],[CustomerID_Check]],Table2[CustomerID],Table2[CustomerType],"Missing Value",0) -> Standard
... A1218: TXN-11292 | B1218: 45766 | C1218: C-1102 | D1218: =UPPER(Table1[[#This Row],[ProductID_Clean]]) -> P-FS-001 | E1218: P-FS-001 | F1218: LATIN AMERICA | G1218: =TRIM(Table1[[#This Row],[Region_Clean]]) -> LATIN AMERICA | H1218: Field Services | I1218: Distributor | J1218: 1 | K1218: 1333.75 | L1218: 1850 | M1218: 1850 | N1218: 516.25 | O1218: 1333.75 | P1218: USD | Q1218: Standard PO | R1218: Manufacturing | S1218: =TRIM(PROPER(_xlfn.XLOOKUP(Table1[[#This Row],[ProductID_Clean]],Table3[ProductID],Table3[Category],"Missing Value",0))) -> Services | T1218: =_xlfn.XLOOKUP(Table1[[#This Row],[CustomerID_Check]],Table2[CustomerID],Table2[CustomerType],"Missing Value",0) -> Emerging
A1219: Total | J1219: =SUBTOTAL(109,Table1[Quantity]) -> 3470 | M1219: =SUBTOTAL(109,Table1[GrossRevenue_Analytical]) -> 4586720 | N1219: =SUBTOTAL(109,Table1[DiscountAmount_Analytical]) -> 672959.56 | O1219: =SUBTOTAL(109,Table1[NetRevenue_Analytical]) -> 3913760.4
M1221: Discount Rate | N1221: =Table1[[#Totals],[DiscountAmount_Analytical]]/Table1[[#Totals],[GrossRevenue_Analytical]] -> 0.14671913
O1222: Business Unit | P1222: Gross Revenue | Q1222: Discount | R1222: Discount Rate (%) | S1222: Net Revenue | T1222: Revenue Contribution (%) | U1222: Quantity
O1223: Sensors & Instruments | P1223: =SUMIF(Table1[BusinessUnit_Clean],Table8[[#This Row],[Business Unit]],Table1[GrossRevenue_Analytical]) -> 2647045 | Q1223: =SUMIF(Table1[BusinessUnit_Clean],Table8[[#This Row],[Business Unit]],Table1[DiscountAmount_Analytical]) -> 387131.82 | R1223: =Table8[[#This Row],[Discount]]/Table8[[#This Row],[Gross Revenue]] -> 0.14625056 | S1223: =SUMIF(Table1[BusinessUnit_Clean],Table8[[#This Row],[Business Unit]],Table1[NetRevenue_Analytical]) -> 2259913.2 | T1223: =Table8[[#This Row],[Net Revenue]]/Table8[[#Totals],[Net Revenue]] -> 0.57532475 | U1223: =SUMIF(Table1[BusinessUnit_Clean],Table8[[#This Row],[Business Unit]],Table1[Quantity]) -> 2922
O1224: Software & Analytics | P1224: =SUMIF(Table1[BusinessUnit_Clean],Table8[[#This Row],[Business Unit]],Table1[GrossRevenue_Analytical]) -> 1511650 | Q1224: =SUMIF(Table1[BusinessUnit_Clean],Table8[[#This Row],[Business Unit]],Table1[DiscountAmount_Analytical]) -> 216870.24 | R1224: =Table8[[#This Row],[Discount]]/Table8[[#This Row],[Gross Revenue]] -> 0.14346591 | S1224: =SUMIF(Table1[BusinessUnit_Clean],Table8[[#This Row],[Business Unit]],Table1[NetRevenue_Analytical]) -> 1294779.8 | T1224: =Table8[[#This Row],[Net Revenue]]/Table8[[#Totals],[Net Revenue]] -> 0.32962277 | U1224: =SUMIF(Table1[BusinessUnit_Clean],Table8[[#This Row],[Business Unit]],Table1[Quantity]) -> 357
O1225: Field Services | P1225: =SUMIF(Table1[BusinessUnit_Clean],Table8[[#This Row],[Business Unit]],Table1[GrossRevenue_Analytical]) -> 444000 | Q1225: =SUMIF(Table1[BusinessUnit_Clean],Table8[[#This Row],[Business Unit]],Table1[DiscountAmount_Analytical]) -> 70627.65 | R1225: =Table8[[#This Row],[Discount]]/Table8[[#This Row],[Gross Revenue]] -> 0.15907128 | S1225: =SUMIF(Table1[BusinessUnit_Clean],Table8[[#This Row],[Business Unit]],Table1[NetRevenue_Analytical]) -> 373372.35 | T1225: =Table8[[#This Row],[Net Revenue]]/Table8[[#Totals],[Net Revenue]] -> 0.095052481 | U1225: =SUMIF(Table1[BusinessUnit_Clean],Table8[[#This Row],[Business Unit]],Table1[Quantity]) -> 204
O1226: Total | P1226: =SUBTOTAL(109,Table8[Gross Revenue]) -> 4602695 | Q1226: =SUBTOTAL(109,Table8[Discount]) -> 674629.71 | S1226: =SUBTOTAL(109,Table8[Net Revenue]) -> 3928065.3 | T1226: =SUBTOTAL(109,Table8[Revenue Contribution (%)]) -> 1 | U1226: =SUBTOTAL(109,Table8[Quantity]) -> 3483
O1228: Business Unit | P1228: Gross Revenue | Q1228: Discount | R1228: Net Revenue | S1228: Net Revenue Contribution % | T1228: Quantity
O1229: Field Services | P1229: 442550 | Q1229: 70491.39 | R1229: =Business_Unit_Valid_Product_Revenue[[#This Row],[Gross Revenue]]-Business_Unit_Valid_Product_Revenue[[#This Row],[Discount]] -> 372058.61 | S1229: =Business_Unit_Valid_Product_Revenue[[#This Row],[Net Revenue]]/Business_Unit_Valid_Product_Revenue[[#Totals],[Net Revenue]] -> 0.095064227 | T1229: 203
O1230: Software & Analytics | P1230: 1505150 | Q1230: 216197.72 | R1230: =Business_Unit_Valid_Product_Revenue[[#This Row],[Gross Revenue]]-Business_Unit_Valid_Product_Revenue[[#This Row],[Discount]] -> 1288952.3 | S1230: =Business_Unit_Valid_Product_Revenue[[#This Row],[Net Revenue]]/Business_Unit_Valid_Product_Revenue[[#Totals],[Net Revenue]] -> 0.32933857 | T1230: 354
O1231: Sensors & Instruments | P1231: 2639020 | Q1231: 386270.45 | R1231: =Business_Unit_Valid_Product_Revenue[[#This Row],[Gross Revenue]]-Business_Unit_Valid_Product_Revenue[[#This Row],[Discount]] -> 2252749.5 | S1231: =Business_Unit_Valid_Product_Revenue[[#This Row],[Net Revenue]]/Business_Unit_Valid_Product_Revenue[[#Totals],[Net Revenue]] -> 0.5755972 | T1231: 2913
O1232: Total | P1232: =SUBTOTAL(109,Business_Unit_Valid_Product_Revenue[Gross Revenue]) -> 4586720 | R1232: =SUBTOTAL(109,Business_Unit_Valid_Product_Revenue[Net Revenue]) -> 3913760.4 | S1232: =SUBTOTAL(109,Business_Unit_Valid_Product_Revenue[Net Revenue Contribution %]) -> 1 | T1232: =SUBTOTAL(109,Business_Unit_Valid_Product_Revenue[Quantity]) -> 3470
O1235: Region | P1235: Gross Revenue | Q1235: Discount | R1235: Discount Rate (%) | S1235: Net Revenue | T1235: Revenue Contribution (%) | U1235: Quantity
O1236: N. AMERICA | P1236: =SUMIF(Table1[RegionClean_],Table9[[#This Row],[Region]],Table1[GrossRevenue_Analytical]) -> 1804200 | Q1236: =SUMIF(Table1[RegionClean_],Table9[[#This Row],[Region]],Table1[DiscountAmount_Analytical]) -> 243296.87 | R1236: =Table9[[#This Row],[Discount]]/Table9[[#This Row],[Gross Revenue]] -> 0.13485028 | S1236: =SUMIF(Table1[RegionClean_],Table9[[#This Row],[Region]],Table1[NetRevenue_Analytical]) -> 1560903.1 | T1236: =Table9[[#This Row],[Net Revenue]]/Table9[[#Totals],[Net Revenue]] -> 0.39737199 | U1236: =SUMIF(Table1[RegionClean_],Table9[[#This Row],[Region]],Table1[Quantity]) -> 1394
O1237: EMEA | P1237: =SUMIF(Table1[RegionClean_],Table9[[#This Row],[Region]],Table1[GrossRevenue_Analytical]) -> 1484225 | Q1237: =SUMIF(Table1[RegionClean_],Table9[[#This Row],[Region]],Table1[DiscountAmount_Analytical]) -> 197909.43 | R1237: =Table9[[#This Row],[Discount]]/Table9[[#This Row],[Gross Revenue]] -> 0.13334193 | S1237: =SUMIF(Table1[RegionClean_],Table9[[#This Row],[Region]],Table1[NetRevenue_Analytical]) -> 1286315.6 | T1237: =Table9[[#This Row],[Net Revenue]]/Table9[[#Totals],[Net Revenue]] -> 0.32746797 | U1237: =SUMIF(Table1[RegionClean_],Table9[[#This Row],[Region]],Table1[Quantity]) -> 1116
F1238: Month | G1238: Gross Revenue | H1238: Discount | I1238: Net Revenue | J1238: Revenue Growth (%) | K1238: Quantity | O1238: APAC | P1238: =SUMIF(Table1[RegionClean_],Table9[[#This Row],[Region]],Table1[GrossRevenue_Analytical]) -> 814715 | Q1238: =SUMIF(Table1[RegionClean_],Table9[[#This Row],[Region]],Table1[DiscountAmount_Analytical]) -> 148525.88 | R1238: =Table9[[#This Row],[Discount]]/Table9[[#This Row],[Gross Revenue]] -> 0.18230409 | S1238: =SUMIF(Table1[RegionClean_],Table9[[#This Row],[Region]],Table1[NetRevenue_Analytical]) -> 666189.12 | T1238: =Table9[[#This Row],[Net Revenue]]/Table9[[#Totals],[Net Revenue]] -> 0.16959726 | U1238: =SUMIF(Table1[RegionClean_],Table9[[#This Row],[Region]],Table1[Quantity]) -> 617
F1239: 45688 | G1239: =SUMIFS(Table1[GrossRevenue_Analytical],Table1[TransactionDate_Clean],">"&EOMONTH(Table12[[#This Row],[Month]],-1),Table1[TransactionDate_Clean],"<="&Table12[[#This Row],[Month]]) -> 644255 | H1239: =SUMIFS(Table1[DiscountAmount_Analytical],Table1[TransactionDate_Clean],">"&EOMONTH(Table12[[#This Row],[Month]],-1),Table1[TransactionDate_Clean],"<="&Table12[[#This Row],[Month]]) -> 101513.06 | I1239: =SUMIFS(Table1[NetRevenue_Analytical],Table1[TransactionDate_Clean],">"&EOMONTH(Table12[[#This Row],[Month]],-1),Table1[TransactionDate_Clean],"<="&Table12[[#This Row],[Month]]) -> 542741.94 | J1239: — | K1239: =SUMIFS(Table1[Quantity],Table1[TransactionDate_Clean],">"&EOMONTH(Table12[[#This Row],[Month]],-1),Table1[TransactionDate_Clean],"<="&Table12[[#This Row],[Month]]) -> 496 | O1239: LATIN AMERICA | P1239: =SUMIF(Table1[RegionClean_],Table9[[#This Row],[Region]],Table1[GrossRevenue_Analytical]) -> 499555 | Q1239: =SUMIF(Table1[RegionClean_],Table9[[#This Row],[Region]],Table1[DiscountAmount_Analytical]) -> 84897.53 | R1239: =Table9[[#This Row],[Discount]]/Table9[[#This Row],[Gross Revenue]] -> 0.16994631 | S1239: =SUMIF(Table1[RegionClean_],Table9[[#This Row],[Region]],Table1[NetRevenue_Analytical]) -> 414657.47 | T1239: =Table9[[#This Row],[Net Revenue]]/Table9[[#Totals],[Net Revenue]] -> 0.10556277 | U1239: =SUMIF(Table1[RegionClean_],Table9[[#This Row],[Region]],Table1[Quantity]) -> 356
F1240: 45716 | G1240: =SUMIFS(Table1[GrossRevenue_Analytical],Table1[TransactionDate_Clean],">"&EOMONTH(Table12[[#This Row],[Month]],-1),Table1[TransactionDate_Clean],"<="&Table12[[#This Row],[Month]]) -> 562320 | H1240: =SUMIFS(Table1[DiscountAmount_Analytical],Table1[TransactionDate_Clean],">"&EOMONTH(Table12[[#This Row],[Month]],-1),Table1[TransactionDate_Clean],"<="&Table12[[#This Row],[Month]]) -> 84533 | I1240: =SUMIFS(Table1[NetRevenue_Analytical],Table1[TransactionDate_Clean],">"&EOMONTH(Table12[[#This Row],[Month]],-1),Table1[TransactionDate_Clean],"<="&Table12[[#This Row],[Month]]) -> 477787 | J1240: =(Table12[[#This Row],[Net Revenue]]-I1239)/I1239 -> -0.11967923 | K1240: =SUMIFS(Table1[Quantity],Table1[TransactionDate_Clean],">"&EOMONTH(Table12[[#This Row],[Month]],-1),Table1[TransactionDate_Clean],"<="&Table12[[#This Row],[Month]]) -> 499 | O1240: Total | P1240: =SUBTOTAL(109,Table9[Gross Revenue]) -> 4602695 | Q1240: =SUBTOTAL(109,Table9[Discount]) -> 674629.71 | S1240: =SUBTOTAL(109,Table9[Net Revenue]) -> 3928065.3 | T1240: =SUBTOTAL(109,Table9[Revenue Contribution (%)]) -> 1 | U1240: =SUBTOTAL(109,Table9[Quantity]) -> 3483
F1241: 45747 | G1241: =SUMIFS(Table1[GrossRevenue_Analytical],Table1[TransactionDate_Clean],">"&EOMONTH(Table12[[#This Row],[Month]],-1),Table1[TransactionDate_Clean],"<="&Table12[[#This Row],[Month]]) -> 688795 | H1241: =SUMIFS(Table1[DiscountAmount_Analytical],Table1[TransactionDate_Clean],">"&EOMONTH(Table12[[#This Row],[Month]],-1),Table1[TransactionDate_Clean],"<="&Table12[[#This Row],[Month]]) -> 94640.99 | I1241: =SUMIFS(Table1[NetRevenue_Analytical],Table1[TransactionDate_Clean],">"&EOMONTH(Table12[[#This Row],[Month]],-1),Table1[TransactionDate_Clean],"<="&Table12[[#This Row],[Month]]) -> 594154.01 | J1241: =(Table12[[#This Row],[Net Revenue]]-I1240)/I1240 -> 0.24355416 | K1241: =SUMIFS(Table1[Quantity],Table1[TransactionDate_Clean],">"&EOMONTH(Table12[[#This Row],[Month]],-1),Table1[TransactionDate_Clean],"<="&Table12[[#This Row],[Month]]) -> 581
F1242: 45777 | G1242: =SUMIFS(Table1[GrossRevenue_Analytical],Table1[TransactionDate_Clean],">"&EOMONTH(Table12[[#This Row],[Month]],-1),Table1[TransactionDate_Clean],"<="&Table12[[#This Row],[Month]]) -> 847870 | H1242: =SUMIFS(Table1[DiscountAmount_Analytical],Table1[TransactionDate_Clean],">"&EOMONTH(Table12[[#This Row],[Month]],-1),Table1[TransactionDate_Clean],"<="&Table12[[#This Row],[Month]]) -> 115587.19 | I1242: =SUMIFS(Table1[NetRevenue_Analytical],Table1[TransactionDate_Clean],">"&EOMONTH(Table12[[#This Row],[Month]],-1),Table1[TransactionDate_Clean],"<="&Table12[[#This Row],[Month]]) -> 732282.81 | J1242: =(Table12[[#This Row],[Net Revenue]]-I1241)/I1241 -> 0.23247979 | K1242: =SUMIFS(Table1[Quantity],Table1[TransactionDate_Clean],">"&EOMONTH(Table12[[#This Row],[Month]],-1),Table1[TransactionDate_Clean],"<="&Table12[[#This Row],[Month]]) -> 645 | O1242: Region | P1242: Column1 | Q1242: Gross Revenue | R1242: Discount | S1242: Net Revenue | T1242: Net Contribution | U1242: Quantity
F1243: 45808 | G1243: =SUMIFS(Table1[GrossRevenue_Analytical],Table1[TransactionDate_Clean],">"&EOMONTH(Table12[[#This Row],[Month]],-1),Table1[TransactionDate_Clean],"<="&Table12[[#This Row],[Month]]) -> 882260 | H1243: =SUMIFS(Table1[DiscountAmount_Analytical],Table1[TransactionDate_Clean],">"&EOMONTH(Table12[[#This Row],[Month]],-1),Table1[TransactionDate_Clean],"<="&Table12[[#This Row],[Month]]) -> 132063.05 | I1243: =SUMIFS(Table1[NetRevenue_Analytical],Table1[TransactionDate_Clean],">"&EOMONTH(Table12[[#This Row],[Month]],-1),Table1[TransactionDate_Clean],"<="&Table12[[#This Row],[Month]]) -> 750196.95 | J1243: =(Table12[[#This Row],[Net Revenue]]-I1242)/I1242 -> 0.024463417 | K1243: =SUMIFS(Table1[Quantity],Table1[TransactionDate_Clean],">"&EOMONTH(Table12[[#This Row],[Month]],-1),Table1[TransactionDate_Clean],"<="&Table12[[#This Row],[Month]]) -> 590 | O1243: N. AMERICA | Q1243: 1800120 | R1243: 242814.14 | S1243: =Invalid_ProductID_Exclusion[[#This Row],[Gross Revenue]]-Invalid_ProductID_Exclusion[[#This Row],[Discount]] -> 1557305.9 | T1243: =Invalid_ProductID_Exclusion[[#This Row],[Net Revenue]]/Invalid_ProductID_Exclusion[[#Totals],[Net Revenue]] -> 0.39790526 | U1243: 1391
F1244: 45838 | G1244: =SUMIFS(Table1[GrossRevenue_Analytical],Table1[TransactionDate_Clean],">"&EOMONTH(Table12[[#This Row],[Month]],-1),Table1[TransactionDate_Clean],"<="&Table12[[#This Row],[Month]]) -> 977195 | H1244: =SUMIFS(Table1[DiscountAmount_Analytical],Table1[TransactionDate_Clean],">"&EOMONTH(Table12[[#This Row],[Month]],-1),Table1[TransactionDate_Clean],"<="&Table12[[#This Row],[Month]]) -> 146292.42 | I1244: =SUMIFS(Table1[NetRevenue_Analytical],Table1[TransactionDate_Clean],">"&EOMONTH(Table12[[#This Row],[Month]],-1),Table1[TransactionDate_Clean],"<="&Table12[[#This Row],[Month]]) -> 830902.58 | J1244: =(Table12[[#This Row],[Net Revenue]]-I1243)/I1243 -> 0.10757926 | K1244: =SUMIFS(Table1[Quantity],Table1[TransactionDate_Clean],">"&EOMONTH(Table12[[#This Row],[Month]],-1),Table1[TransactionDate_Clean],"<="&Table12[[#This Row],[Month]]) -> 672 | O1244: EMEA | Q1244: 1474750 | R1244: 197046.59 | S1244: =Invalid_ProductID_Exclusion[[#This Row],[Gross Revenue]]-Invalid_ProductID_Exclusion[[#This Row],[Discount]] -> 1277703.4 | T1244: =Invalid_ProductID_Exclusion[[#This Row],[Net Revenue]]/Invalid_ProductID_Exclusion[[#Totals],[Net Revenue]] -> 0.32646439 | U1244: 1110
F1245: Total | G1245: =SUBTOTAL(109,Table12[Gross Revenue]) -> 4602695 | H1245: =SUBTOTAL(109,Table12[Discount]) -> 674629.71 | I1245: =SUBTOTAL(109,Table12[Net Revenue]) -> 3928065.3 | K1245: =SUBTOTAL(109,Table12[Quantity]) -> 3483 | O1245: APAC | Q1245: 812295 | R1245: 148201.3 | S1245: =Invalid_ProductID_Exclusion[[#This Row],[Gross Revenue]]-Invalid_ProductID_Exclusion[[#This Row],[Discount]] -> 664093.7 | T1245: =Invalid_ProductID_Exclusion[[#This Row],[Net Revenue]]/Invalid_ProductID_Exclusion[[#Totals],[Net Revenue]] -> 0.16968174 | U1245: 613
O1246: LATIN AMERICA | Q1246: 499555 | R1246: 84897.53 | S1246: =Invalid_ProductID_Exclusion[[#This Row],[Gross Revenue]]-Invalid_ProductID_Exclusion[[#This Row],[Discount]] -> 414657.47 | T1246: =Invalid_ProductID_Exclusion[[#This Row],[Net Revenue]]/Invalid_ProductID_Exclusion[[#Totals],[Net Revenue]] -> 0.10594861 | U1246: 356
O1247: Total | Q1247: =SUBTOTAL(109,Invalid_ProductID_Exclusion[Gross Revenue]) -> 4586720 | R1247: =SUBTOTAL(109,Invalid_ProductID_Exclusion[Discount]) -> 672959.56 | S1247: =SUBTOTAL(109,Invalid_ProductID_Exclusion[Net Revenue]) -> 3913760.4 | T1247: =SUBTOTAL(109,Invalid_ProductID_Exclusion[Net Contribution]) -> 1 | U1247: =SUBTOTAL(109,Invalid_ProductID_Exclusion[Quantity]) -> 3470
O1249: Product Category | P1249: Gross Revenue | Q1249: Discount | R1249: Discount Rate % | S1249: Net Revenue | T1249: Net Revenue Contribution % | U1249: Quantity
O1250: Services | P1250: 442550 | Q1250: 70491.39 | R1250: =Product_Category_Valid_Product_Revenue[[#This Row],[Discount]]/Product_Category_Valid_Product_Revenue[[#This Row],[Gross Revenue]] -> 0.15928458 | S1250: =Product_Category_Valid_Product_Revenue[[#This Row],[Gross Revenue]]-Product_Category_Valid_Product_Revenue[[#This Row],[Discount]] -> 372058.61 | T1250: =Product_Category_Valid_Product_Revenue[[#This Row],[Net Revenue]]/Product_Category_Valid_Product_Revenue[[#Totals],[Net Revenue]] -> 0.095064227 | U1250: 203
O1251: Software | P1251: 1341950 | Q1251: 192895.8 | R1251: =Product_Category_Valid_Product_Revenue[[#This Row],[Discount]]/Product_Category_Valid_Product_Revenue[[#This Row],[Gross Revenue]] -> 0.14374291 | S1251: =Product_Category_Valid_Product_Revenue[[#This Row],[Gross Revenue]]-Product_Category_Valid_Product_Revenue[[#This Row],[Discount]] -> 1149054.2 | T1251: =Product_Category_Valid_Product_Revenue[[#This Row],[Net Revenue]]/Product_Category_Valid_Product_Revenue[[#Totals],[Net Revenue]] -> 0.29359339 | U1251: 303
O1252: Software / Integration | P1252: 163200 | Q1252: 23301.92 | R1252: =Product_Category_Valid_Product_Revenue[[#This Row],[Discount]]/Product_Category_Valid_Product_Revenue[[#This Row],[Gross Revenue]] -> 0.14278137 | S1252: =Product_Category_Valid_Product_Revenue[[#This Row],[Gross Revenue]]-Product_Category_Valid_Product_Revenue[[#This Row],[Discount]] -> 139898.08 | T1252: =Product_Category_Valid_Product_Revenue[[#This Row],[Net Revenue]]/Product_Category_Valid_Product_Revenue[[#Totals],[Net Revenue]] -> 0.035745182 | U1252: 51
O1253: Sensors | P1253: 1339150 | Q1253: 203632.17 | R1253: =Product_Category_Valid_Product_Revenue[[#This Row],[Discount]]/Product_Category_Valid_Product_Revenue[[#This Row],[Gross Revenue]] -> 0.15206076 | S1253: =Product_Category_Valid_Product_Revenue[[#This Row],[Gross Revenue]]-Product_Category_Valid_Product_Revenue[[#This Row],[Discount]] -> 1135517.8 | T1253: =Product_Category_Valid_Product_Revenue[[#This Row],[Net Revenue]]/Product_Category_Valid_Product_Revenue[[#Totals],[Net Revenue]] -> 0.29013473 | U1253: 2146
O1254: Instruments | P1254: 1299870 | Q1254: 182638.28 | R1254: =Product_Category_Valid_Product_Revenue[[#This Row],[Discount]]/Product_Category_Valid_Product_Revenue[[#This Row],[Gross Revenue]] -> 0.14050504 | S1254: =Product_Category_Valid_Product_Revenue[[#This Row],[Gross Revenue]]-Product_Category_Valid_Product_Revenue[[#This Row],[Discount]] -> 1117231.7 | T1254: =Product_Category_Valid_Product_Revenue[[#This Row],[Net Revenue]]/Product_Category_Valid_Product_Revenue[[#Totals],[Net Revenue]] -> 0.28546247 | U1254: 767
P1255: =SUBTOTAL(109,Product_Category_Valid_Product_Revenue[Gross Revenue]) -> 4586720 | Q1255: =SUBTOTAL(109,Product_Category_Valid_Product_Revenue[Discount]) -> 672959.56 | S1255: =SUBTOTAL(109,Product_Category_Valid_Product_Revenue[Net Revenue]) -> 3913760.4 | T1255: =SUBTOTAL(109,Product_Category_Valid_Product_Revenue[Net Revenue Contribution %]) -> 1 | U1255: =SUBTOTAL(109,Product_Category_Valid_Product_Revenue[Quantity]) -> 3470
O1260: Customer Segment | P1260: Gross Revenue | Q1260: Discount | R1260: Discount Rate (%) | S1260: Net Revenue | T1260: Revenue Contribution (%) | U1260: Quantity
O1261: Research & Labs | P1261: =SUMIF(Table1[CustomerSegment],Table10[[#This Row],[Customer Segment]],Table1[GrossRevenue_Analytical]) -> 701995 | Q1261: =SUMIF(Table1[CustomerSegment],Table10[[#This Row],[Customer Segment]],Table1[DiscountAmount_Analytical]) -> 84447.32 | R1261: =Table10[[#This Row],[Discount]]/Table10[[#This Row],[Gross Revenue]] -> 0.12029618 | S1261: =SUMIF(Table1[CustomerSegment],Table10[[#This Row],[Customer Segment]],Table1[NetRevenue_Analytical]) -> 617547.68 | T1261: =Table10[[#This Row],[Net Revenue]]/Table10[[#Totals],[Net Revenue]] -> 0.15721421 | U1261: =SUMIF(Table1[CustomerSegment],Table10[[#This Row],[Customer Segment]],Table1[Quantity]) -> 524
O1262: Manufacturing | P1262: =SUMIF(Table1[CustomerSegment],Table10[[#This Row],[Customer Segment]],Table1[GrossRevenue_Analytical]) -> 1432890 | Q1262: =SUMIF(Table1[CustomerSegment],Table10[[#This Row],[Customer Segment]],Table1[DiscountAmount_Analytical]) -> 206639.23 | R1262: =Table10[[#This Row],[Discount]]/Table10[[#This Row],[Gross Revenue]] -> 0.14421151 | S1262: =SUMIF(Table1[CustomerSegment],Table10[[#This Row],[Customer Segment]],Table1[NetRevenue_Analytical]) -> 1226250.8 | T1262: =Table10[[#This Row],[Net Revenue]]/Table10[[#Totals],[Net Revenue]] -> 0.31217678 | U1262: =SUMIF(Table1[CustomerSegment],Table10[[#This Row],[Customer Segment]],Table1[Quantity]) -> 1105
F1263: ProductID | G1263: Gross Revenue | H1263: Discount | I1263: Discount Rate (%) | J1263: Net Revenue | K1263: Revenue Contribution (%) | L1263: Quantity | O1263: Energy & Utilities | P1263: =SUMIF(Table1[CustomerSegment],Table10[[#This Row],[Customer Segment]],Table1[GrossRevenue_Analytical]) -> 970620 | Q1263: =SUMIF(Table1[CustomerSegment],Table10[[#This Row],[Customer Segment]],Table1[DiscountAmount_Analytical]) -> 161872.59 | R1263: =Table10[[#This Row],[Discount]]/Table10[[#This Row],[Gross Revenue]] -> 0.16677236 | S1263: =SUMIF(Table1[CustomerSegment],Table10[[#This Row],[Customer Segment]],Table1[NetRevenue_Analytical]) -> 808747.41 | T1263: =Table10[[#This Row],[Net Revenue]]/Table10[[#Totals],[Net Revenue]] -> 0.2058895 | U1263: =SUMIF(Table1[CustomerSegment],Table10[[#This Row],[Customer Segment]],Table1[Quantity]) -> 710
F1264: P-FS-001 | G1264: =SUMIF(Table1[ProductID_Clean],Table14[[#This Row],[ProductID]],Table1[GrossRevenue_Analytical]) -> 92500 | H1264: =SUMIF(Table1[ProductID_Clean],Table14[[#This Row],[ProductID]],Table1[DiscountAmount_Analytical]) -> 20879.16 | I1264: =Table14[[#This Row],[Discount]]/Table14[[#This Row],[Gross Revenue]] -> 0.22572065 | J1264: =SUMIF(Table1[ProductID_Clean],Table14[[#This Row],[ProductID]],Table1[NetRevenue_Analytical]) -> 71620.84 | K1264: =Table14[[#This Row],[Net Revenue]]/Table14[[#Totals],[Net Revenue]] -> 0.018299751 | L1264: =SUMIF(Table1[ProductID_Clean],Table14[[#This Row],[ProductID]],Table1[Quantity]) -> 50 | O1264: Aerospace & Defense | P1264: =SUMIF(Table1[CustomerSegment],Table10[[#This Row],[Customer Segment]],Table1[GrossRevenue_Analytical]) -> 725270 | Q1264: =SUMIF(Table1[CustomerSegment],Table10[[#This Row],[Customer Segment]],Table1[DiscountAmount_Analytical]) -> 117086.82 | R1264: =Table10[[#This Row],[Discount]]/Table10[[#This Row],[Gross Revenue]] -> 0.16143894 | S1264: =SUMIF(Table1[CustomerSegment],Table10[[#This Row],[Customer Segment]],Table1[NetRevenue_Analytical]) -> 608183.18 | T1264: =Table10[[#This Row],[Net Revenue]]/Table10[[#Totals],[Net Revenue]] -> 0.15483021 | U1264: =SUMIF(Table1[CustomerSegment],Table10[[#This Row],[Customer Segment]],Table1[Quantity]) -> 574
F1265: P-FS-002 | G1265: =SUMIF(Table1[ProductID_Clean],Table14[[#This Row],[ProductID]],Table1[GrossRevenue_Analytical]) -> 122400 | H1265: =SUMIF(Table1[ProductID_Clean],Table14[[#This Row],[ProductID]],Table1[DiscountAmount_Analytical]) -> 17486.96 | I1265: =Table14[[#This Row],[Discount]]/Table14[[#This Row],[Gross Revenue]] -> 0.14286732 | J1265: =SUMIF(Table1[ProductID_Clean],Table14[[#This Row],[ProductID]],Table1[NetRevenue_Analytical]) -> 104913.04 | K1265: =Table14[[#This Row],[Net Revenue]]/Table14[[#Totals],[Net Revenue]] -> 0.026806199 | L1265: =SUMIF(Table1[ProductID_Clean],Table14[[#This Row],[ProductID]],Table1[Quantity]) -> 51 | O1265: Process Industries | P1265: =SUMIF(Table1[CustomerSegment],Table10[[#This Row],[Customer Segment]],Table1[GrossRevenue_Analytical]) -> 771920 | Q1265: =SUMIF(Table1[CustomerSegment],Table10[[#This Row],[Customer Segment]],Table1[DiscountAmount_Analytical]) -> 104583.75 | R1265: =Table10[[#This Row],[Discount]]/Table10[[#This Row],[Gross Revenue]] -> 0.13548522 | S1265: =SUMIF(Table1[CustomerSegment],Table10[[#This Row],[Customer Segment]],Table1[NetRevenue_Analytical]) -> 667336.25 | T1265: =Table10[[#This Row],[Net Revenue]]/Table10[[#Totals],[Net Revenue]] -> 0.1698893 | U1265: =SUMIF(Table1[CustomerSegment],Table10[[#This Row],[Customer Segment]],Table1[Quantity]) -> 570
F1266: P-FS-003 | G1266: =SUMIF(Table1[ProductID_Clean],Table14[[#This Row],[ProductID]],Table1[GrossRevenue_Analytical]) -> 102500 | H1266: =SUMIF(Table1[ProductID_Clean],Table14[[#This Row],[ProductID]],Table1[DiscountAmount_Analytical]) -> 13917.66 | I1266: =Table14[[#This Row],[Discount]]/Table14[[#This Row],[Gross Revenue]] -> 0.13578205 | J1266: =SUMIF(Table1[ProductID_Clean],Table14[[#This Row],[ProductID]],Table1[NetRevenue_Analytical]) -> 88582.34 | K1266: =Table14[[#This Row],[Net Revenue]]/Table14[[#Totals],[Net Revenue]] -> 0.022633562 | L1266: =SUMIF(Table1[ProductID_Clean],Table14[[#This Row],[ProductID]],Table1[Quantity]) -> 25 | O1266: Total | P1266: =SUBTOTAL(109,Table10[Gross Revenue]) -> 4602695 | Q1266: =SUBTOTAL(109,Table10[Discount]) -> 674629.71 | S1266: =SUBTOTAL(109,Table10[Net Revenue]) -> 3928065.3 | T1266: =SUBTOTAL(109,Table10[Revenue Contribution (%)]) -> 1 | U1266: =SUBTOTAL(109,Table10[Quantity]) -> 3483
F1267: P-FS-004 | G1267: =SUMIF(Table1[ProductID_Clean],Table14[[#This Row],[ProductID]],Table1[GrossRevenue_Analytical]) -> 51200 | H1267: =SUMIF(Table1[ProductID_Clean],Table14[[#This Row],[ProductID]],Table1[DiscountAmount_Analytical]) -> 5532.36 | I1267: =Table14[[#This Row],[Discount]]/Table14[[#This Row],[Gross Revenue]] -> 0.10805391 | J1267: =SUMIF(Table1[ProductID_Clean],Table14[[#This Row],[ProductID]],Table1[NetRevenue_Analytical]) -> 45667.64 | K1267: =Table14[[#This Row],[Net Revenue]]/Table14[[#Totals],[Net Revenue]] -> 0.011668481 | L1267: =SUMIF(Table1[ProductID_Clean],Table14[[#This Row],[ProductID]],Table1[Quantity]) -> 16
F1268: P-FS-005 | G1268: =SUMIF(Table1[ProductID_Clean],Table14[[#This Row],[ProductID]],Table1[GrossRevenue_Analytical]) -> 27550 | H1268: =SUMIF(Table1[ProductID_Clean],Table14[[#This Row],[ProductID]],Table1[DiscountAmount_Analytical]) -> 6112.89 | I1268: =Table14[[#This Row],[Discount]]/Table14[[#This Row],[Gross Revenue]] -> 0.22188348 | J1268: =SUMIF(Table1[ProductID_Clean],Table14[[#This Row],[ProductID]],Table1[NetRevenue_Analytical]) -> 21437.11 | K1268: =Table14[[#This Row],[Net Revenue]]/Table14[[#Totals],[Net Revenue]] -> 0.005477369 | L1268: =SUMIF(Table1[ProductID_Clean],Table14[[#This Row],[ProductID]],Table1[Quantity]) -> 29 | O1268: Product Category | P1268: Gross Revenue | Q1268: Discount | R1268: Discount Rate (%) | S1268: Net Revenue | T1268: Revenue Contribution (%) | U1268: Quantity
F1269: P-FS-006 | G1269: =SUMIF(Table1[ProductID_Clean],Table14[[#This Row],[ProductID]],Table1[GrossRevenue_Analytical]) -> 46400 | H1269: =SUMIF(Table1[ProductID_Clean],Table14[[#This Row],[ProductID]],Table1[DiscountAmount_Analytical]) -> 6562.36 | I1269: =Table14[[#This Row],[Discount]]/Table14[[#This Row],[Gross Revenue]] -> 0.14143017 | J1269: =SUMIF(Table1[ProductID_Clean],Table14[[#This Row],[ProductID]],Table1[NetRevenue_Analytical]) -> 39837.64 | K1269: =Table14[[#This Row],[Net Revenue]]/Table14[[#Totals],[Net Revenue]] -> 0.010178865 | L1269: =SUMIF(Table1[ProductID_Clean],Table14[[#This Row],[ProductID]],Table1[Quantity]) -> 32 | O1269: Services | P1269: =SUMIF(Table1[ProductCategory],Table11[[#This Row],[Product Category]],Table1[GrossRevenue_Analytical]) -> 442550 | Q1269: =SUMIF(Table1[ProductCategory],Table11[[#This Row],[Product Category]],Table1[DiscountAmount_Analytical]) -> 70491.39 | R1269: =Table11[[#This Row],[Discount]]/Table11[[#This Row],[Gross Revenue]] -> 0.15928458 | S1269: =SUMIF(Table1[ProductCategory],Table11[[#This Row],[Product Category]],Table1[NetRevenue_Analytical]) -> 372058.61 | T1269: =Table11[[#This Row],[Net Revenue]]/Table11[[#Totals],[Net Revenue]] -> 0.095064227 | U1269: =SUMIF(Table1[ProductCategory],Table11[[#This Row],[Product Category]],Table1[Quantity]) -> 203
F1270: P-SA-001 | G1270: =SUMIF(Table1[ProductID_Clean],Table14[[#This Row],[ProductID]],Table1[GrossRevenue_Analytical]) -> 516600 | H1270: =SUMIF(Table1[ProductID_Clean],Table14[[#This Row],[ProductID]],Table1[DiscountAmount_Analytical]) -> 76660.72 | I1270: =Table14[[#This Row],[Discount]]/Table14[[#This Row],[Gross Revenue]] -> 0.14839473 | J1270: =SUMIF(Table1[ProductID_Clean],Table14[[#This Row],[ProductID]],Table1[NetRevenue_Analytical]) -> 439939.28 | K1270: =Table14[[#This Row],[Net Revenue]]/Table14[[#Totals],[Net Revenue]] -> 0.11240833 | L1270: =SUMIF(Table1[ProductID_Clean],Table14[[#This Row],[ProductID]],Table1[Quantity]) -> 123 | O1270: Software | P1270: =SUMIF(Table1[ProductCategory],Table11[[#This Row],[Product Category]],Table1[GrossRevenue_Analytical]) -> 1341950 | Q1270: =SUMIF(Table1[ProductCategory],Table11[[#This Row],[Product Category]],Table1[DiscountAmount_Analytical]) -> 192895.8 | R1270: =Table11[[#This Row],[Discount]]/Table11[[#This Row],[Gross Revenue]] -> 0.14374291 | S1270: =SUMIF(Table1[ProductCategory],Table11[[#This Row],[Product Category]],Table1[NetRevenue_Analytical]) -> 1149054.2 | T1270: =Table11[[#This Row],[Net Revenue]]/Table11[[#Totals],[Net Revenue]] -> 0.29359339 | U1270: =SUMIF(Table1[ProductCategory],Table11[[#This Row],[Product Category]],Table1[Quantity]) -> 303
F1271: P-SA-002 | G1271: =SUMIF(Table1[ProductID_Clean],Table14[[#This Row],[ProductID]],Table1[GrossRevenue_Analytical]) -> 558600 | H1271: =SUMIF(Table1[ProductID_Clean],Table14[[#This Row],[ProductID]],Table1[DiscountAmount_Analytical]) -> 79033.28 | I1271: =Table14[[#This Row],[Discount]]/Table14[[#This Row],[Gross Revenue]] -> 0.14148457 | J1271: =SUMIF(Table1[ProductID_Clean],Table14[[#This Row],[ProductID]],Table1[NetRevenue_Analytical]) -> 479566.72 | K1271: =Table14[[#This Row],[Net Revenue]]/Table14[[#Totals],[Net Revenue]] -> 0.12253349 | L1271: =SUMIF(Table1[ProductID_Clean],Table14[[#This Row],[ProductID]],Table1[Quantity]) -> 57 | O1271: Software / Integration | P1271: =SUMIF(Table1[ProductCategory],Table11[[#This Row],[Product Category]],Table1[GrossRevenue_Analytical]) -> 163200 | Q1271: =SUMIF(Table1[ProductCategory],Table11[[#This Row],[Product Category]],Table1[DiscountAmount_Analytical]) -> 23301.92 | R1271: =Table11[[#This Row],[Discount]]/Table11[[#This Row],[Gross Revenue]] -> 0.14278137 | S1271: =SUMIF(Table1[ProductCategory],Table11[[#This Row],[Product Category]],Table1[NetRevenue_Analytical]) -> 139898.08 | T1271: =Table11[[#This Row],[Net Revenue]]/Table11[[#Totals],[Net Revenue]] -> 0.035745182 | U1271: =SUMIF(Table1[ProductCategory],Table11[[#This Row],[Product Category]],Table1[Quantity]) -> 51
F1272: P-SA-003 | G1272: =SUMIF(Table1[ProductID_Clean],Table14[[#This Row],[ProductID]],Table1[GrossRevenue_Analytical]) -> 159500 | H1272: =SUMIF(Table1[ProductID_Clean],Table14[[#This Row],[ProductID]],Table1[DiscountAmount_Analytical]) -> 22693.86 | I1272: =Table14[[#This Row],[Discount]]/Table14[[#This Row],[Gross Revenue]] -> 0.14228125 | J1272: =SUMIF(Table1[ProductID_Clean],Table14[[#This Row],[ProductID]],Table1[NetRevenue_Analytical]) -> 136806.14 | K1272: =Table14[[#This Row],[Net Revenue]]/Table14[[#Totals],[Net Revenue]] -> 0.034955165 | L1272: =SUMIF(Table1[ProductID_Clean],Table14[[#This Row],[ProductID]],Table1[Quantity]) -> 58 | O1272: Sensors | P1272: =SUMIF(Table1[ProductCategory],Table11[[#This Row],[Product Category]],Table1[GrossRevenue_Analytical]) -> 1339150 | Q1272: =SUMIF(Table1[ProductCategory],Table11[[#This Row],[Product Category]],Table1[DiscountAmount_Analytical]) -> 203632.17 | R1272: =Table11[[#This Row],[Discount]]/Table11[[#This Row],[Gross Revenue]] -> 0.15206076 | S1272: =SUMIF(Table1[ProductCategory],Table11[[#This Row],[Product Category]],Table1[NetRevenue_Analytical]) -> 1135517.8 | T1272: =Table11[[#This Row],[Net Revenue]]/Table11[[#Totals],[Net Revenue]] -> 0.29013473 | U1272: =SUMIF(Table1[ProductCategory],Table11[[#This Row],[Product Category]],Table1[Quantity]) -> 2146
F1273: P-SA-004 | G1273: =SUMIF(Table1[ProductID_Clean],Table14[[#This Row],[ProductID]],Table1[GrossRevenue_Analytical]) -> 107250 | H1273: =SUMIF(Table1[ProductID_Clean],Table14[[#This Row],[ProductID]],Table1[DiscountAmount_Analytical]) -> 14507.94 | I1273: =Table14[[#This Row],[Discount]]/Table14[[#This Row],[Gross Revenue]] -> 0.13527217 | J1273: =SUMIF(Table1[ProductID_Clean],Table14[[#This Row],[ProductID]],Table1[NetRevenue_Analytical]) -> 92742.06 | K1273: =Table14[[#This Row],[Net Revenue]]/Table14[[#Totals],[Net Revenue]] -> 0.023696407 | L1273: =SUMIF(Table1[ProductID_Clean],Table14[[#This Row],[ProductID]],Table1[Quantity]) -> 65 | O1273: Instruments | P1273: =SUMIF(Table1[ProductCategory],Table11[[#This Row],[Product Category]],Table1[GrossRevenue_Analytical]) -> 1299870 | Q1273: =SUMIF(Table1[ProductCategory],Table11[[#This Row],[Product Category]],Table1[DiscountAmount_Analytical]) -> 182638.28 | R1273: =Table11[[#This Row],[Discount]]/Table11[[#This Row],[Gross Revenue]] -> 0.14050504 | S1273: =SUMIF(Table1[ProductCategory],Table11[[#This Row],[Product Category]],Table1[NetRevenue_Analytical]) -> 1117231.7 | T1273: =Table11[[#This Row],[Net Revenue]]/Table11[[#Totals],[Net Revenue]] -> 0.28546247 | U1273: =SUMIF(Table1[ProductCategory],Table11[[#This Row],[Product Category]],Table1[Quantity]) -> 767
F1274: P-SA-005 | G1274: =SUMIF(Table1[ProductID_Clean],Table14[[#This Row],[ProductID]],Table1[GrossRevenue_Analytical]) -> 163200 | H1274: =SUMIF(Table1[ProductID_Clean],Table14[[#This Row],[ProductID]],Table1[DiscountAmount_Analytical]) -> 23301.92 | I1274: =Table14[[#This Row],[Discount]]/Table14[[#This Row],[Gross Revenue]] -> 0.14278137 | J1274: =SUMIF(Table1[ProductID_Clean],Table14[[#This Row],[ProductID]],Table1[NetRevenue_Analytical]) -> 139898.08 | K1274: =Table14[[#This Row],[Net Revenue]]/Table14[[#Totals],[Net Revenue]] -> 0.035745182 | L1274: =SUMIF(Table1[ProductID_Clean],Table14[[#This Row],[ProductID]],Table1[Quantity]) -> 51 | O1274: Total | P1274: =SUBTOTAL(109,Table11[Gross Revenue]) -> 4586720 | Q1274: =SUBTOTAL(109,Table11[Discount]) -> 672959.56 | S1274: =SUBTOTAL(109,Table11[Net Revenue]) -> 3913760.4 | T1274: =SUBTOTAL(109,Table11[Revenue Contribution (%)]) -> 1 | U1274: =SUBTOTAL(109,Table11[Quantity]) -> 3470
F1275: P-SI-001 | G1275: =SUMIF(Table1[ProductID_Clean],Table14[[#This Row],[ProductID]],Table1[GrossRevenue_Analytical]) -> 296820 | H1275: =SUMIF(Table1[ProductID_Clean],Table14[[#This Row],[ProductID]],Table1[DiscountAmount_Analytical]) -> 38077.41 | I1275: =Table14[[#This Row],[Discount]]/Table14[[#This Row],[Gross Revenue]] -> 0.12828452 | J1275: =SUMIF(Table1[ProductID_Clean],Table14[[#This Row],[ProductID]],Table1[NetRevenue_Analytical]) -> 258742.59 | K1275: =Table14[[#This Row],[Net Revenue]]/Table14[[#Totals],[Net Revenue]] -> 0.066110993 | L1275: =SUMIF(Table1[ProductID_Clean],Table14[[#This Row],[ProductID]],Table1[Quantity]) -> 612 | O1275: Missing Value | T1275: —
F1276: P-SI-002 | G1276: =SUMIF(Table1[ProductID_Clean],Table14[[#This Row],[ProductID]],Table1[GrossRevenue_Analytical]) -> 287100 | H1276: =SUMIF(Table1[ProductID_Clean],Table14[[#This Row],[ProductID]],Table1[DiscountAmount_Analytical]) -> 44204.91 | I1276: =Table14[[#This Row],[Discount]]/Table14[[#This Row],[Gross Revenue]] -> 0.15397043 | J1276: =SUMIF(Table1[ProductID_Clean],Table14[[#This Row],[ProductID]],Table1[NetRevenue_Analytical]) -> 242895.09 | K1276: =Table14[[#This Row],[Net Revenue]]/Table14[[#Totals],[Net Revenue]] -> 0.062061818 | L1276: =SUMIF(Table1[ProductID_Clean],Table14[[#This Row],[ProductID]],Table1[Quantity]) -> 396
F1277: P-SI-003 | G1277: =SUMIF(Table1[ProductID_Clean],Table14[[#This Row],[ProductID]],Table1[GrossRevenue_Analytical]) -> 497070 | H1277: =SUMIF(Table1[ProductID_Clean],Table14[[#This Row],[ProductID]],Table1[DiscountAmount_Analytical]) -> 75434.02 | I1277: =Table14[[#This Row],[Discount]]/Table14[[#This Row],[Gross Revenue]] -> 0.15175734 | J1277: =SUMIF(Table1[ProductID_Clean],Table14[[#This Row],[ProductID]],Table1[NetRevenue_Analytical]) -> 421635.98 | K1277: =Table14[[#This Row],[Net Revenue]]/Table14[[#Totals],[Net Revenue]] -> 0.10773168 | L1277: =SUMIF(Table1[ProductID_Clean],Table14[[#This Row],[ProductID]],Table1[Quantity]) -> 263 | O1277: Customer Type | P1277: Gross Revenue | Q1277: Discount | R1277: Discount Rate (%) | S1277: Net Revenue | T1277: Revenue Contribution (%) | U1277: Quantity
F1278: P-SI-004 | G1278: =SUMIF(Table1[ProductID_Clean],Table14[[#This Row],[ProductID]],Table1[GrossRevenue_Analytical]) -> 529200 | H1278: =SUMIF(Table1[ProductID_Clean],Table14[[#This Row],[ProductID]],Table1[DiscountAmount_Analytical]) -> 75841.3 | I1278: =Table14[[#This Row],[Discount]]/Table14[[#This Row],[Gross Revenue]] -> 0.14331311 | J1278: =SUMIF(Table1[ProductID_Clean],Table14[[#This Row],[ProductID]],Table1[NetRevenue_Analytical]) -> 453358.7 | K1278: =Table14[[#This Row],[Net Revenue]]/Table14[[#Totals],[Net Revenue]] -> 0.11583711 | L1278: =SUMIF(Table1[ProductID_Clean],Table14[[#This Row],[ProductID]],Table1[Quantity]) -> 216 | O1278: Strategic | P1278: =SUMIF(Table1[CustumerType],Table16[[#This Row],[Customer Type]],Table1[GrossRevenue_Analytical]) -> 1144990 | Q1278: =SUMIF(Table1[CustumerType],Table16[[#This Row],[Customer Type]],Table1[DiscountAmount_Analytical]) -> 230612.02 | R1278: =Table16[[#This Row],[Discount]]/Table16[[#This Row],[Gross Revenue]] -> 0.20140964 | S1278: =SUMIF(Table1[CustumerType],Table16[[#This Row],[Customer Type]],Table1[NetRevenue_Analytical]) -> 914377.98 | T1278: =Table16[[#This Row],[Net Revenue]]/Table16[[#Totals],[Net Revenue]] -> 0.23454012 | U1278: =SUMIF(Table1[CustumerType],Table16[[#This Row],[Customer Type]],Table1[Quantity]) -> 890
F1279: P-SI-005 | G1279: =SUMIF(Table1[ProductID_Clean],Table14[[#This Row],[ProductID]],Table1[GrossRevenue_Analytical]) -> 290080 | H1279: =SUMIF(Table1[ProductID_Clean],Table14[[#This Row],[ProductID]],Table1[DiscountAmount_Analytical]) -> 42382.35 | I1279: =Table14[[#This Row],[Discount]]/Table14[[#This Row],[Gross Revenue]] -> 0.14610573 | J1279: =SUMIF(Table1[ProductID_Clean],Table14[[#This Row],[ProductID]],Table1[NetRevenue_Analytical]) -> 247697.65 | K1279: =Table14[[#This Row],[Net Revenue]]/Table14[[#Totals],[Net Revenue]] -> 0.063288915 | L1279: =SUMIF(Table1[ProductID_Clean],Table14[[#This Row],[ProductID]],Table1[Quantity]) -> 259 | O1279: Key Account | P1279: =SUMIF(Table1[CustumerType],Table16[[#This Row],[Customer Type]],Table1[GrossRevenue_Analytical]) -> 1549620 | Q1279: =SUMIF(Table1[CustumerType],Table16[[#This Row],[Customer Type]],Table1[DiscountAmount_Analytical]) -> 230526.17 | R1279: =Table16[[#This Row],[Discount]]/Table16[[#This Row],[Gross Revenue]] -> 0.14876303 | S1279: =SUMIF(Table1[CustumerType],Table16[[#This Row],[Customer Type]],Table1[NetRevenue_Analytical]) -> 1319093.8 | T1279: =Table16[[#This Row],[Net Revenue]]/Table16[[#Totals],[Net Revenue]] -> 0.33835069 | U1279: =SUMIF(Table1[CustumerType],Table16[[#This Row],[Customer Type]],Table1[Quantity]) -> 1135
F1280: P-SI-006 | G1280: =SUMIF(Table1[ProductID_Clean],Table14[[#This Row],[ProductID]],Table1[GrossRevenue_Analytical]) -> 111370 | H1280: =SUMIF(Table1[ProductID_Clean],Table14[[#This Row],[ProductID]],Table1[DiscountAmount_Analytical]) -> 24209.74 | I1280: =Table14[[#This Row],[Discount]]/Table14[[#This Row],[Gross Revenue]] -> 0.21738116 | J1280: =SUMIF(Table1[ProductID_Clean],Table14[[#This Row],[ProductID]],Table1[NetRevenue_Analytical]) -> 87160.26 | K1280: =Table14[[#This Row],[Net Revenue]]/Table14[[#Totals],[Net Revenue]] -> 0.022270208 | L1280: =SUMIF(Table1[ProductID_Clean],Table14[[#This Row],[ProductID]],Table1[Quantity]) -> 518 | O1280: Standard | P1280: =SUMIF(Table1[CustumerType],Table16[[#This Row],[Customer Type]],Table1[GrossRevenue_Analytical]) -> 1524220 | Q1280: =SUMIF(Table1[CustumerType],Table16[[#This Row],[Customer Type]],Table1[DiscountAmount_Analytical]) -> 163965.19 | R1280: =Table16[[#This Row],[Discount]]/Table16[[#This Row],[Gross Revenue]] -> 0.10757318 | S1280: =SUMIF(Table1[CustumerType],Table16[[#This Row],[Customer Type]],Table1[NetRevenue_Analytical]) -> 1360254.8 | T1280: =Table16[[#This Row],[Net Revenue]]/Table16[[#Totals],[Net Revenue]] -> 0.34890858 | U1280: =SUMIF(Table1[CustumerType],Table16[[#This Row],[Customer Type]],Table1[Quantity]) -> 1188
F1281: P-SI-007 | G1281: =SUMIF(Table1[ProductID_Clean],Table14[[#This Row],[ProductID]],Table1[GrossRevenue_Analytical]) -> 353780 | H1281: =SUMIF(Table1[ProductID_Clean],Table14[[#This Row],[ProductID]],Table1[DiscountAmount_Analytical]) -> 54757.76 | I1281: =Table14[[#This Row],[Discount]]/Table14[[#This Row],[Gross Revenue]] -> 0.15477913 | J1281: =SUMIF(Table1[ProductID_Clean],Table14[[#This Row],[ProductID]],Table1[NetRevenue_Analytical]) -> 299022.24 | K1281: =Table14[[#This Row],[Net Revenue]]/Table14[[#Totals],[Net Revenue]] -> 0.076402796 | L1281: =SUMIF(Table1[ProductID_Clean],Table14[[#This Row],[ProductID]],Table1[Quantity]) -> 361 | O1281: Emerging | P1281: =SUMIF(Table1[CustumerType],Table16[[#This Row],[Customer Type]],Table1[GrossRevenue_Analytical]) -> 349275 | Q1281: =SUMIF(Table1[CustumerType],Table16[[#This Row],[Customer Type]],Table1[DiscountAmount_Analytical]) -> 44402.17 | R1281: =Table16[[#This Row],[Discount]]/Table16[[#This Row],[Gross Revenue]] -> 0.12712668 | S1281: =SUMIF(Table1[CustumerType],Table16[[#This Row],[Customer Type]],Table1[NetRevenue_Analytical]) -> 304872.83 | T1281: =Table16[[#This Row],[Net Revenue]]/Table16[[#Totals],[Net Revenue]] -> 0.078200604 | U1281: =SUMIF(Table1[CustumerType],Table16[[#This Row],[Customer Type]],Table1[Quantity]) -> 236
F1282: P-SI-008 | G1282: =SUMIF(Table1[ProductID_Clean],Table14[[#This Row],[ProductID]],Table1[GrossRevenue_Analytical]) -> 273600 | H1282: =SUMIF(Table1[ProductID_Clean],Table14[[#This Row],[ProductID]],Table1[DiscountAmount_Analytical]) -> 31362.96 | I1282: =Table14[[#This Row],[Discount]]/Table14[[#This Row],[Gross Revenue]] -> 0.1146307 | J1282: =SUMIF(Table1[ProductID_Clean],Table14[[#This Row],[ProductID]],Table1[NetRevenue_Analytical]) -> 242237.04 | K1282: =Table14[[#This Row],[Net Revenue]]/Table14[[#Totals],[Net Revenue]] -> 0.061893681 | L1282: =SUMIF(Table1[ProductID_Clean],Table14[[#This Row],[ProductID]],Table1[Quantity]) -> 288 | O1282: Total | P1282: =SUBTOTAL(109,Table16[Gross Revenue]) -> 4568105 | Q1282: =SUBTOTAL(109,Table16[Discount]) -> 669505.55 | S1282: =SUBTOTAL(109,Table16[Net Revenue]) -> 3898599.5 | T1282: =SUBTOTAL(109,Table16[Revenue Contribution (%)]) -> 1 | U1282: =SUBTOTAL(109,Table16[Quantity]) -> 3449
F1283: Total | G1283: =SUBTOTAL(109,Table14[Gross Revenue]) -> 4586720 | H1283: =SUBTOTAL(109,Table14[Discount]) -> 672959.56 | J1283: =SUBTOTAL(109,Table14[Net Revenue]) -> 3913760.4 | K1283: =SUBTOTAL(109,Table14[Revenue Contribution (%)]) -> 1 | L1283: =SUBTOTAL(109,Table14[Quantity]) -> 3470 | O1283: Missing Value
O1285: Sales Channel | P1285: Gross Revenue | Q1285: Discount | R1285: Discount Rate (%) | S1285: Net Revenue | T1285: Revenue Contribution (%) | U1285: Quantity
F1286: Customer Segment | G1286: Gross Revenue | H1286: Discount | I1286: Discount Rate | J1286: Net Revenue | K1286: Revenue Contribution | L1286: Quantity | O1286: Direct | P1286: =SUMIF(Table1[SalesChannelClean],Table17[[#This Row],[Sales Channel]],Table1[GrossRevenue_Analytical]) -> 2446190 | Q1286: =SUMIF(Table1[SalesChannelClean],Table17[[#This Row],[Sales Channel]],Table1[DiscountAmount_Analytical]) -> 277997.05 | R1286: =Table17[[#This Row],[Discount]]/Table17[[#This Row],[Gross Revenue]] -> 0.11364491 | S1286: =SUMIF(Table1[SalesChannelClean],Table17[[#This Row],[Sales Channel]],Table1[NetRevenue_Analytical]) -> 2168193 | T1286: =Table17[[#This Row],[Net Revenue]]/Table17[[#Totals],[Net Revenue]] -> 0.57080277 | U1286: =SUMIF(Table1[SalesChannelClean],Table17[[#This Row],[Sales Channel]],Table1[Quantity]) -> 1875
F1287: Aerospace & Defense | G1287: 725270 | H1287: 117086.82 | I1287: =Table57[[#This Row],[Discount]]/Table57[[#This Row],[Gross Revenue]] -> 0.16143894 | J1287: =Table57[[#This Row],[Gross Revenue]]-Table57[[#This Row],[Discount]] -> 608183.18 | K1287: =Table57[[#This Row],[Net Revenue]]/Table57[[#Totals],[Net Revenue]] -> 0.15539612 | L1287: 574 | O1287: Distributor | P1287: =SUMIF(Table1[SalesChannelClean],Table17[[#This Row],[Sales Channel]],Table1[GrossRevenue_Analytical]) -> 1404940 | Q1287: =SUMIF(Table1[SalesChannelClean],Table17[[#This Row],[Sales Channel]],Table1[DiscountAmount_Analytical]) -> 280142.02 | R1287: =Table17[[#This Row],[Discount]]/Table17[[#This Row],[Gross Revenue]] -> 0.19939785 | S1287: =SUMIF(Table1[SalesChannelClean],Table17[[#This Row],[Sales Channel]],Table1[NetRevenue_Analytical]) -> 1124798 | T1287: =Table17[[#This Row],[Net Revenue]]/Table17[[#Totals],[Net Revenue]] -> 0.29611654 | U1287: =SUMIF(Table1[SalesChannelClean],Table17[[#This Row],[Sales Channel]],Table1[Quantity]) -> 1038
F1288: Manufacturing | G1288: 1431240 | H1288: 206477.83 | I1288: =Table57[[#This Row],[Discount]]/Table57[[#This Row],[Gross Revenue]] -> 0.14426499 | J1288: =Table57[[#This Row],[Gross Revenue]]-Table57[[#This Row],[Discount]] -> 1224762.2 | K1288: =Table57[[#This Row],[Net Revenue]]/Table57[[#Totals],[Net Revenue]] -> 0.31293744 | L1288: 1104 | O1288: Partner Portal | P1288: =SUMIF(Table1[SalesChannelClean],Table17[[#This Row],[Sales Channel]],Table1[GrossRevenue_Analytical]) -> 601600 | Q1288: =SUMIF(Table1[SalesChannelClean],Table17[[#This Row],[Sales Channel]],Table1[DiscountAmount_Analytical]) -> 96093.31 | R1288: =Table17[[#This Row],[Discount]]/Table17[[#This Row],[Gross Revenue]] -> 0.15972957 | S1288: =SUMIF(Table1[SalesChannelClean],Table17[[#This Row],[Sales Channel]],Table1[NetRevenue_Analytical]) -> 505506.69 | T1288: =Table17[[#This Row],[Net Revenue]]/Table17[[#Totals],[Net Revenue]] -> 0.13308069 | U1288: =SUMIF(Table1[SalesChannelClean],Table17[[#This Row],[Sales Channel]],Table1[Quantity]) -> 483
F1289: Energy & Utilities | G1289: 962340 | H1289: 160951.1 | I1289: =Table57[[#This Row],[Discount]]/Table57[[#This Row],[Gross Revenue]] -> 0.16724972 | J1289: =Table57[[#This Row],[Gross Revenue]]-Table57[[#This Row],[Discount]] -> 801388.9 | K1289: =Table57[[#This Row],[Net Revenue]]/Table57[[#Totals],[Net Revenue]] -> 0.20476187 | L1289: 706 | O1289: Total | P1289: =SUBTOTAL(109,Table17[Gross Revenue]) -> 4452730 | Q1289: =SUBTOTAL(109,Table17[Discount]) -> 654232.38 | S1289: =SUBTOTAL(109,Table17[Net Revenue]) -> 3798497.6 | T1289: =SUBTOTAL(109,Table17[Revenue Contribution (%)]) -> 1 | U1289: =SUBTOTAL(109,Table17[Quantity]) -> 3396
F1290: Process Industries | G1290: 771920 | H1290: 104583.75 | I1290: =Table57[[#This Row],[Discount]]/Table57[[#This Row],[Gross Revenue]] -> 0.13548522 | J1290: =Table57[[#This Row],[Gross Revenue]]-Table57[[#This Row],[Discount]] -> 667336.25 | K1290: =Table57[[#This Row],[Net Revenue]]/Table57[[#Totals],[Net Revenue]] -> 0.17051024 | L1290: 570 | O1290: Missing Value
F1291: Research & Labs | G1291: 695950 | H1291: 83860.06 | I1291: =Table57[[#This Row],[Discount]]/Table57[[#This Row],[Gross Revenue]] -> 0.12049725 | J1291: =Table57[[#This Row],[Gross Revenue]]-Table57[[#This Row],[Discount]] -> 612089.94 | K1291: =Table57[[#This Row],[Net Revenue]]/Table57[[#Totals],[Net Revenue]] -> 0.15639433 | L1291: 516 | T1291: —
F1292: Total | G1292: =SUBTOTAL(109,Table57[Gross Revenue]) -> 4586720 | H1292: =SUBTOTAL(109,Table57[Discount]) -> 672959.56 | J1292: =SUBTOTAL(109,Table57[Net Revenue]) -> 3913760.4 | K1292: =SUBTOTAL(109,Table57[Revenue Contribution]) -> 1 | L1292: =SUBTOTAL(109,Table57[Quantity]) -> 3470
O1293: Dimension | P1293: Highest-Discount Cohort | Q1293: Gross Revenue | R1293: Discount | S1293: Discount Rate (%) | T1293: Net Revenue | U1293: Revenue Contribution (%) | V1293: Revenue Contribution Rank | W1293: Quantity
J1294: — | O1294: Customer Type | P1294: Strategic | Q1294: 1144990 | R1294: 230612.02 | S1294: 0.2014 | T1294: 914377.98 | U1294: 0.2345 | V1294: 3rd of 4 | W1294: 890
O1295: Customer Segment | P1295: Energy & Utilities | Q1295: 970620 | R1295: 161872.59 | S1295: 0.1668 | T1295: 808747.41 | U1295: 0.2056 | V1295: 2nd of 5 | W1295: 710
O1296: Region | P1296: APAC | Q1296: 819195 | R1296: 149707.8 | S1296: 0.1827 | T1296: 669487.2 | U1296: 0.1702 | V1296: 3rd of 4 | W1296: 621
O1297: Sales Channel | P1297: Distributor | Q1297: 1404940 | R1297: 280142.02 | S1297: 0.1994 | T1297: 1124798 | U1297: 0.2961 | V1297: 2nd of 3 | W1297: 1038

Sheet Custumer
A1: CustomerID | B1: CustomerName | C1: CustomerName_Clean | D1: CustomerSegment | E1: CustomerSegment_Clean | F1: CustomerType | G1: Region | H1: Region_Clean | I1: Industry | J1: AccountStatus | K1: AccountStatus_Clean | L1: PrimaryContact | M1: CreditLimit | N1: CreditLimit_Clean
A2: C-1001 | B2: Rodriguez Figueroa and Sanchez | C2: Rodriguez Figueroa And Sanchez | D2: ENERGY & UTILITIES | E2: Energy & Utilities | F2: Standard | G2: Latin America | H2: LATIN AMERICA | I2: Oil & Gas | J2: Active | K2: Active | L2: Brian Yang | M2: 100000 | N2: 100000
A3: C-1002 | B3: Miller Henderson and Johnson | C3: Miller Henderson And Johnson | D3: Manufacturing | E3: Manufacturing | F3: Emerging | G3: North America | H3: N. AMERICA | I3: Discrete Manufacturing | J3: Active | K3: Active | L3: Jonathan Johnson | M3: 500000 | N3: 500000
A4: C-1003 | B4: Baldwin Ltd Corp | C4: Baldwin Ltd Corp | D4: MANUFACTURING | E4: Manufacturing | F4: Emerging | G4: Latin America | H4: LATIN AMERICA | I4: Automotive | J4: Active | K4: Active | L4: Connie Lawrence | M4: 100000 | N4: 100000
A5: C-1004 | B5: Blake and Sons Inc | C5: Blake And Sons Inc | D5: Manufacturing | E5: Manufacturing | F5: Standard | G5: North America | H5: N. AMERICA | I5: Automotive | J5: Active | K5: Active | L5: Gina Moore | M5: 100000 | N5: 100000
A6: C-1005 | B6: Garcia-James LLC | C6: Garcia-James Llc | D6: PROCESS INDUSTRIES | E6: Process Industries | F6: Key Account | G6: North america | H6: N. AMERICA | I6: Chemicals | J6: Active | K6: Active | L6: Gregory Baker | M6: 250000 | N6: 250000
A7: C-1006 | B7: Blair PLC AG | C7: Blair Plc Ag | D7: AEROSPACE & DEFENSE | E7: Aerospace & Defense | F7: Standard | G7: North America | H7: N. AMERICA | I7: Avionics | J7: Active | K7: Active | L7: Thomas Miller | M7: 50000 | N7: 50000
A8: C-1007 | B8: Calderon-Montgomery Co | C8: Calderon-Montgomery Co | D8: Process Industries | E8: Process Industries | F8: Strategic | G8: North America | H8: N. AMERICA | I8: Food & Beverage | J8: Active | K8: Active | L8: Laura Bush | M8: 2500000 | N8: 2500000
A9: C-1008 | B9: Stanley LLC | C9: Stanley Llc | D9: Aerospace & Defense | E9: Aerospace & Defense | F9: Strategic | G9: North America | H9: N. AMERICA | I9: Aerospace OEM | J9: Active | K9: Active | L9: Dr. Sharon James | M9: 250000 | N9: 250000
A10: C-1009 | B10: Reid-Diaz | C10: Reid-Diaz | D10: MANUFACTURING | E10: Manufacturing | F10: Strategic | G10: EMEA | H10: EMEA | I10: Discrete Manufacturing | J10: Active | K10: Active | L10: Daniel Adams | M10: $100,000 | N10: 100000
A11: C-1010 | B11: wong lynch and jackson | C11: Wong Lynch And Jackson | D11: Process Industries | E11: Process Industries | F11: Standard | G11: North America | H11: N. AMERICA | I11: Food & Beverage | J11: Active | K11: Active | L11: Carla Gray | M11: 100000 | N11: 100000
A12: C-1011 | B12: Watts Robinson and Nguyen LLC | C12: Watts Robinson And Nguyen Llc | D12: Research & Labs | E12: Research & Labs | F12: Emerging | G12: APAC | H12: APAC | I12: Private R&D | J12: Active | K12: Active | L12: Amy Underwood | M12: 250000 | N12: 250000
A13: C-1012 | B13: Morales-Jones Pty Ltd | C13: Morales-Jones Pty Ltd | D13: Research & Labs | E13: Research & Labs | F13: Key Account | G13: North america | H13: N. AMERICA | I13: University Lab | J13: Active | K13: Active | L13: Latoya Robbins | M13: 100000 | N13: 100000
A14: C-1013 | B14: Rios Group SA | C14: Rios Group Sa | D14: Energy & Utilities | E14: Energy & Utilities | F14: Emerging | G14: North America | H14: N. AMERICA | I14: Renewables | J14: Active | K14: Active | L14: Maria Thomas | M14: 100000 | N14: 100000
A15: C-1014 | B15: Wright PLC | C15: Wright Plc | D15: Process Industries | E15: Process Industries | F15: Standard | G15: North America | H15: N. AMERICA | I15: Pulp & Paper | J15: Active | K15: Active | L15: Nicole Patterson | M15: 2500000 | N15: 2500000
A16: C-1015 | B16: Ross Robinson and Bright Pty Ltd | C16: Ross Robinson And Bright Pty Ltd | D16: AEROSPACE & DEFENSE | E16: Aerospace & Defense | F16: Strategic | G16: North America | H16: N. AMERICA | I16: Aerospace OEM | J16: Active | K16: Active | L16: Ann Williams | M16: 500000 | N16: 500000
A17: C-1016 | B17: hernandez and sons co | C17: Hernandez And Sons Co | D17: AEROSPACE & DEFENSE | E17: Aerospace & Defense | F17: Strategic | G17: APAC | H17: APAC | I17: MRO | J17: Active | K17: Active | L17: Jennifer Brown | M17: $50,000 | N17: 50000
A18: C-1017 | B18: Carlson-Mcdonald Corporation | C18: Carlson-Mcdonald Corporation | D18: Aerospace & Defense | E18: Aerospace & Defense | F18: Key Account | G18: EMEA | H18: EMEA | I18: Aerospace OEM | J18: Active | K18: Active | L18: Juan Dunlap | M18: 100000 | N18: 100000
A19: C-1018 | B19: Le Maldonado and Herrera | C19: Le Maldonado And Herrera | D19: Energy & Utilities | E19: Energy & Utilities | F19: Standard | G19: APAC | H19: APAC | I19: Renewables | J19: Active | K19: Active | L19: Martin Rodriguez | M19: 250000 | N19: 250000
A20: C-1019 | B20: Moore-Smith | C20: Moore-Smith | D20: Manufacturing | E20: Manufacturing | F20: Standard | G20: APAC | H20: APAC | I20: Discrete Manufacturing | J20: Active | K20: Active | L20: Michelle Stanton | M20: 500000 | N20: 500000
A21: C-1020 | B21: Romero Inc | C21: Romero Inc | D21: Energy & Utilities | E21: Energy & Utilities | F21: Standard | G21: EMEA | H21: EMEA | I21: Utilities | J21: Active | K21: Active | L21: Elizabeth Fowler | M21: 50000 | N21: 50000
A22: C-1021 | B22: Gonzalez Brooks and Martin SA | C22: Gonzalez Brooks And Martin Sa | D22: Manufacturing | E22: Manufacturing | F22: Key Account | G22: EMEA | H22: EMEA | I22: Discrete Manufacturing | J22: Active | K22: Active | L22: Tammy Sellers | M22: 1000000 | N22: 1000000
A23: C-1022 | B23: Nguyen Smith and Hickman LLC | C23: Nguyen Smith And Hickman Llc | D23: Manufacturing | E23: Manufacturing | F23: Standard | G23: North America | H23: N. AMERICA | I23: Machinery | J23: Active | K23: Active | L23: Sandra Parker | M23: 50000 | N23: 50000
A24: C-1023 | B24: Allen PLC | C24: Allen Plc | D24: Manufacturing | E24: Manufacturing | F24: Emerging | G24: North America | H24: N. AMERICA | I24: Automotive | J24: Active | K24: Active | L24: Angelica Tucker | M24: 250000 | N24: 250000
A25: C-1024 | B25: Spence PLC | C25: Spence Plc | D25: Research & Labs | E25: Research & Labs | F25: Key Account | G25: APAC | H25: APAC | I25: National Lab | J25: Active | K25: Active | L25: Betty Alvarez | M25: 250000 | N25: 250000
A26: C-1025 | B26: Martin Rose and Obrien LLC | C26: Martin Rose And Obrien Llc | D26: Aerospace & Defense | E26: Aerospace & Defense | F26: Key Account | G26: Latin America | H26: LATIN AMERICA | I26: Defense Contractor | J26: Active | K26: Active | L26: Tanya Campos | M26: 100000 | N26: 100000
A27: C-1026 | B27: Harris Collins and Carney GmbH | C27: Harris Collins And Carney Gmbh | D27: Energy & Utilities | E27: Energy & Utilities | F27: Emerging | G27: APAC | H27: APAC | I27: Power Generation | J27: Active | K27: Active | L27: Jessica Holmes | M27: 250000 | N27: 250000
A28: C-1027 | B28: Wright Inc | C28: Wright Inc | D28: Energy & Utilities | E28: Energy & Utilities | F28: Strategic | G28: North America | H28: N. AMERICA | I28: Oil & Gas | J28: Active | K28: Active | L28: Kevin Hall | M28: 1000000 | N28: 1000000
A29: C-1028 | B29: Smith Ltd Inc | C29: Smith Ltd Inc | D29: Energy & Utilities | E29: Energy & Utilities | F29: Standard | G29: EMEA | H29: EMEA | I29: Renewables | J29: Active | K29: Active | L29: Crystal Whitehead | M29: 2500000 | N29: 2500000
... A33: C-1032 | B33: Brown Ltd | C33: Brown Ltd | D33: Manufacturing | E33: Manufacturing | F33: Standard | G33: EMEA | H33: EMEA | I33: Electronics | J33: Active | K33: Active | L33: Scott Wright | M33: 500000 | N33: 500000
A34: C-1033 | B34: Herrera and Sons Ltd | C34: Herrera And Sons Ltd | D34: Energy & Utilities | E34: Energy & Utilities | F34: Standard | G34: EMEA | H34: EMEA | I34: Power Generation | J34: Active | K34: Active | L34: Donald Wright | M34: $50,000 | N34: 50000
A35: C-1034 | B35: Ramos PLC | C35: Ramos Plc | D35: Aerospace & Defense | E35: Aerospace & Defense | F35: Key Account | G35: North America | H35: N. AMERICA | I35: MRO | J35: Active | K35: Active | L35: Matthew Fernandez | M35: 250000 | N35: 250000
A36: C-1035 | B36: Novak and Sons | C36: Novak And Sons | D36: Process Industries | E36: Process Industries | F36: Standard | G36: North america | H36: N. AMERICA | I36: Pulp & Paper | J36: Active | K36: Active | L36: John Lewis | M36: 250000 | N36: 250000
A37: C-1036 | B37: Barrera-Martin | C37: Barrera-Martin | D37: Manufacturing | E37: Manufacturing | F37: Standard | G37: EMEA | H37: EMEA | I37: Electronics | J37: Active | K37: Active | L37: James House | M37: 50000 | N37: 50000
A38: C-1037 | B38: Mitchell-Horton Ltd | C38: Mitchell-Horton Ltd | D38: Energy & Utilities | E38: Energy & Utilities | F38: Emerging | G38: North America | H38: N. AMERICA | I38: Utilities | J38: Active | K38: Active | L38: Rachel Stanley | M38: 100000 | N38: 100000
A39: C-1038 | B39: Moore-Phillips Inc | C39: Moore-Phillips Inc | D39: Process Industries | E39: Process Industries | F39: Standard | G39: APAC | H39: APAC | I39: Chemicals | J39: Active | K39: Active | L39: Lauren Daniels | M39: $100,000 | N39: 100000
A40: C-1039 | B40: Edwards Williams and Woods Ltd | C40: Edwards Williams And Woods Ltd | D40: Manufacturing | E40: Manufacturing | F40: Emerging | G40: Latin America | H40: LATIN AMERICA | I40: Electronics | J40: Active | K40: Active | L40: Kim Brown | M40: 100000 | N40: 100000
A41: C-1040 | B41: Miller Lopez and Larson Pty Ltd | C41: Miller Lopez And Larson Pty Ltd | D41: Energy & Utilities | E41: Energy & Utilities | F41: Emerging | G41: APAC | H41: APAC | I41: Utilities | J41: Active | K41: Active | L41: Cynthia Wilson | M41: 500000 | N41: 500000
A42: C-1041 | B42: Sanchez Wheeler and Harvey BV | C42: Sanchez Wheeler And Harvey Bv | D42: Process Industries | E42: Process Industries | F42: Key Account | G42: North america | H42: N. AMERICA | I42: Food & Beverage | J42: Active | K42: Active | L42: Kevin Mills | M42: 250000 | N42: 250000
A43: C-1042 | B43: Harris-Moran | C43: Harris-Moran | D43: MANUFACTURING | E43: Manufacturing | F43: Standard | G43: North America | H43: N. AMERICA | I43: Automotive | J43: Active | K43: Active | L43: James Powers | M43: 100000 | N43: 100000
A44: C-1043 | B44: Bryant-Hickman | C44: Bryant-Hickman | D44: Process Industries | E44: Process Industries | F44: Standard | G44: EMEA | H44: EMEA | I44: Chemicals | J44: Active | K44: Active | L44: Alexandra Howell | M44: 500000 | N44: 500000
A45: C-1044 | B45: Ferrell Jones and Lewis | C45: Ferrell Jones And Lewis | D45: Manufacturing | E45: Manufacturing | F45: Standard | G45: North America | H45: N. AMERICA | I45: Machinery | J45: Active | K45: Active | L45: Timothy Ibarra | M45: 500000 | N45: 500000
A46: C-1045 | B46: Wood and Sons | C46: Wood And Sons | D46: Process Industries | E46: Process Industries | F46: Strategic | G46: EMEA | H46: EMEA | I46: Food & Beverage | J46: Active | K46: Active | L46: Joshua Turner | M46: 100000 | N46: 100000
A47: C-1046 | B47: Rice Contreras and Spe... | C47: Rice Contreras And Spe... | D47: Manufacturing | E47: Manufacturing | F47: Standard | G47: Latin America | H47: LATIN AMERICA | I47: Discrete Manufacturing | J47: Active | K47: Active | L47: Ashley Humphrey | M47: 250000 | N47: 250000
A48: C-1047 | B48: Wilson-Rodriguez GmbH | C48: Wilson-Rodriguez Gmbh | D48: Aerospace & Defense | E48: Aerospace & Defense | F48: Standard | G48: EMEA | H48: EMEA | I48: Defense Contractor | J48: Active | K48: Active | L48: Denise Jacobs | M48: 100000 | N48: 100000
A49: C-1048 | B49: Cooper Watts and Farrell Corp | C49: Cooper Watts And Farrell Corp | D49: Aerospace & Defense | E49: Aerospace & Defense | F49: Strategic | G49: North America | H49: N. AMERICA | I49: MRO | J49: Active | K49: Active | L49: Danielle Odonnell | M49: 100000 | N49: 100000
A50: C-1049 | B50: Davis Group | C50: Davis Group | D50: RESEARCH & LABS | E50: Research & Labs | F50: Emerging | G50: LatAm | H50: LATIN AMERICA | I50: National Lab | J50: Active | K50: Active | L50: Amanda Cook | M50: 50000 | N50: 50000
A51: C-1050 | B51: Walsh LLC Ltd | C51: Walsh Llc Ltd | D51: Research & Labs | E51: Research & Labs | F51: Emerging | G51: EMEA | H51: EMEA | I51: University Lab | J51: On Hold | K51: On Hold | L51: Jeremy Thornton | M51: 500000 | N51: 500000
... A60: C-1059 | B60: Murphy-Lin | C60: Murphy-Lin | D60: Manufacturing | E60: Manufacturing | F60: Emerging | G60: North America | H60: N. AMERICA | I60: Electronics | J60: Active | K60: Active | L60: Diana May | M60: 50000 | N60: 50000
A61: C-1060 | B61: Frazier-Anthony | C61: Frazier-Anthony | D61: Energy & Utilities | E61: Energy & Utilities | F61: Key Account | G61: APAC | H61: APAC | I61: Renewables | K61: Missing Value | L61: Alexander Wiley | M61: 50000 | N61: 50000
A62: C-1061 | B62: white-estes ag | C62: White-Estes Ag | D62: Manufacturing | E62: Manufacturing | F62: Standard | G62: EMEA | H62: EMEA | I62: Electronics | J62: Active | K62: Active | L62: Brian Hamilton | M62: 500000 | N62: 500000
A63: C-1062 | B63: Hartman Graham and Joyce LLC | C63: Hartman Graham And Joyce Llc | D63: Research & Labs | E63: Research & Labs | F63: Key Account | G63: EMEA | H63: EMEA | I63: University Lab | J63: Active | K63: Active | L63: Steven Lee | M63: 100000 | N63: 100000
A64: C-1063 | B64: Fletcher Inc Co | C64: Fletcher Inc Co | D64: Energy & Utilities | E64: Energy & Utilities | F64: Strategic | G64: North America | H64: N. AMERICA | I64: Power Generation | K64: Missing Value | L64: Renee Mcdaniel | M64: 500000 | N64: 500000
A65: C-1064 | B65: Mclaughlin Gonzalez and Reynolds Inc | C65: Mclaughlin Gonzalez And Reynolds Inc | D65: Process Industries | E65: Process Industries | F65: Key Account | G65: North America | H65: N. AMERICA | I65: Chemicals | J65: Active | K65: Active | L65: Tammie Hanson | M65: 100000 | N65: 100000
A66: C-1065 | B66: Charles Cortez and Evans | C66: Charles Cortez And Evans | D66: Process Industries | E66: Process Industries | F66: Standard | G66: APAC | H66: APAC | I66: Chemicals | J66: Active | K66: Active | L66: Jason Powell | M66: 1000000 | N66: 1000000
A67: C-1066 | B67: Spencer-Lee | C67: Spencer-Lee | D67: Aerospace & Defense | E67: Aerospace & Defense | F67: Standard | G67: EMEA | H67: EMEA | I67: MRO | J67: Active | K67: Active | L67: Jamie Adkins | M67: 100000 | N67: 100000
A68: C-1067 | B68: Gilbert LLC LLC | C68: Gilbert Llc Llc | D68: Energy & Utilities | E68: Energy & Utilities | F68: Strategic | G68: APAC | H68: APAC | I68: Renewables | J68: Active | K68: Active | L68: Roy Torres | M68: 50000 | N68: 50000
A69: C-1068 | B69: jordan plc | C69: Jordan Plc | D69: Manufacturing | E69: Manufacturing | F69: Standard | G69: APAC | H69: APAC | I69: Discrete Manufacturing | J69: Active | K69: Active | L69: Erica Ramos | M69: 50000 | N69: 50000
A70: C-1069 | B70: Lewis Kennedy and Santana Co | C70: Lewis Kennedy And Santana Co | D70: Energy & Utilities | E70: Energy & Utilities | F70: Key Account | G70: EMEA | H70: EMEA | I70: Utilities | J70: Active | K70: Active | L70: Carolyn Miller | M70: 100000 | N70: 100000
A71: C-1070 | B71: Beck Harvey and Davis BV | C71: Beck Harvey And Davis Bv | D71: Process Industries | E71: Process Industries | F71: Strategic | G71: EMEA | H71: EMEA | I71: Pulp & Paper | J71: Active | K71: Active | L71: Cynthia Collins | M71: 250000 | N71: 250000
A72: C-1071 | B72: Hernandez Inc Corp | C72: Hernandez Inc Corp | D72: Energy & Utilities | E72: Energy & Utilities | F72: Standard | G72: APAC | H72: APAC | I72: Utilities | J72: Active | K72: Active | L72: John Atkinson | M72: 50000 | N72: 50000
A73: C-1072 | B73: Gibson Ltd Pty Ltd | C73: Gibson Ltd Pty Ltd | D73: Process Industries | E73: Process Industries | F73: Standard | G73: North America | H73: N. AMERICA | I73: Pulp & Paper | J73: Active | K73: Active | L73: Michelle Cruz | M73: 250000 | N73: 250000
A74: C-1073 | B74: Sanchez-Douglas | C74: Sanchez-Douglas | D74: Energy & Utilities | E74: Energy & Utilities | F74: Standard | G74: EMEA | H74: EMEA | I74: Oil & Gas | J74: Active | K74: Active | L74: Paul Carrillo | M74: 1000000 | N74: 1000000
A75: C-1074 | B75: Osborne and Sons | C75: Osborne And Sons | D75: Energy & Utilities | E75: Energy & Utilities | F75: Emerging | G75: Latin America | H75: LATIN AMERICA | I75: Oil & Gas | K75: Missing Value | L75: Tyler Holmes | M75: 50000 | N75: 50000
A76: C-1075 | B76: Grant Inc SA | C76: Grant Inc Sa | D76: Manufacturing | E76: Manufacturing | F76: Strategic | G76: North America | H76: N. AMERICA | I76: Automotive | J76: Active | K76: Active | L76: Robert Contreras | M76: 50000 | N76: 50000
A77: C-1076 | B77: Larson Dodson and Vance LLC | C77: Larson Dodson And Vance Llc | D77: Manufacturing | E77: Manufacturing | F77: Strategic | G77: APAC | H77: APAC | I77: Electronics | J77: Active | K77: Active | L77: Michelle Wagner | M77: 100000 | N77: 100000
A78: C-1077 | B78: Griffin Moore and Hensley Ltd | C78: Griffin Moore And Hensley Ltd | D78: Manufacturing | E78: Manufacturing | F78: Standard | G78: EMEA | H78: EMEA | I78: Machinery | J78: Active | K78: Active | L78: Paul Larsen | M78: 500000 | N78: 500000
A79: C-1078 | B79: Cannon-Boyd Corp | C79: Cannon-Boyd Corp | D79: Aerospace & Defense | E79: Aerospace & Defense | F79: Key Account | G79: North America | H79: N. AMERICA | I79: Avionics | J79: Active | K79: Active | L79: Denise Jones | M79: 500000 | N79: 500000
A80: C-1079 | B80: Young-Rogers | C80: Young-Rogers | D80: Research & Labs | E80: Research & Labs | F80: Standard | G80: North America | H80: N. AMERICA | I80: University Lab | J80: Active | K80: Active | L80: Angela Hernandez | M80: 100000 | N80: 100000
A81: C-1080 | B81: Benson-Mccarthy AG | C81: Benson-Mccarthy Ag | D81: Research & Labs | E81: Research & Labs | F81: Standard | G81: APAC | H81: APAC | I81: University Lab | J81: Active | K81: Active | L81: Jason Daniels | M81: 500000 | N81: 500000
A82: C-1081 | B82: Brown-Wall | C82: Brown-Wall | D82: Manufacturing | E82: Manufacturing | F82: Standard | G82: Latin America | H82: LATIN AMERICA | I82: Discrete Manufacturing | J82: Active | K82: Active | L82: Randy Shah | M82: 100000 | N82: 100000
A83: C-1082 | B83: Gates PLC BV | C83: Gates Plc Bv | D83: Research & Labs | E83: Research & Labs | F83: Strategic | G83: North America | H83: N. AMERICA | I83: Testing Facility | J83: Active | K83: Active | L83: Aaron Bell | M83: 50000 | N83: 50000
A84: C-1083 | B84: Castaneda-Ashley Pty Limited | C84: Castaneda-Ashley Pty Limited | D84: Manufacturing | E84: Manufacturing | F84: Emerging | G84: Latin America | H84: LATIN AMERICA | I84: Automotive | J84: Active | K84: Active | L84: Paul Payne | M84: $250,000 | N84: 250000
A85: C-1084 | B85: Hurst Freeman and Nelson Inc | C85: Hurst Freeman And Nelson Inc | D85: Energy & Utilities | E85: Energy & Utilities | F85: Key Account | G85: North america | H85: N. AMERICA | I85: Utilities | J85: Active | K85: Active | L85: Mr. Michael Yates | M85: 500000 | N85: 500000
A86: C-1085 | B86: Martin Mcdonald and Anderson BV | C86: Martin Mcdonald And Anderson Bv | D86: Aerospace & Defense | E86: Aerospace & Defense | F86: Strategic | G86: APAC | H86: APAC | I86: MRO | J86: Active | K86: Active | L86: Alyssa Long | M86: 50000 | N86: 50000
A87: C-1086 | B87: Alvarado Miller and Patterson AG | C87: Alvarado Miller And Patterson Ag | D87: Process Industries | E87: Process Industries | F87: Emerging | G87: EMEA | H87: EMEA | I87: Pulp & Paper | J87: Active | K87: Active | L87: Catherine Green | M87: 50000 | N87: 50000
A88: C-1087 | B88: Lewis-Murphy GmbH | C88: Lewis-Murphy Gmbh | D88: MANUFACTURING | E88: Manufacturing | F88: Standard | G88: APAC | H88: APAC | I88: Discrete Manufacturing | J88: Active | K88: Active | L88: Jamie Walton | M88: 50000 | N88: 50000
A89: C-1088 | B89: King-Miller | C89: King-Miller | D89: Process Industries | E89: Process Industries | F89: Emerging | G89: North America | H89: N. AMERICA | I89: Chemicals | J89: Active | K89: Active | L89: Joshua Cooke | M89: 50000 | N89: 50000
A90: C-1089 | B90: Walker-Jones | C90: Walker-Jones | D90: Manufacturing | E90: Manufacturing | F90: Standard | G90: Latin America | H90: LATIN AMERICA | I90: Automotive | J90: Active | K90: Active | L90: Amanda Johnson | M90: 500000 | N90: 500000
A91: C-1090 | B91: Gonzalez Inc BV | C91: Gonzalez Inc Bv | D91: Research & Labs | E91: Research & Labs | F91: Standard | G91: Latin America | H91: LATIN AMERICA | I91: National Lab | J91: Active | K91: Active | L91: Cynthia Wells | M91: 50000 | N91: 50000
A92: C-1091 | B92: Elliott and Sons AG | C92: Elliott And Sons Ag | D92: Aerospace & Defense | E92: Aerospace & Defense | F92: Standard | G92: EMEA | H92: EMEA | I92: Aerospace OEM | J92: Active | K92: Active | L92: David Wood | M92: 50000 | N92: 50000
A93: C-1092 | B93: Lawson Adkins and Wilson | C93: Lawson Adkins And Wilson | D93: Energy & Utilities | E93: Energy & Utilities | F93: Standard | G93: North America | H93: N. AMERICA | I93: Oil & Gas | J93: Active | K93: Active | L93: Traci Rodriguez | M93: 50000 | N93: 50000
A94: C-1093 | B94: Hickman PLC LLC | C94: Hickman Plc Llc | D94: Manufacturing | E94: Manufacturing | F94: Standard | G94: EMEA | H94: EMEA | I94: Electronics | J94: Active | K94: Active | L94: Tina Sanders | M94: 2500000 | N94: 2500000
A95: C-1094 | B95: Gonzalez Vargas and Rivas Co | C95: Gonzalez Vargas And Rivas Co | D95: Energy & Utilities | E95: Energy & Utilities | F95: Emerging | G95: North America | H95: N. AMERICA | I95: Power Generation | J95: Active | K95: Active | L95: Michael Turner | M95: 2500000 | N95: 2500000
A96: C-1095 | B96: Burke Martinez and Riggs Inc | C96: Burke Martinez And Riggs Inc | D96: Manufacturing | E96: Manufacturing | F96: Strategic | G96: Latin America | H96: LATIN AMERICA | I96: Automotive | J96: Active | K96: Active | L96: Hannah Patterson | M96: 250000 | N96: 250000
... A98: C-1097 | B98: Yu-Reid | C98: Yu-Reid | D98: Process Industries | E98: Process Industries | F98: Standard | G98: EMEA | H98: EMEA | I98: Pharmaceuticals | J98: Active | K98: Active | L98: Michelle Graham | M98: 250000 | N98: 250000
A99: C-1098 | B99: Boyd Santos and Gilbert | C99: Boyd Santos And Gilbert | D99: Research & Labs | E99: Research & Labs | F99: Key Account | G99: North America | H99: N. AMERICA | I99: Private R&D | K99: Missing Value | L99: Patricia Marshall | M99: 1000000 | N99: 1000000
A100: C-1099 | B100: vargas morris and sanchez pty ltd | C100: Vargas Morris And Sanchez Pty Ltd | D100: Energy & Utilities | E100: Energy & Utilities | F100: Key Account | G100: EMEA | H100: EMEA | I100: Power Generation | J100: Active | K100: Active | L100: Diana Hayes | M100: $250,000 | N100: 250000
A101: C-1100 | B101: Hudson-Barnett | C101: Hudson-Barnett | D101: Energy & Utilities | E101: Energy & Utilities | F101: Strategic | G101: EMEA | H101: EMEA | I101: Renewables | J101: On Hold | K101: On Hold | L101: Johnny Nguyen | M101: 2500000 | N101: 2500000
A102: C-1101 | B102: Lewis-Salinas Corp | C102: Lewis-Salinas Corp | D102: PROCESS INDUSTRIES | E102: Process Industries | F102: Key Account | G102: EMEA | H102: EMEA | I102: Chemicals | J102: Active | K102: Active | L102: Spencer Haynes | M102: 250000 | N102: 250000
A103: C-1102 | B103: Peters-Black Co | C103: Peters-Black Co | D103: Manufacturing | E103: Manufacturing | F103: Emerging | G103: Latin America | H103: LATIN AMERICA | I103: Automotive | J103: Active | K103: Active | L103: David Russell | M103: 500000 | N103: 500000
A104: C-1103 | B104: Chang Vaughn and Brewer LLC | C104: Chang Vaughn And Brewer Llc | D104: Process Industries | E104: Process Industries | F104: Emerging | G104: North America | H104: N. AMERICA | I104: Food & Beverage | J104: Active | K104: Active | L104: Ricky Davis II | M104: 50000 | N104: 50000
A105: C-1104 | B105: Sanchez Beck and Wood SA | C105: Sanchez Beck And Wood Sa | D105: MANUFACTURING | E105: Manufacturing | F105: Standard | G105: North America | H105: N. AMERICA | I105: Automotive | J105: Inactive | K105: Inactive | L105: Hailey Barajas | M105: $100,000 | N105: 100000
A106: C-1105 | B106: Rivera Warner and Nelson | C106: Rivera Warner And Nelson | D106: Process Industries | E106: Process Industries | F106: Emerging | G106: North America | H106: N. AMERICA | I106: Food & Beverage | J106: Active | K106: Active | L106: Bryan Lee | M106: 500000 | N106: 500000
A107: C-1106 | B107: Newton Ltd BV | C107: Newton Ltd Bv | D107: Energy & Utilities | E107: Energy & Utilities | F107: Key Account | G107: North America | H107: N. AMERICA | I107: Renewables | J107: Active | K107: Active | L107: Daniel Washington | M107: 500000 | N107: 500000
A108: C-1107 | B108: Lawrence Wolf and Carlson | C108: Lawrence Wolf And Carlson | D108: Aerospace & Defense | E108: Aerospace & Defense | F108: Emerging | G108: Latin America | H108: LATIN AMERICA | I108: Aerospace OEM | J108: Active | K108: Active | L108: Dr. Elizabeth Ward | M108: 500000 | N108: 500000
A109: C-1108 | B109: Smith-Ferguson | C109: Smith-Ferguson | D109: Research & Labs | E109: Research & Labs | F109: Key Account | G109: APAC | H109: APAC | I109: Private R&D | J109: Active | K109: Active | L109: William Tran | M109: $50,000 | N109: 50000
A110: C-1109 | B110: Raymond Little and Mullins | C110: Raymond Little And Mullins | D110: Research & Labs | E110: Research & Labs | F110: Key Account | G110: EMEA | H110: EMEA | I110: University Lab | J110: Active | K110: Active | L110: Adam Mitchell | M110: 250000 | N110: 250000
A111: C-1110 | B111: Alexander-Lopez | C111: Alexander-Lopez | D111: Energy & Utilities | E111: Energy & Utilities | F111: Standard | G111: North America | H111: N. AMERICA | I111: Power Generation | J111: Active | K111: Active | L111: Todd Woods | M111: 500000 | N111: 500000
A112: C-1111 | B112: Morales Inc Corp | C112: Morales Inc Corp | D112: Energy & Utilities | E112: Energy & Utilities | F112: Standard | G112: APAC | H112: APAC | I112: Power Generation | J112: Active | K112: Active | L112: Melissa Hernandez | M112: 500000 | N112: 500000
...

Sheet Product
A1: ProductID | B1: ProductName | C1: ProductName_Clean | D1: Category | E1: Category_Clean | F1: Family | G1: Family_Clean | H1: BU | I1: ListPrice | J1: StdVarCost_Clean | K1: StdFixedAlloc
A2: P-FS-001 | B2: On-Site Commissioning & Calibration | C2: On-Site Commissioning & Calibration | D2: Services | E2: Services | F2: Commissioning | G2: Commissioning | H2: Field Services | I2: 1850 | J2: 980 | K2: 220
A3: P-FS-002 | B3: Annual Maint. Contract - Standard | C3: Annual Maint. Contract - Standard | D3: Services | E3: Services | F3: Maintenance | G3: Maintenance | H3: Field Services | I3: 2400 | J3: 1120 | K3: 280
A4: P-FS-003 | B4: Annual Maintenance Contract - Premium | C4: Annual Maintenance Contract - Premium | D4: Services | E4: Services | F4: Maintenance | G4: Maintenance | H4: Field Services | I4: 4100 | J4: 1850 | K4: 410
A5: P-FS-004 | B5: Emergency Response Call-Out | C5: Emergency Response Call-Out | D5: SERVICES | E5: Services | F5: Emergency | G5: Emergency | H5: Field Services | I5: 3200 | J5: 1650 | K5: 350
A6: P-FS-005 | B6: Training Workshop - Operator Level | C6: Training Workshop - Operator Level | D6: Services | E6: Services | F6: Training | G6: Training | H6: Field Services | I6: 950 | J6: 420 | K6: 95
A7: P-FS-006 | B7: Remote Diagnostics Support (Annual) | C7: Remote Diagnostics Support (Annual) | D7: Services | E7: Services | F7: Support | G7: Support | H7: Field Services | I7: 1450 | J7: 380 | K7: 175
A8: P-SA-001 | B8: AetherView Analytics Plat. - Std | C8: Aetherview Analytics Plat. - Std | D8: Software | E8: Software | F8: Analytics Platform | G8: Analytics Platform | H8: Software & Analytics | I8: 4200 | J8: 185 | K8: 310
A9: P-SA-002 | B9: AetherView Analytics Platform Enterprise | C9: Aetherview Analytics Platform Enterprise | D9: Software | E9: Software | F9: Analytics Platform | G9: Analytics Platform | H9: Software & Analytics | I9: 9800 | J9: 420 | K9: 680
A10: P-SA-003 | B10: ConditionIQ Predictive Module | C10: Conditioniq Predictive Module | D10: Software | E10: Software | F10: Predictive Modules | G10: Predictive Modules | H10: Software & Analytics | I10: 2750 | J10: 95 | K10: 210
A11: P-SA-004 | B11: AssetHealth Dashboard License | C11: Assethealth Dashboard License | D11: Software | E11: Software | F11: Dashboards | G11: Dashboards | H11: Software & Analytics | I11: 1650 | J11: 65 | K11: 145
A12: P-SA-005 | B12: AetherConnect API Integration Pack | C12: Aetherconnect Api Integration Pack | D12: Software / Integration | E12: Software / Integration | F12: Integration | G12: Integration | H12: Software & Analytics | I12: 3200 | J12: 140 | K12: 255
A13: P-SI-001 | B13: AetherProbe XT-200 Temp. Sensor | C13: Aetherprobe Xt-200 Temp. Sensor | D13: SENSORS | E13: Sensors | F13: Temperature | G13: Temperature | H13: Sensors & Instruments | I13: 485 | J13: 187.5 | K13: 42
... A20: P-SI-008 | B20: VibraSense Lite Portable Analyzer | C20: Vibrasense Lite Portable Analyzer | D20: Instruments | E20: Instruments | F20: Vibration | G20: Vibration | H20: Sensors & Instruments | I20: 950 | J20: 385 | K20: 72

Sheet Cost
A1: CostID | B1: Period_Clean | C1: ProductID | D1: ProductID_Clean | E1: CostCategory | F1: CostType | G1: StandardCost | H1: ActualCost_Clean | I1: CostCenter_Clean | J1: Notes | K1: BU
A2: COST-5027 | B2: 2025-01 | C2: P-FS-001 | D2: P-FS-001 | E2: Variable COGS | F2: Variable | G2: 980 | H2: 1126.25 | I2: FS | K2: =_xlfn.XLOOKUP(Table4[[#This Row],[ProductID_Clean]],Table3[ProductID],Table3[BU],"Missing Value",0) -> Field Services | M2: ProductID | N2: Standard Variable Cost | O2: Actual Variable Cost | P2: Cost Variance vs Standard | Q2: Cost Variance vs Standard %
A3: COST-5028 | B3: 2025-01 | C3: P-FS-001 | D3: P-FS-001 | E3: Fixed Allocation | F3: Fixed | G3: 220 | H3: 217.99 | I3: FS | K3: =_xlfn.XLOOKUP(Table4[[#This Row],[ProductID_Clean]],Table3[ProductID],Table3[BU],"Missing Value",0) -> Field Services | M3: P-FS-001 | N3: =_xlfn.XLOOKUP(Table15[[#This Row],[ProductID]],Table3[ProductID],Table3[StdVarCost_Clean]) -> 980 | O3: =_xlfn.XLOOKUP(Table15[[#This Row],[ProductID]],Table4[ProductID_Clean],Table4[ActualCost_Clean]) -> 1126.25 | P3: =Table15[[#This Row],[Standard Variable Cost]]-Table15[[#This Row],[Actual Variable Cost]] -> -146.25 | Q3: =Table15[[#This Row],[Cost Variance vs Standard]]/Table15[[#This Row],[Standard Variable Cost]] -> -0.14923469
A4: COST-5065 | B4: 2025-02 | C4: P-FS-001 | D4: P-FS-001 | E4: Variable COGS | F4: Variable | G4: 980 | H4: 1124.28 | I4: FS | K4: =_xlfn.XLOOKUP(Table4[[#This Row],[ProductID_Clean]],Table3[ProductID],Table3[BU],"Missing Value",0) -> Field Services | M4: P-FS-002 | N4: =_xlfn.XLOOKUP(Table15[[#This Row],[ProductID]],Table3[ProductID],Table3[StdVarCost_Clean]) -> 1120 | O4: =_xlfn.XLOOKUP(Table15[[#This Row],[ProductID]],Table4[ProductID_Clean],Table4[ActualCost_Clean]) -> 1263.71 | P4: =Table15[[#This Row],[Standard Variable Cost]]-Table15[[#This Row],[Actual Variable Cost]] -> -143.71 | Q4: =Table15[[#This Row],[Cost Variance vs Standard]]/Table15[[#This Row],[Standard Variable Cost]] -> -0.1283125
A5: COST-5066 | B5: 2025-02 | C5: P-FS-001 | D5: P-FS-001 | E5: Fixed Allocation | F5: Fixed | G5: 220 | H5: 211.2 | I5: FS | K5: =_xlfn.XLOOKUP(Table4[[#This Row],[ProductID_Clean]],Table3[ProductID],Table3[BU],"Missing Value",0) -> Field Services | M5: P-FS-003 | N5: =_xlfn.XLOOKUP(Table15[[#This Row],[ProductID]],Table3[ProductID],Table3[StdVarCost_Clean]) -> 1850 | O5: =_xlfn.XLOOKUP(Table15[[#This Row],[ProductID]],Table4[ProductID_Clean],Table4[ActualCost_Clean]) -> 2111.06 | P5: =Table15[[#This Row],[Standard Variable Cost]]-Table15[[#This Row],[Actual Variable Cost]] -> -261.06 | Q5: =Table15[[#This Row],[Cost Variance vs Standard]]/Table15[[#This Row],[Standard Variable Cost]] -> -0.14111351
A6: COST-5103 | B6: 2025-03 | C6: P-FS-001 | D6: P-FS-001 | E6: Variable COGS | F6: Variable | G6: 980 | H6: 1108.08 | I6: FS | K6: =_xlfn.XLOOKUP(Table4[[#This Row],[ProductID_Clean]],Table3[ProductID],Table3[BU],"Missing Value",0) -> Field Services | M6: P-FS-004 | N6: =_xlfn.XLOOKUP(Table15[[#This Row],[ProductID]],Table3[ProductID],Table3[StdVarCost_Clean]) -> 1650 | O6: =_xlfn.XLOOKUP(Table15[[#This Row],[ProductID]],Table4[ProductID_Clean],Table4[ActualCost_Clean]) -> 2021.96 | P6: =Table15[[#This Row],[Standard Variable Cost]]-Table15[[#This Row],[Actual Variable Cost]] -> -371.96 | Q6: =Table15[[#This Row],[Cost Variance vs Standard]]/Table15[[#This Row],[Standard Variable Cost]] -> -0.2254303
A7: COST-5104 | B7: 2025-03 | C7: P-FS-001 | D7: P-FS-001 | E7: Fixed Allocation | F7: Fixed | G7: 220 | H7: 224.06 | I7: FS | K7: =_xlfn.XLOOKUP(Table4[[#This Row],[ProductID_Clean]],Table3[ProductID],Table3[BU],"Missing Value",0) -> Field Services | M7: P-FS-005 | N7: =_xlfn.XLOOKUP(Table15[[#This Row],[ProductID]],Table3[ProductID],Table3[StdVarCost_Clean]) -> 420 | O7: =_xlfn.XLOOKUP(Table15[[#This Row],[ProductID]],Table4[ProductID_Clean],Table4[ActualCost_Clean]) -> 408.11 | P7: =Table15[[#This Row],[Standard Variable Cost]]-Table15[[#This Row],[Actual Variable Cost]] -> 11.89 | Q7: =Table15[[#This Row],[Cost Variance vs Standard]]/Table15[[#This Row],[Standard Variable Cost]] -> 0.028309524
A8: COST-5141 | B8: 2025-04 | C8: P-FS-001 | D8: P-FS-001 | E8: Variable COGS | F8: Variable | G8: 980 | H8: 1123.73 | I8: FS | K8: =_xlfn.XLOOKUP(Table4[[#This Row],[ProductID_Clean]],Table3[ProductID],Table3[BU],"Missing Value",0) -> Field Services | M8: P-FS-006 | N8: =_xlfn.XLOOKUP(Table15[[#This Row],[ProductID]],Table3[ProductID],Table3[StdVarCost_Clean]) -> 380 | O8: =_xlfn.XLOOKUP(Table15[[#This Row],[ProductID]],Table4[ProductID_Clean],Table4[ActualCost_Clean]) -> 391.05 | P8: =Table15[[#This Row],[Standard Variable Cost]]-Table15[[#This Row],[Actual Variable Cost]] -> -11.05 | Q8: =Table15[[#This Row],[Cost Variance vs Standard]]/Table15[[#This Row],[Standard Variable Cost]] -> -0.029078947
A9: COST-5142 | B9: 2025-04 | C9: P-FS-001 | D9: P-FS-001 | E9: Fixed Allocation | F9: Fixed | G9: 220 | H9: 220.46 | I9: FS | K9: =_xlfn.XLOOKUP(Table4[[#This Row],[ProductID_Clean]],Table3[ProductID],Table3[BU],"Missing Value",0) -> Field Services | M9: P-SA-001 | N9: =_xlfn.XLOOKUP(Table15[[#This Row],[ProductID]],Table3[ProductID],Table3[StdVarCost_Clean]) -> 185 | O9: =_xlfn.XLOOKUP(Table15[[#This Row],[ProductID]],Table4[ProductID_Clean],Table4[ActualCost_Clean]) -> 200.94 | P9: =Table15[[#This Row],[Standard Variable Cost]]-Table15[[#This Row],[Actual Variable Cost]] -> -15.94 | Q9: =Table15[[#This Row],[Cost Variance vs Standard]]/Table15[[#This Row],[Standard Variable Cost]] -> -0.086162162
A10: COST-5179 | B10: 2025-05 | C10: P-FS-001 | D10: P-FS-001 | E10: Variable COGS | F10: Variable | G10: 980 | H10: 1153.56 | I10: FS | K10: =_xlfn.XLOOKUP(Table4[[#This Row],[ProductID_Clean]],Table3[ProductID],Table3[BU],"Missing Value",0) -> Field Services | M10: P-SA-002 | N10: =_xlfn.XLOOKUP(Table15[[#This Row],[ProductID]],Table3[ProductID],Table3[StdVarCost_Clean]) -> 420 | O10: =_xlfn.XLOOKUP(Table15[[#This Row],[ProductID]],Table4[ProductID_Clean],Table4[ActualCost_Clean]) -> 403.51 | P10: =Table15[[#This Row],[Standard Variable Cost]]-Table15[[#This Row],[Actual Variable Cost]] -> 16.49 | Q10: =Table15[[#This Row],[Cost Variance vs Standard]]/Table15[[#This Row],[Standard Variable Cost]] -> 0.039261905
A11: COST-5180 | B11: 2025-05 | C11: P-FS-001 | D11: P-FS-001 | E11: Fixed Allocation | F11: Fixed | G11: 220 | H11: 213.28 | I11: FS | K11: =_xlfn.XLOOKUP(Table4[[#This Row],[ProductID_Clean]],Table3[ProductID],Table3[BU],"Missing Value",0) -> Field Services | M11: P-SA-003 | N11: =_xlfn.XLOOKUP(Table15[[#This Row],[ProductID]],Table3[ProductID],Table3[StdVarCost_Clean]) -> 95 | O11: =_xlfn.XLOOKUP(Table15[[#This Row],[ProductID]],Table4[ProductID_Clean],Table4[ActualCost_Clean]) -> 93.7 | P11: =Table15[[#This Row],[Standard Variable Cost]]-Table15[[#This Row],[Actual Variable Cost]] -> 1.3 | Q11: =Table15[[#This Row],[Cost Variance vs Standard]]/Table15[[#This Row],[Standard Variable Cost]] -> 0.013684211
A12: COST-5217 | B12: 2025-06 | C12: P-FS-001 | D12: P-FS-001 | E12: Variable COGS | F12: Variable | G12: 980 | H12: 1118.05 | I12: FS | K12: =_xlfn.XLOOKUP(Table4[[#This Row],[ProductID_Clean]],Table3[ProductID],Table3[BU],"Missing Value",0) -> Field Services | M12: P-SA-004 | N12: =_xlfn.XLOOKUP(Table15[[#This Row],[ProductID]],Table3[ProductID],Table3[StdVarCost_Clean]) -> 65 | O12: =_xlfn.XLOOKUP(Table15[[#This Row],[ProductID]],Table4[ProductID_Clean],Table4[ActualCost_Clean]) -> 66.33 | P12: =Table15[[#This Row],[Standard Variable Cost]]-Table15[[#This Row],[Actual Variable Cost]] -> -1.33 | Q12: =Table15[[#This Row],[Cost Variance vs Standard]]/Table15[[#This Row],[Standard Variable Cost]] -> -0.020461538
A13: COST-5218 | B13: 2025-06 | C13: P-FS-001 | D13: P-FS-001 | E13: Fixed Allocation | F13: Fixed | G13: 220 | H13: 213.4 | I13: FS | K13: =_xlfn.XLOOKUP(Table4[[#This Row],[ProductID_Clean]],Table3[ProductID],Table3[BU],"Missing Value",0) -> Field Services | M13: P-SA-005 | N13: =_xlfn.XLOOKUP(Table15[[#This Row],[ProductID]],Table3[ProductID],Table3[StdVarCost_Clean]) -> 140 | O13: =_xlfn.XLOOKUP(Table15[[#This Row],[ProductID]],Table4[ProductID_Clean],Table4[ActualCost_Clean]) -> 253.97 | P13: =Table15[[#This Row],[Standard Variable Cost]]-Table15[[#This Row],[Actual Variable Cost]] -> -113.97 | Q13: =Table15[[#This Row],[Cost Variance vs Standard]]/Table15[[#This Row],[Standard Variable Cost]] -> -0.81407143
A14: COST-5029 | B14: 2025-01 | C14: P-FS-002 | D14: P-FS-002 | E14: Variable COGS | F14: Variable | G14: 1120 | H14: 1263.71 | I14: FS | K14: =_xlfn.XLOOKUP(Table4[[#This Row],[ProductID_Clean]],Table3[ProductID],Table3[BU],"Missing Value",0) -> Field Services | M14: P-SI-001 | N14: =_xlfn.XLOOKUP(Table15[[#This Row],[ProductID]],Table3[ProductID],Table3[StdVarCost_Clean]) -> 187.5 | O14: =_xlfn.XLOOKUP(Table15[[#This Row],[ProductID]],Table4[ProductID_Clean],Table4[ActualCost_Clean]) -> 185.89 | P14: =Table15[[#This Row],[Standard Variable Cost]]-Table15[[#This Row],[Actual Variable Cost]] -> 1.61 | Q14: =Table15[[#This Row],[Cost Variance vs Standard]]/Table15[[#This Row],[Standard Variable Cost]] -> 0.0085866667
... A21: COST-5144 | B21: 2025-04 | C21: P-FS-002 | D21: P-FS-002 | E21: Fixed Allocation | F21: Fixed | G21: 280 | H21: 290.36 | I21: FS | K21: =_xlfn.XLOOKUP(Table4[[#This Row],[ProductID_Clean]],Table3[ProductID],Table3[BU],"Missing Value",0) -> Field Services | M21: P-SI-008 | N21: =_xlfn.XLOOKUP(Table15[[#This Row],[ProductID]],Table3[ProductID],Table3[StdVarCost_Clean]) -> 385 | O21: =_xlfn.XLOOKUP(Table15[[#This Row],[ProductID]],Table4[ProductID_Clean],Table4[ActualCost_Clean]) -> 386.6 | P21: =Table15[[#This Row],[Standard Variable Cost]]-Table15[[#This Row],[Actual Variable Cost]] -> -1.6 | Q21: =Table15[[#This Row],[Cost Variance vs Standard]]/Table15[[#This Row],[Standard Variable Cost]] -> -0.0041558442
A22: COST-5181 | B22: 2025-05 | C22: P-FS-002 | D22: P-FS-002 | E22: Variable COGS | F22: Variable | G22: 1120 | H22: 1247.2 | I22: FS | K22: =_xlfn.XLOOKUP(Table4[[#This Row],[ProductID_Clean]],Table3[ProductID],Table3[BU],"Missing Value",0) -> Field Services
A23: COST-5182 | B23: 2025-05 | C23: P-FS-002 | D23: P-FS-002 | E23: fixed allocation | F23: Fixed | G23: 280 | H23: 283.91 | I23: FS | K23: =_xlfn.XLOOKUP(Table4[[#This Row],[ProductID_Clean]],Table3[ProductID],Table3[BU],"Missing Value",0) -> Field Services | M23: Negative = Unfavorable / Overrun; Positive = Favorable / Saving
A24: COST-5219 | B24: 2025-06 | C24: P-FS-002 | D24: P-FS-002 | E24: Variable COGS | F24: Variable | G24: 1120 | H24: 1271.29 | I24: FS | K24: =_xlfn.XLOOKUP(Table4[[#This Row],[ProductID_Clean]],Table3[ProductID],Table3[BU],"Missing Value",0) -> Field Services | M24: Note: P-SA-005 excluded from the cost-overrun ranking because January 2025 Variable COGS is missing. Complete monthly Actual Variable Cost data is required for a full H1 comparison.
A25: COST-5220 | B25: 2025-06 | C25: P-FS-002 | D25: P-FS-002 | E25: Fixed Allocation | F25: Fixed | G25: 280 | H25: 296.85 | I25: FS | K25: =_xlfn.XLOOKUP(Table4[[#This Row],[ProductID_Clean]],Table3[ProductID],Table3[BU],"Missing Value",0) -> Field Services
A26: COST-5031 | B26: 2025-01 | C26: P-FS-003 | D26: P-FS-003 | E26: Variable COGS | F26: Variable | G26: 1850 | H26: 2111.06 | I26: FS | K26: =_xlfn.XLOOKUP(Table4[[#This Row],[ProductID_Clean]],Table3[ProductID],Table3[BU],"Missing Value",0) -> Field Services
A27: COST-5032 | B27: 2025-01 | C27: P-FS-003 | D27: P-FS-003 | E27: Fixed Allocation | F27: Fixed | G27: 410 | H27: 424.87 | I27: FS | K27: =_xlfn.XLOOKUP(Table4[[#This Row],[ProductID_Clean]],Table3[ProductID],Table3[BU],"Missing Value",0) -> Field Services
A28: COST-5070 | B28: 2025-02 | C28: P-FS-003 | D28: P-FS-003 | E28: Fixed Allocation | F28: Fixed | G28: 410 | H28: 415.32 | I28: FS | K28: =_xlfn.XLOOKUP(Table4[[#This Row],[ProductID_Clean]],Table3[ProductID],Table3[BU],"Missing Value",0) -> Field Services
A29: COST-5069 | B29: 2025-02 | C29: P-FS-003 | D29: P-FS-003 | E29: Variable COGS | F29: Variable | G29: 1850 | H29: 2067.25 | I29: FS | K29: =_xlfn.XLOOKUP(Table4[[#This Row],[ProductID_Clean]],Table3[ProductID],Table3[BU],"Missing Value",0) -> Field Services | M29: Cost Category | N29: Actual Cost | O29: % of Total Overhead
A30: COST-5107 | B30: 2025-03 | C30: P-FS-003 | D30: P-FS-003 | E30: Variable COGS | F30: Variable | G30: 1850 | H30: 2105 | I30: FS | K30: =_xlfn.XLOOKUP(Table4[[#This Row],[ProductID_Clean]],Table3[ProductID],Table3[BU],"Missing Value",0) -> Field Services | M30: Regional Sales Overhead | N30: =SUMIF(Table4[CostCategory],Table18[[#This Row],[Cost Category]],Table4[ActualCost_Clean]) -> 884457.01 | O30: =Table18[[#This Row],[Actual Cost]]/Table18[[#Totals],[Actual Cost]] -> 0.37458513
A31: COST-5108 | B31: 2025-03 | C31: P-FS-003 | D31: P-FS-003 | E31: Fixed Allocation | F31: Fixed | G31: 410 | H31: 408.18 | I31: FS | K31: =_xlfn.XLOOKUP(Table4[[#This Row],[ProductID_Clean]],Table3[ProductID],Table3[BU],"Missing Value",0) -> Field Services | M31: Shared R&D Allocation | N31: =SUMIF(Table4[CostCategory],Table18[[#This Row],[Cost Category]],Table4[ActualCost_Clean]) -> 619088.43 | O31: =Table18[[#This Row],[Actual Cost]]/Table18[[#Totals],[Actual Cost]] -> 0.26219626
A32: COST-5145 | B32: 2025-04 | C32: P-FS-003 | D32: P-FS-003 | E32: Variable COGS | F32: Variable | G32: 1850 | H32: 2112.37 | I32: FS | K32: =_xlfn.XLOOKUP(Table4[[#This Row],[ProductID_Clean]],Table3[ProductID],Table3[BU],"Missing Value",0) -> Field Services | M32: Logistics & Distribution | N32: =SUMIF(Table4[CostCategory],Table18[[#This Row],[Cost Category]],Table4[ActualCost_Clean]) -> 466498.32 | O32: =Table18[[#This Row],[Actual Cost]]/Table18[[#Totals],[Actual Cost]] -> 0.19757131
A33: COST-5146 | B33: 2025-04 | C33: P-FS-003 | D33: P-FS-003 | E33: Fixed Allocation | F33: Fixed | G33: 410 | H33: 434.23 | I33: FS | K33: =_xlfn.XLOOKUP(Table4[[#This Row],[ProductID_Clean]],Table3[ProductID],Table3[BU],"Missing Value",0) -> Field Services | M33: Quality Assurance | N33: =SUMIF(Table4[CostCategory],Table18[[#This Row],[Cost Category]],Table4[ActualCost_Clean]) -> 296005.53 | O33: =Table18[[#This Row],[Actual Cost]]/Table18[[#Totals],[Actual Cost]] -> 0.12536423
A34: COST-5183 | B34: 2025-05 | C34: P-FS-003 | D34: P-FS-003 | E34: Variable COGS | F34: Variable | G34: 1850 | H34: 2122.36 | I34: FS | K34: =_xlfn.XLOOKUP(Table4[[#This Row],[ProductID_Clean]],Table3[ProductID],Table3[BU],"Missing Value",0) -> Field Services | M34: Variable COGS | N34: =SUMIF(Table4[CostCategory],Table18[[#This Row],[Cost Category]],Table4[ActualCost_Clean]) -> 72363.06 | O34: =Table18[[#This Row],[Actual Cost]]/Table18[[#Totals],[Actual Cost]] -> 0.030647194
A35: COST-5184 | B35: 2025-05 | C35: P-FS-003 | D35: P-FS-003 | E35: Fixed Allocation | F35: Fixed | G35: 410 | H35: 393.61 | I35: FS | K35: =_xlfn.XLOOKUP(Table4[[#This Row],[ProductID_Clean]],Table3[ProductID],Table3[BU],"Missing Value",0) -> Field Services | M35: Fixed Allocation | N35: =SUMIF(Table4[CostCategory],Table18[[#This Row],[Cost Category]],Table4[ActualCost_Clean]) -> 22751.9 | O35: =Table18[[#This Row],[Actual Cost]]/Table18[[#Totals],[Actual Cost]] -> 0.009635882
A36: COST-5221 | B36: 2025-06 | C36: P-FS-003 | D36: P-FS-003 | E36: Variable COGS | F36: Variable | G36: 1850 | H36: 2152.22 | I36: FS | K36: =_xlfn.XLOOKUP(Table4[[#This Row],[ProductID_Clean]],Table3[ProductID],Table3[BU],"Missing Value",0) -> Field Services | M36: Total | N36: =SUBTOTAL(109,Table18[Actual Cost]) -> 2361164.2 | O36: =SUBTOTAL(109,Table18[% of Total Overhead]) -> 1
A37: COST-5222 | B37: 2025-06 | C37: P-FS-003 | D37: P-FS-003 | E37: Fixed Allocation | F37: Fixed | G37: 410 | H37: 393.65 | I37: FS | K37: =_xlfn.XLOOKUP(Table4[[#This Row],[ProductID_Clean]],Table3[ProductID],Table3[BU],"Missing Value",0) -> Field Services
A38: COST-5033 | B38: 2025-01 | C38: P-FS-004 | D38: P-FS-004 | E38: Variable COGS | F38: Variable | G38: 1650 | H38: 2021.96 | I38: FS | K38: =_xlfn.XLOOKUP(Table4[[#This Row],[ProductID_Clean]],Table3[ProductID],Table3[BU],"Missing Value",0) -> Field Services | M38: Notes | N38: Actual Overhead Cost | O38: % of Total Overhead
A39: COST-5034 | B39: 2025-01 | C39: P-FS-004 | D39: P-FS-004 | E39: Fixed Allocation | F39: Fixed | G39: 350 | H39: 369.2 | I39: FS | K39: =_xlfn.XLOOKUP(Table4[[#This Row],[ProductID_Clean]],Table3[ProductID],Table3[BU],"Missing Value",0) -> Field Services | M39: Blank | N39: 95114.96 | O39: =Table19[[#This Row],[Actual Overhead Cost]]/Table19[[#Totals],[Actual Overhead Cost]] -> 0.040283076
A40: COST-5071 | B40: 2025-02 | C40: P-FS-004 | D40: P-FS-004 | E40: Variable COGS | F40: Variable | G40: 1650 | H40: 2067.88 | I40: FS | K40: =_xlfn.XLOOKUP(Table4[[#This Row],[ProductID_Clean]],Table3[ProductID],Table3[BU],"Missing Value",0) -> Field Services | M40: North America overhead | N40: =SUMIF(Table4[Notes],Table19[[#This Row],[Notes]],Table4[ActualCost_Clean]) -> 818074.55 | O40: =Table19[[#This Row],[Actual Overhead Cost]]/Table19[[#Totals],[Actual Overhead Cost]] -> 0.34647084
A41: COST-5072 | B41: 2025-02 | C41: P-FS-004 | D41: P-FS-004 | E41: Fixed Allocation | F41: Fixed | G41: 350 | H41: 341.28 | I41: FS | K41: =_xlfn.XLOOKUP(Table4[[#This Row],[ProductID_Clean]],Table3[ProductID],Table3[BU],"Missing Value",0) -> Field Services | M41: EMEA overhead | N41: =SUMIF(Table4[Notes],Table19[[#This Row],[Notes]],Table4[ActualCost_Clean]) -> 589408.46 | O41: =Table19[[#This Row],[Actual Overhead Cost]]/Table19[[#Totals],[Actual Overhead Cost]] -> 0.2496262
A42: COST-5109 | B42: 2025-03 | C42: P-FS-004 | D42: P-FS-004 | E42: Variable COGS | F42: Variable | G42: 1650 | H42: 2041.18 | I42: FS | K42: =_xlfn.XLOOKUP(Table4[[#This Row],[ProductID_Clean]],Table3[ProductID],Table3[BU],"Missing Value",0) -> Field Services | M42: APAC overhead | N42: =SUMIF(Table4[Notes],Table19[[#This Row],[Notes]],Table4[ActualCost_Clean]) -> 523502.7 | O42: =Table19[[#This Row],[Actual Overhead Cost]]/Table19[[#Totals],[Actual Overhead Cost]] -> 0.2217138
A43: COST-5110 | B43: 2025-03 | C43: P-FS-004 | D43: P-FS-004 | E43: Fixed Allocation | F43: Fixed | G43: 350 | H43: 338.29 | I43: FS | K43: =_xlfn.XLOOKUP(Table4[[#This Row],[ProductID_Clean]],Table3[ProductID],Table3[BU],"Missing Value",0) -> Field Services | M43: Latin America overhead | N43: =SUMIF(Table4[Notes],Table19[[#This Row],[Notes]],Table4[ActualCost_Clean]) -> 335063.58 | O43: =Table19[[#This Row],[Actual Overhead Cost]]/Table19[[#Totals],[Actual Overhead Cost]] -> 0.14190609
A44: COST-5147 | B44: 2025-04 | C44: P-FS-004 | D44: P-FS-004 | E44: Variable COGS | F44: Variable | G44: 1650 | H44: 2023.48 | I44: FS | K44: =_xlfn.XLOOKUP(Table4[[#This Row],[ProductID_Clean]],Table3[ProductID],Table3[BU],"Missing Value",0) -> Field Services | M44: Total | N44: =SUBTOTAL(109,Table19[Actual Overhead Cost]) -> 2361164.2 | O44: =SUBTOTAL(109,Table19[% of Total Overhead]) -> 1
A45: COST-5148 | B45: 2025-04 | C45: P-FS-004 | D45: P-FS-004 | E45: Fixed Allocation | F45: Fixed | G45: 350 | H45: 350.82 | I45: FS | K45: =_xlfn.XLOOKUP(Table4[[#This Row],[ProductID_Clean]],Table3[ProductID],Table3[BU],"Missing Value",0) -> Field Services
A46: COST-5185 | B46: 2025-05 | C46: P-FS-004 | D46: P-FS-004 | E46: Variable COGS | F46: Variable | G46: 1650 | H46: 2070.92 | I46: FS | K46: =_xlfn.XLOOKUP(Table4[[#This Row],[ProductID_Clean]],Table3[ProductID],Table3[BU],"Missing Value",0) -> Field Services
A47: COST-5186 | B47: 2025-05 | C47: P-FS-004 | D47: P-FS-004 | E47: Fixed Allocation | F47: Fixed | G47: 350 | H47: 345.26 | I47: FS | K47: =_xlfn.XLOOKUP(Table4[[#This Row],[ProductID_Clean]],Table3[ProductID],Table3[BU],"Missing Value",0) -> Field Services
A48: COST-5224 | B48: 2025-06 | C48: P-FS-004 | D48: P-FS-004 | E48: fixed allocation | F48: Fixed | G48: 350 | H48: 372.27 | I48: FS | K48: =_xlfn.XLOOKUP(Table4[[#This Row],[ProductID_Clean]],Table3[ProductID],Table3[BU],"Missing Value",0) -> Field Services
A49: COST-5223 | B49: 2025-06 | C49: P-FS-004 | D49: P-FS-004 | E49: variable cogs | F49: Variable | G49: 1650 | H49: 2059.78 | I49: FS | K49: =_xlfn.XLOOKUP(Table4[[#This Row],[ProductID_Clean]],Table3[ProductID],Table3[BU],"Missing Value",0) -> Field Services
A50: COST-5035 | B50: 2025-01 | C50: P-FS-005 | D50: P-FS-005 | E50: Variable COGS | F50: Variable | G50: 420 | H50: 408.11 | I50: FS | K50: =_xlfn.XLOOKUP(Table4[[#This Row],[ProductID_Clean]],Table3[ProductID],Table3[BU],"Missing Value",0) -> Field Services
A51: COST-5036 | B51: 2025-01 | C51: P-FS-005 | D51: P-FS-005 | E51: Fixed Allocation | F51: Fixed | G51: 95 | H51: 95.2 | I51: FS | K51: =_xlfn.XLOOKUP(Table4[[#This Row],[ProductID_Clean]],Table3[ProductID],Table3[BU],"Missing Value",0) -> Field Services
A52: COST-5073 | B52: 2025-02 | C52: P-FS-005 | D52: P-FS-005 | E52: Variable COGS | F52: Variable | G52: 420 | H52: 432.84 | I52: FS | K52: =_xlfn.XLOOKUP(Table4[[#This Row],[ProductID_Clean]],Table3[ProductID],Table3[BU],"Missing Value",0) -> Field Services
A53: COST-5074 | B53: 2025-02 | C53: P-FS-005 | D53: P-FS-005 | E53: Fixed Allocation | F53: Fixed | G53: 95 | H53: 90.78 | I53: FS | K53: =_xlfn.XLOOKUP(Table4[[#This Row],[ProductID_Clean]],Table3[ProductID],Table3[BU],"Missing Value",0) -> Field Services
A54: COST-5111 | B54: 2025-03 | C54: P-FS-005 | D54: P-FS-005 | E54: Variable COGS | F54: Variable | G54: 420 | H54: 436.29 | I54: FS | K54: =_xlfn.XLOOKUP(Table4[[#This Row],[ProductID_Clean]],Table3[ProductID],Table3[BU],"Missing Value",0) -> Field Services
A55: COST-5112 | B55: 2025-03 | C55: P-FS-005 | D55: P-FS-005 | E55: fixed allocation | F55: Fixed | G55: 95 | H55: 92.08 | I55: FS | K55: =_xlfn.XLOOKUP(Table4[[#This Row],[ProductID_Clean]],Table3[ProductID],Table3[BU],"Missing Value",0) -> Field Services
A56: COST-5149 | B56: 2025-04 | C56: P-FS-005 | D56: P-FS-005 | E56: Variable COGS | F56: Variable | G56: 420 | H56: 443.31 | I56: FS | K56: =_xlfn.XLOOKUP(Table4[[#This Row],[ProductID_Clean]],Table3[ProductID],Table3[BU],"Missing Value",0) -> Field Services
... A225: COST-5206 | B225: 2025-06 | C225: P-SI-008 | D225: P-SI-008 | E225: fixed allocation | F225: Fixed | G225: 72 | H225: 74.59 | I225: SI | K225: =_xlfn.XLOOKUP(Table4[[#This Row],[ProductID_Clean]],Table3[ProductID],Table3[BU],"Missing Value",0) -> Sensors & Instruments
A226: COST-5200 | B226: 2025-06 | D226: Missing Value | E226: Fixed Allocation | F226: Fixed | G226: 78 | H226: 74.95 | I226: SI | K226: =_xlfn.XLOOKUP(Table4[[#This Row],[ProductID_Clean]],Table3[ProductID],Table3[BU],"Missing Value",0) -> Missing Value
A227: COST-5231 | B227: 2025-01 | D227: Missing Value | E227: Logistics & Distribution | F227: Variable | G227: 35630.75 | H227: 36732.73 | I227: Missing Value | J227: North America overhead | K227: =_xlfn.XLOOKUP(Table4[[#This Row],[ProductID_Clean]],Table3[ProductID],Table3[BU],"Missing Value",0) -> Missing Value
A228: COST-5235 | B228: 2025-01 | D228: Missing Value | E228: Logistics & Distribution | F228: Variable | G228: 26061.32 | H228: 26867.34 | I228: EM | J228: EMEA overhead | K228: =_xlfn.XLOOKUP(Table4[[#This Row],[ProductID_Clean]],Table3[ProductID],Table3[BU],"Missing Value",0) -> Missing Value
A229: COST-5239 | B229: 2025-01 | D229: Missing Value | E229: Logistics & Distribution | F229: Variable | G229: 21026.97 | H229: 21677.29 | I229: AP | J229: APAC overhead | K229: =_xlfn.XLOOKUP(Table4[[#This Row],[ProductID_Clean]],Table3[ProductID],Table3[BU],"Missing Value",0) -> Missing Value
A230: COST-5243 | B230: 2025-01 | D230: Missing Value | E230: Logistics & Distribution | F230: Variable | G230: 12067.01 | H230: 12440.22 | I230: LA | J230: Latin America overhead | K230: =_xlfn.XLOOKUP(Table4[[#This Row],[ProductID_Clean]],Table3[ProductID],Table3[BU],"Missing Value",0) -> Missing Value
A231: COST-5247 | B231: 2025-02 | D231: Missing Value | E231: Logistics & Distribution | F231: Variable | G231: 23656.1 | H231: 24387.73 | I231: Missing Value | J231: North America overhead | K231: =_xlfn.XLOOKUP(Table4[[#This Row],[ProductID_Clean]],Table3[ProductID],Table3[BU],"Missing Value",0) -> Missing Value
A232: COST-5251 | B232: 2025-02 | D232: Missing Value | E232: Logistics & Distribution | F232: Variable | G232: 17650.28 | H232: 18196.16 | I232: EM | J232: EMEA overhead | K232: =_xlfn.XLOOKUP(Table4[[#This Row],[ProductID_Clean]],Table3[ProductID],Table3[BU],"Missing Value",0) -> Missing Value
A233: COST-5255 | B233: 2025-02 | D233: Missing Value | E233: Logistics & Distribution | F233: Variable | G233: 19300.01 | H233: 19896.92 | I233: AP | J233: APAC overhead | K233: =_xlfn.XLOOKUP(Table4[[#This Row],[ProductID_Clean]],Table3[ProductID],Table3[BU],"Missing Value",0) -> Missing Value
A234: COST-5259 | B234: 2025-02 | D234: Missing Value | E234: Logistics & Distribution | F234: Variable | G234: 13273.11 | H234: 13683.62 | I234: LA | J234: Latin America overhead | K234: =_xlfn.XLOOKUP(Table4[[#This Row],[ProductID_Clean]],Table3[ProductID],Table3[BU],"Missing Value",0) -> Missing Value
A235: COST-5263 | B235: 2025-03 | D235: Missing Value | E235: logistics & distribution | F235: Variable | G235: 35121.14 | H235: 36207.36 | I235: Missing Value | J235: North America overhead | K235: =_xlfn.XLOOKUP(Table4[[#This Row],[ProductID_Clean]],Table3[ProductID],Table3[BU],"Missing Value",0) -> Missing Value
A236: COST-5267 | B236: 2025-03 | D236: Missing Value | E236: Logistics & Distribution | F236: Variable | G236: 15215.81 | H236: 15686.4 | I236: EM | J236: EMEA overhead | K236: =_xlfn.XLOOKUP(Table4[[#This Row],[ProductID_Clean]],Table3[ProductID],Table3[BU],"Missing Value",0) -> Missing Value
A237: COST-5271 | B237: 2025-03 | D237: Missing Value | E237: Logistics & Distribution | F237: Variable | G237: 16281.77 | H237: 16785.33 | I237: AP | J237: APAC overhead | K237: =_xlfn.XLOOKUP(Table4[[#This Row],[ProductID_Clean]],Table3[ProductID],Table3[BU],"Missing Value",0) -> Missing Value
A238: COST-5275 | B238: 2025-03 | D238: Missing Value | E238: Logistics & Distribution | F238: Variable | G238: 10513.45 | H238: 10838.61 | I238: LA | J238: Latin America overhead | K238: =_xlfn.XLOOKUP(Table4[[#This Row],[ProductID_Clean]],Table3[ProductID],Table3[BU],"Missing Value",0) -> Missing Value
... A322: COST-5322 | B322: 2025-06 | D322: Missing Value | E322: shared r&d allocation | F322: Fixed | G322: 15329.79 | H322: 15803.91 | I322: LA | J322: Latin America overhead | K322: =_xlfn.XLOOKUP(Table4[[#This Row],[ProductID_Clean]],Table3[ProductID],Table3[BU],"Missing Value",0) -> Missing Value
A323: COST-5025 | B323: 2025-01 | D323: Missing Value | E323: Variable COGS | F323: Variable | G323: 140 | H323: 137.22 | I323: SA | K323: =_xlfn.XLOOKUP(Table4[[#This Row],[ProductID_Clean]],Table3[ProductID],Table3[BU],"Missing Value",0) -> Missing Value
A324: COST-5039 | B324: 2025-02 | D324: Missing Value | E324: Variable COGS | F324: Variable | G324: 187.5 | H324: 189.3 | I324: SI | K324: =_xlfn.XLOOKUP(Table4[[#This Row],[ProductID_Clean]],Table3[ProductID],Table3[BU],"Missing Value",0) -> Missing Value
A325: COST-5121 | B325: 2025-04 | D325: Missing Value | E325: Variable COGS | F325: Variable | G325: 980 | H325: 1149.75 | I325: SI | K325: =_xlfn.XLOOKUP(Table4[[#This Row],[ProductID_Clean]],Table3[ProductID],Table3[BU],"Missing Value",0) -> Missing Value
A326: Total | G326: =SUBTOTAL(109,Table4[StandardCost]) -> 2285412.8 | H326: =SUBTOTAL(109,Table4[ActualCost_Clean]) -> 2361164.3

Sheet Budget
A1: BudgetID | B1: Period | C1: BusinessUnit | D1: BusinessUnit_clean | E1: Region_Clean | F1: RevenueBudget | G1: VariableCostBudget | H1: FixedCostBudget | I1: ContributionProfitTarget | J1: OperatingProfitTarget | K1: Version
A2: BUD-2025-01-SI-NA | B2: 2025-01 | C2: Sensors & Instruments | D2: =SUBSTITUTE(SUBSTITUTE(TRIM(Table5[[#This Row],[BusinessUnit]]),"Software and Analytics","Software & Analytics"),"Sensors and Instruments","Sensors & Instruments") -> Sensors & Instruments | E2: N. AMERICA | F2: 359017 | G2: 140163 | H2: 41528 | I2: 218854 | J2: 177326 | K2: Board Approved H1 2025
A3: BUD-2025-01-SI-EM | B3: 2025-01 | C3: Sensors & Instruments | D3: =SUBSTITUTE(SUBSTITUTE(TRIM(Table5[[#This Row],[BusinessUnit]]),"Software and Analytics","Software & Analytics"),"Sensors and Instruments","Sensors & Instruments") -> Sensors & Instruments | E3: EMEA | F3: 248509 | G3: 99942 | H3: 28770 | I3: 148567 | J3: 119797 | K3: Board Approved H1 2025
A4: BUD-2025-01-SI-AP | B4: 2025-01 | C4: Sensors & Instruments | D4: =SUBSTITUTE(SUBSTITUTE(TRIM(Table5[[#This Row],[BusinessUnit]]),"Software and Analytics","Software & Analytics"),"Sensors and Instruments","Sensors & Instruments") -> Sensors & Instruments | E4: APAC | F4: 165364 | G4: 65135 | H4: 19988 | I4: 100229 | J4: 80241 | K4: Board Approved H1 2025
A5: BUD-2025-01-SI-LA | B5: 2025-01 | C5: Sensors & Instruments | D5: =SUBSTITUTE(SUBSTITUTE(TRIM(Table5[[#This Row],[BusinessUnit]]),"Software and Analytics","Software & Analytics"),"Sensors and Instruments","Sensors & Instruments") -> Sensors & Instruments | E5: LATIN AMERICA | F5: 72840 | G5: 29238 | H5: 8670 | I5: 43602 | J5: 34932 | K5: Board Approved H1 2025
A6: BUD-2025-01-SA-NA | B6: 2025-01 | C6: Software & Analytics | D6: =SUBSTITUTE(SUBSTITUTE(TRIM(Table5[[#This Row],[BusinessUnit]]),"Software and Analytics","Software & Analytics"),"Sensors and Instruments","Sensors & Instruments") -> Software & Analytics | E6: N. AMERICA | F6: 265815 | G6: 14363 | H6: 46872 | I6: 251452 | J6: 204580 | K6: Board Approved H1 2025
A7: BUD-2025-01-SA-EM | B7: 2025-01 | C7: Software and Analytics | D7: =SUBSTITUTE(SUBSTITUTE(TRIM(Table5[[#This Row],[BusinessUnit]]),"Software and Analytics","Software & Analytics"),"Sensors and Instruments","Sensors & Instruments") -> Software & Analytics | E7: EMEA | F7: 165690 | G7: 9017 | H7: 28485 | I7: 156673 | J7: 128188 | K7: Board Approved H1 2025
A8: BUD-2025-01-SA-AP | B8: 2025-01 | C8: Software & Analytics | D8: =SUBSTITUTE(SUBSTITUTE(TRIM(Table5[[#This Row],[BusinessUnit]]),"Software and Analytics","Software & Analytics"),"Sensors and Instruments","Sensors & Instruments") -> Software & Analytics | E8: APAC | F8: 100757 | G8: 5563 | H8: 18067 | I8: 95194 | J8: 77127 | K8: Board Approved H1 2025
A9: BUD-2025-01-SA-LA | B9: 2025-01 | C9: Software & Analytics | D9: =SUBSTITUTE(SUBSTITUTE(TRIM(Table5[[#This Row],[BusinessUnit]]),"Software and Analytics","Software & Analytics"),"Sensors and Instruments","Sensors & Instruments") -> Software & Analytics | E9: LATIN AMERICA | F9: 39651 | G9: 2223 | H9: 7049 | I9: 37428 | J9: 30379 | K9: Board Approved H1 2025
A10: BUD-2025-01-FS-NA | B10: 2025-01 | C10: Field Services | D10: =SUBSTITUTE(SUBSTITUTE(TRIM(Table5[[#This Row],[BusinessUnit]]),"Software and Analytics","Software & Analytics"),"Sensors and Instruments","Sensors & Instruments") -> Field Services | E10: N. AMERICA | F10: 158467 | G10: 76147 | H10: 25168 | I10: 82320 | J10: 57152 | K10: Board Approved H1 2025
A11: BUD-2025-01-FS-EM | B11: 2025-01 | C11: Field Services | D11: =SUBSTITUTE(SUBSTITUTE(TRIM(Table5[[#This Row],[BusinessUnit]]),"Software and Analytics","Software & Analytics"),"Sensors and Instruments","Sensors & Instruments") -> Field Services | E11: EMEA | F11: 100593 | G11: 48664 | H11: 15344 | I11: 51929 | J11: 36585 | K11: Board Approved H1 2025
A12: BUD-2025-01-FS-AP | B12: 2025-01 | C12: Field Services | D12: =SUBSTITUTE(SUBSTITUTE(TRIM(Table5[[#This Row],[BusinessUnit]]),"Software and Analytics","Software & Analytics"),"Sensors and Instruments","Sensors & Instruments") -> Field Services | E12: APAC | F12: 66512 | G12: 31614 | H12: 10349 | I12: 34898 | J12: 24549 | K12: Board Approved H1 2025
A13: BUD-2025-01-FS-LA | B13: 2025-01 | C13: Field Services | D13: =SUBSTITUTE(SUBSTITUTE(TRIM(Table5[[#This Row],[BusinessUnit]]),"Software and Analytics","Software & Analytics"),"Sensors and Instruments","Sensors & Instruments") -> Field Services | E13: LATIN AMERICA | F13: 32590 | G13: 15505 | H13: 5109 | I13: 17085 | J13: 11976 | K13: Board Approved H1 2025
... A73: BUD-2025-06-FS-LA | B73: 2025-06 | C73: Field Services | D73: =SUBSTITUTE(SUBSTITUTE(TRIM(Table5[[#This Row],[BusinessUnit]]),"Software and Analytics","Software & Analytics"),"Sensors and Instruments","Sensors & Instruments") -> Field Services | E73: LATIN AMERICA | F73: 38837 | G73: 18144 | H73: 5996 | I73: 20693 | J73: 14697 | K73: Board Approved H1 2025
A74: Total | F74: =SUBTOTAL(109,Table5[RevenueBudget]) -> 11524128 | G74: =SUBTOTAL(109,Table5[VariableCostBudget]) -> 3455918 | H74: =SUBTOTAL(109,Table5[FixedCostBudget]) -> 1652058 | I74: =SUBTOTAL(109,Table5[ContributionProfitTarget]) -> 8068210 | J74: =SUBTOTAL(109,Table5[OperatingProfitTarget]) -> 6416152 | K74: =SUBTOTAL(103,Table5[Version]) -> 72

Sheet Sheet2

Sheet Org_Reference
A1: Column1 | B1: Column2 | C1: Column3 | D1: Column4 | E1: Column5 | F1: Column6 | G1: Column7 | H1: Column8
A2: BusinessUnit | B2: Region | C2: RegionCode | D2: RegionCode_Clean | E2: RegionCode2 | F2: PrimaryManager | G2: FinancePartner | H2: CostCenterPrefix
A3: Sensors & Instruments | B3: SI | C3: North America | D3: N. AMERICA | F3: Michael Flynn | G3: Rebecca Herrera | H3: SI-NA
A4: Sensors & Instruments | B4: SI | C4: EMEA | D4: EMEA | E4: EM | F4: Craig Wilson | G4: Katherine Church | H4: SI-EM
A5: Sensors & Instruments | B5: SI | C5: APAC | D5: APAC | E5: AP | F5: James Long | G5: Harold Ellis | H5: SI-AP
A6: Sensors & Instruments | B6: SI | C6: Latin America | D6: Latin America | E6: LA | F6: Michael Mcbride | G6: Leslie Powers | H6: SI-LA
A7: Software & Analytics | B7: SA | C7: North America | D7: N. AMERICA | F7: David Wilson | G7: Charles Price | H7: SA-NA
A8: Software & Analytics | B8: SA | C8: EMEA | D8: EMEA | E8: EM | F8: Laura Henderson | G8: Mr. Thomas Arias | H8: SA-EM
A9: Software & Analytics | B9: SA | C9: APAC | D9: APAC | E9: AP | F9: Christopher Roberts | G9: Ryan Harvey | H9: SA-AP
A10: Software & Analytics | B10: SA | C10: Latin America | D10: Latin America | E10: LA | F10: Tiffany Washington | G10: James Hoffman | H10: SA-LA
A11: Field Services | B11: FS | C11: North America | D11: N. AMERICA | F11: Jennifer Vasquez | G11: Jill Jackson | H11: FS-NA
A12: Field Services | B12: FS | C12: EMEA | D12: EMEA | E12: EM | F12: Rebecca Walker | G12: Danny Roberts | H12: FS-EM
A13: Field Services | B13: FS | C13: APAC | D13: APAC | E13: AP | F13: Krystal Barton | G13: Jorge Armstrong III | H13: FS-AP
A14: Field Services | B14: FS | C14: Latin America | D14: Latin America | E14: LA | F14: Wendy Weaver | G14: Olivia Alexander | H14: FS-LA

Sheet FX
A1: Period | B1: Currency | C1: RateToUSD
A2: 2025-01 | B2: USD | C2: 1
A3: 2025-01 | B3: EUR | C3: 1.0827
A4: 2025-01 | B4: GBP | C4: 1.3004
A5: 2025-02 | B5: USD | C5: 1
A6: 2025-02 | B6: EUR | C6: 1.1054
A7: 2025-02 | B7: GBP | C7: 1.3132
A8: 2025-03 | B8: USD | C8: 1
A9: 2025-03 | B9: EUR | C9: 1.1038
A10: 2025-03 | B10: GBP | C10: 1.2808
A11: 2025-04 | B11: USD | C11: 1
A12: 2025-04 | B12: EUR | C12: 1.083
A13: 2025-04 | B13: GBP | C13: 1.3031
... A19: 2025-06 | B19: GBP | C19: 1.2746

Sheet Region_Profitability
A1: ProductID | B1: Region | C1: 1/1/2025 | D1: 2/1/2025 | E1: 3/1/2025 | F1: 4/1/2025 | G1: 5/1/2025 | H1: 6/1/2025 | I1: H1 Total | L1: ProductID | M1: Region | N1: 2025-01 | O1: 2025-02 | P1: 2025-03 | Q1: 2025-04 | R1: 2025-05 | S1: 2025-06 | V1: ProductID | W1: Region | X1: 25-Jan | Y1: 25-Feb | Z1: 25-Mar | AA1: 25-Apr | AB1: 25-May | AC1: 25-Jun | AD1: H1 Variable Cost | AG1: ProductID | AH1: Region | AI1: 2025-01 | AJ1: 2025-02 | AK1: 2025-03 | AL1: 2025-04 | AM1: 2025-05 | AN1: 2025-06 | AQ1: ProductID | AR1: Region | AS1: 25-Jan | AT1: 25-Feb | AU1: 25-Mar | AV1: 25-Apr | AW1: 25-May | AX1: 25-Jun | AY1: H1 Fixed Cost | BB1: ProductID | BC1: Region | BD1: 25-Jan | BE1: 25-Feb | BF1: 25-Mar | BG1: 25-Apr | BH1: 25-May | BI1: 25-Jun | BJ1: H1 COGS
A2: P-FS-001 | B2: N. AMERICA | C2: =SUMIFS(Table1[Quantity],Table1[ProductID],Table33[[#This Row],[ProductID]],Table1[RegionClean_],Table33[[#This Row],[Region]],Table1[TransactionDate_Clean],">"&EOMONTH($C$1,-1),Table1[TransactionDate_Clean],"<="&EOMONTH($C$1,0)) -> 3 | D2: =SUMIFS(Table1[Quantity],Table1[ProductID],Table33[[#This Row],[ProductID]],Table1[RegionClean_],Table33[[#This Row],[Region]],Table1[TransactionDate_Clean],">"&EOMONTH($D$1,-1),Table1[TransactionDate_Clean],"<="&EOMONTH($D$1,0)) -> 4 | E2: =SUMIFS(Table1[Quantity],Table1[ProductID],Table33[[#This Row],[ProductID]],Table1[RegionClean_],Table33[[#This Row],[Region]],Table1[TransactionDate_Clean],">"&EOMONTH($E$1,-1),Table1[TransactionDate_Clean],"<="&EOMONTH($E$1,0)) -> 6 | F2: =SUMIFS(Table1[Quantity],Table1[ProductID],Table33[[#This Row],[ProductID]],Table1[RegionClean_],Table33[[#This Row],[Region]],Table1[TransactionDate_Clean],">"&EOMONTH($F$1,-1),Table1[TransactionDate_Clean],"<="&EOMONTH($F$1,0)) -> 2 | G2: =SUMIFS(Table1[Quantity],Table1[ProductID],Table33[[#This Row],[ProductID]],Table1[RegionClean_],Table33[[#This Row],[Region]],Table1[TransactionDate_Clean],">"&EOMONTH($G$1,-1),Table1[TransactionDate_Clean],"<="&EOMONTH($G$1,0)) -> 1 | H2: =SUMIFS(Table1[Quantity],Table1[ProductID],Table33[[#This Row],[ProductID]],Table1[RegionClean_],Table33[[#This Row],[Region]],Table1[TransactionDate_Clean],">"&EOMONTH($H$1,-1),Table1[TransactionDate_Clean],"<="&EOMONTH($H$1,0)) -> 2 | I2: =SUM(Table33[[#This Row],[1/1/2025]:[6/1/2025]]) -> 18 | L2: P-FS-001 | M2: N. AMERICA | N2: =SUMIFS(Table4[ActualCost_Clean],Table4[ProductID_Clean],Product_Month_Actual_Variable_Cost[[#This Row],[ProductID]],Table4[Period_Clean],Product_Month_Actual_Variable_Cost[[#Headers],[2025-01]],Table4[CostType],"Variable") -> 1126.25 | O2: =SUMIFS(Table4[ActualCost_Clean],Table4[ProductID_Clean],Product_Month_Actual_Variable_Cost[[#This Row],[ProductID]],Table4[Period_Clean],Product_Month_Actual_Variable_Cost[[#Headers],[2025-02]],Table4[CostType],"Variable") -> 1124.28 | P2: =SUMIFS(Table4[ActualCost_Clean],Table4[ProductID_Clean],Product_Month_Actual_Variable_Cost[[#This Row],[ProductID]],Table4[Period_Clean],Product_Month_Actual_Variable_Cost[[#Headers],[2025-03]],Table4[CostType],"Variable") -> 1108.08 | Q2: =SUMIFS(Table4[ActualCost_Clean],Table4[ProductID_Clean],Product_Month_Actual_Variable_Cost[[#This Row],[ProductID]],Table4[Period_Clean],Product_Month_Actual_Variable_Cost[[#Headers],[2025-04]],Table4[CostType],"Variable") -> 1123.73 | R2: =SUMIFS(Table4[ActualCost_Clean],Table4[ProductID_Clean],Product_Month_Actual_Variable_Cost[[#This Row],[ProductID]],Table4[Period_Clean],Product_Month_Actual_Variable_Cost[[#Headers],[2025-05]],Table4[CostType],"Variable") -> 1153.56 | S2: =SUMIFS(Table4[ActualCost_Clean],Table4[ProductID_Clean],Product_Month_Actual_Variable_Cost[[#This Row],[ProductID]],Table4[Period_Clean],Product_Month_Actual_Variable_Cost[[#Headers],[2025-06]],Table4[CostType],"Variable") -> 1118.05 | V2: P-FS-001 | W2: N. AMERICA | X2: =Table33[[#This Row],[1/1/2025]]*Product_Month_Actual_Variable_Cost[[#This Row],[2025-01]] -> 3378.75 | Y2: =Table33[[#This Row],[2/1/2025]]*Product_Month_Actual_Variable_Cost[[#This Row],[2025-02]] -> 4497.12 | Z2: =Table33[[#This Row],[3/1/2025]]*Product_Month_Actual_Variable_Cost[[#This Row],[2025-03]] -> 6648.48 | AA2: =Table33[[#This Row],[4/1/2025]]*Product_Month_Actual_Variable_Cost[[#This Row],[2025-04]] -> 2247.46 | AB2: =Table33[[#This Row],[5/1/2025]]*Product_Month_Actual_Variable_Cost[[#This Row],[2025-05]] -> 1153.56 | AC2: =Table33[[#This Row],[6/1/2025]]*Product_Month_Actual_Variable_Cost[[#This Row],[2025-06]] -> 2236.1 | AD2: =SUM(Product_Region_Monthly_Variable_Cost[[#This Row],[25-Jan]:[25-Jun]]) -> 20161.47 | AG2: P-FS-001 | AH2: N. AMERICA | AI2: =SUMIFS(Table4[ActualCost_Clean],Table4[ProductID_Clean],Product_Month_Actual_Fixed_Cost[[#This Row],[ProductID]],Table4[Period_Clean],Product_Month_Actual_Variable_Cost[[#Headers],[2025-01]],Table4[CostType],"Fixed") -> 217.99 | AJ2: =SUMIFS(Table4[ActualCost_Clean],Table4[ProductID_Clean],Product_Month_Actual_Fixed_Cost[[#This Row],[ProductID]],Table4[Period_Clean],Product_Month_Actual_Variable_Cost[[#Headers],[2025-02]],Table4[CostType],"Fixed") -> 211.2 | AK2: =SUMIFS(Table4[ActualCost_Clean],Table4[ProductID_Clean],Product_Month_Actual_Fixed_Cost[[#This Row],[ProductID]],Table4[Period_Clean],Product_Month_Actual_Variable_Cost[[#Headers],[2025-03]],Table4[CostType],"Fixed") -> 224.06 | AL2: =SUMIFS(Table4[ActualCost_Clean],Table4[ProductID_Clean],Product_Month_Actual_Fixed_Cost[[#This Row],[ProductID]],Table4[Period_Clean],Product_Month_Actual_Variable_Cost[[#Headers],[2025-04]],Table4[CostType],"Fixed") -> 220.46 | AM2: =SUMIFS(Table4[ActualCost_Clean],Table4[ProductID_Clean],Product_Month_Actual_Fixed_Cost[[#This Row],[ProductID]],Table4[Period_Clean],Product_Month_Actual_Variable_Cost[[#Headers],[2025-05]],Table4[CostType],"Fixed") -> 213.28 | AN2: =SUMIFS(Table4[ActualCost_Clean],Table4[ProductID_Clean],Product_Month_Actual_Fixed_Cost[[#This Row],[ProductID]],Table4[Period_Clean],Product_Month_Actual_Variable_Cost[[#Headers],[2025-06]],Table4[CostType],"Fixed") -> 213.4 | AQ2: P-FS-001 | AR2: N. AMERICA | AS2: =Product_Month_Actual_Fixed_Cost[[#This Row],[2025-01]]*Table33[[#This Row],[1/1/2025]] -> 653.97 | AT2: =Product_Month_Actual_Fixed_Cost[[#This Row],[2025-02]]*Table33[[#This Row],[2/1/2025]] -> 844.8 | AU2: =Product_Month_Actual_Fixed_Cost[[#This Row],[2025-03]]*Table33[[#This Row],[3/1/2025]] -> 1344.36 | AV2: =Product_Month_Actual_Fixed_Cost[[#This Row],[2025-04]]*Table33[[#This Row],[4/1/2025]] -> 440.92 | AW2: =Product_Month_Actual_Fixed_Cost[[#This Row],[2025-05]]*Table33[[#This Row],[5/1/2025]] -> 213.28 | AX2: =Product_Month_Actual_Fixed_Cost[[#This Row],[2025-06]]*Table33[[#This Row],[6/1/2025]] -> 426.8 | AY2: =SUM(Product_Region_Monthly_Fixed_Cost[[#This Row],[25-Jan]:[25-Jun]]) -> 3924.13 | BB2: P-FS-001 | BC2: N. AMERICA | BD2: =Product_Region_Monthly_Fixed_Cost[[#This Row],[25-Jan]]+Product_Region_Monthly_Variable_Cost[[#This Row],[25-Jan]] -> 4032.72 | BE2: =Product_Region_Monthly_Fixed_Cost[[#This Row],[25-Feb]]+Product_Region_Monthly_Variable_Cost[[#This Row],[25-Feb]] -> 5341.92 | BF2: =Product_Region_Monthly_Fixed_Cost[[#This Row],[25-Mar]]+Product_Region_Monthly_Variable_Cost[[#This Row],[25-Mar]] -> 7992.84 | BG2: =Product_Region_Monthly_Fixed_Cost[[#This Row],[25-Apr]]+Product_Region_Monthly_Variable_Cost[[#This Row],[25-Apr]] -> 2688.38 | BH2: =Product_Region_Monthly_Fixed_Cost[[#This Row],[25-May]]+Product_Region_Monthly_Variable_Cost[[#This Row],[25-May]] -> 1366.84 | BI2: =Product_Region_Monthly_Fixed_Cost[[#This Row],[25-Jun]]+Product_Region_Monthly_Variable_Cost[[#This Row],[25-Jun]] -> 2662.9 | BJ2: =Product_Region_Monthly_Fixed_Cost[[#This Row],[H1 Fixed Cost]]+Product_Region_Monthly_Variable_Cost[[#This Row],[H1 Variable Cost]] -> 24085.6
A3: P-FS-001 | B3: EMEA | C3: =SUMIFS(Table1[Quantity],Table1[ProductID],Table33[[#This Row],[ProductID]],Table1[RegionClean_],Table33[[#This Row],[Region]],Table1[TransactionDate_Clean],">"&EOMONTH($C$1,-1),Table1[TransactionDate_Clean],"<="&EOMONTH($C$1,0)) -> 1 | D3: =SUMIFS(Table1[Quantity],Table1[ProductID],Table33[[#This Row],[ProductID]],Table1[RegionClean_],Table33[[#This Row],[Region]],Table1[TransactionDate_Clean],">"&EOMONTH($D$1,-1),Table1[TransactionDate_Clean],"<="&EOMONTH($D$1,0)) -> 3 | E3: =SUMIFS(Table1[Quantity],Table1[ProductID],Table33[[#This Row],[ProductID]],Table1[RegionClean_],Table33[[#This Row],[Region]],Table1[TransactionDate_Clean],">"&EOMONTH($E$1,-1),Table1[TransactionDate_Clean],"<="&EOMONTH($E$1,0)) -> 2 | F3: =SUMIFS(Table1[Quantity],Table1[ProductID],Table33[[#This Row],[ProductID]],Table1[RegionClean_],Table33[[#This Row],[Region]],Table1[TransactionDate_Clean],">"&EOMONTH($F$1,-1),Table1[TransactionDate_Clean],"<="&EOMONTH($F$1,0)) -> 2 | G3: =SUMIFS(Table1[Quantity],Table1[ProductID],Table33[[#This Row],[ProductID]],Table1[RegionClean_],Table33[[#This Row],[Region]],Table1[TransactionDate_Clean],">"&EOMONTH($G$1,-1),Table1[TransactionDate_Clean],"<="&EOMONTH($G$1,0)) -> 4 | H3: =SUMIFS(Table1[Quantity],Table1[ProductID],Table33[[#This Row],[ProductID]],Table1[RegionClean_],Table33[[#This Row],[Region]],Table1[TransactionDate_Clean],">"&EOMONTH($H$1,-1),Table1[TransactionDate_Clean],"<="&EOMONTH($H$1,0)) -> 4 | I3: =SUM(Table33[[#This Row],[1/1/2025]:[6/1/2025]]) -> 16 | L3: P-FS-001 | M3: EMEA | N3: =SUMIFS(Table4[ActualCost_Clean],Table4[ProductID_Clean],Product_Month_Actual_Variable_Cost[[#This Row],[ProductID]],Table4[Period_Clean],Product_Month_Actual_Variable_Cost[[#Headers],[2025-01]],Table4[CostType],"Variable") -> 1126.25 | O3: =SUMIFS(Table4[ActualCost_Clean],Table4[ProductID_Clean],Product_Month_Actual_Variable_Cost[[#This Row],[ProductID]],Table4[Period_Clean],Product_Month_Actual_Variable_Cost[[#Headers],[2025-02]],Table4[CostType],"Variable") -> 1124.28 | P3: =SUMIFS(Table4[ActualCost_Clean],Table4[ProductID_Clean],Product_Month_Actual_Variable_Cost[[#This Row],[ProductID]],Table4[Period_Clean],Product_Month_Actual_Variable_Cost[[#Headers],[2025-03]],Table4[CostType],"Variable") -> 1108.08 | Q3: =SUMIFS(Table4[ActualCost_Clean],Table4[ProductID_Clean],Product_Month_Actual_Variable_Cost[[#This Row],[ProductID]],Table4[Period_Clean],Product_Month_Actual_Variable_Cost[[#Headers],[2025-04]],Table4[CostType],"Variable") -> 1123.73 | R3: =SUMIFS(Table4[ActualCost_Clean],Table4[ProductID_Clean],Product_Month_Actual_Variable_Cost[[#This Row],[ProductID]],Table4[Period_Clean],Product_Month_Actual_Variable_Cost[[#Headers],[2025-05]],Table4[CostType],"Variable") -> 1153.56 | S3: =SUMIFS(Table4[ActualCost_Clean],Table4[ProductID_Clean],Product_Month_Actual_Variable_Cost[[#This Row],[ProductID]],Table4[Period_Clean],Product_Month_Actual_Variable_Cost[[#Headers],[2025-06]],Table4[CostType],"Variable") -> 1118.05 | V3: P-FS-001 | W3: EMEA | X3: =Table33[[#This Row],[1/1/2025]]*Product_Month_Actual_Variable_Cost[[#This Row],[2025-01]] -> 1126.25 | Y3: =Table33[[#This Row],[2/1/2025]]*Product_Month_Actual_Variable_Cost[[#This Row],[2025-02]] -> 3372.84 | Z3: =Table33[[#This Row],[3/1/2025]]*Product_Month_Actual_Variable_Cost[[#This Row],[2025-03]] -> 2216.16 | AA3: =Table33[[#This Row],[4/1/2025]]*Product_Month_Actual_Variable_Cost[[#This Row],[2025-04]] -> 2247.46 | AB3: =Table33[[#This Row],[5/1/2025]]*Product_Month_Actual_Variable_Cost[[#This Row],[2025-05]] -> 4614.24 | AC3: =Table33[[#This Row],[6/1/2025]]*Product_Month_Actual_Variable_Cost[[#This Row],[2025-06]] -> 4472.2 | AD3: =SUM(Product_Region_Monthly_Variable_Cost[[#This Row],[25-Jan]:[25-Jun]]) -> 18049.15 | AG3: P-FS-001 | AH3: EMEA | AI3: =SUMIFS(Table4[ActualCost_Clean],Table4[ProductID_Clean],Product_Month_Actual_Fixed_Cost[[#This Row],[ProductID]],Table4[Period_Clean],Product_Month_Actual_Variable_Cost[[#Headers],[2025-01]],Table4[CostType],"Fixed") -> 217.99 | AJ3: =SUMIFS(Table4[ActualCost_Clean],Table4[ProductID_Clean],Product_Month_Actual_Fixed_Cost[[#This Row],[ProductID]],Table4[Period_Clean],Product_Month_Actual_Variable_Cost[[#Headers],[2025-02]],Table4[CostType],"Fixed") -> 211.2 | AK3: =SUMIFS(Table4[ActualCost_Clean],Table4[ProductID_Clean],Product_Month_Actual_Fixed_Cost[[#This Row],[ProductID]],Table4[Period_Clean],Product_Month_Actual_Variable_Cost[[#Headers],[2025-03]],Table4[CostType],"Fixed") -> 224.06 | AL3: =SUMIFS(Table4[ActualCost_Clean],Table4[ProductID_Clean],Product_Month_Actual_Fixed_Cost[[#This Row],[ProductID]],Table4[Period_Clean],Product_Month_Actual_Variable_Cost[[#Headers],[2025-04]],Table4[CostType],"Fixed") -> 220.46 | AM3: =SUMIFS(Table4[ActualCost_Clean],Table4[ProductID_Clean],Product_Month_Actual_Fixed_Cost[[#This Row],[ProductID]],Table4[Period_Clean],Product_Month_Actual_Variable_Cost[[#Headers],[2025-05]],Table4[CostType],"Fixed") -> 213.28 | AN3: =SUMIFS(Table4[ActualCost_Clean],Table4[ProductID_Clean],Product_Month_Actual_Fixed_Cost[[#This Row],[ProductID]],Table4[Period_Clean],Product_Month_Actual_Variable_Cost[[#Headers],[2025-06]],Table4[CostType],"Fixed") -> 213.4 | AQ3: P-FS-001 | AR3: EMEA | AS3: =Product_Month_Actual_Fixed_Cost[[#This Row],[2025-01]]*Table33[[#This Row],[1/1/2025]] -> 217.99 | AT3: =Product_Month_Actual_Fixed_Cost[[#This Row],[2025-02]]*Table33[[#This Row],[2/1/2025]] -> 633.6 | AU3: =Product_Month_Actual_Fixed_Cost[[#This Row],[2025-03]]*Table33[[#This Row],[3/1/2025]] -> 448.12 | AV3: =Product_Month_Actual_Fixed_Cost[[#This Row],[2025-04]]*Table33[[#This Row],[4/1/2025]] -> 440.92 | AW3: =Product_Month_Actual_Fixed_Cost[[#This Row],[2025-05]]*Table33[[#This Row],[5/1/2025]] -> 853.12 | AX3: =Product_Month_Actual_Fixed_Cost[[#This Row],[2025-06]]*Table33[[#This Row],[6/1/2025]] -> 853.6 | AY3: =SUM(Product_Region_Monthly_Fixed_Cost[[#This Row],[25-Jan]:[25-Jun]]) -> 3447.35 | BB3: P-FS-001 | BC3: EMEA | BD3: =Product_Region_Monthly_Fixed_Cost[[#This Row],[25-Jan]]+Product_Region_Monthly_Variable_Cost[[#This Row],[25-Jan]] -> 1344.24 | BE3: =Product_Region_Monthly_Fixed_Cost[[#This Row],[25-Feb]]+Product_Region_Monthly_Variable_Cost[[#This Row],[25-Feb]] -> 4006.44 | BF3: =Product_Region_Monthly_Fixed_Cost[[#This Row],[25-Mar]]+Product_Region_Monthly_Variable_Cost[[#This Row],[25-Mar]] -> 2664.28 | BG3: =Product_Region_Monthly_Fixed_Cost[[#This Row],[25-Apr]]+Product_Region_Monthly_Variable_Cost[[#This Row],[25-Apr]] -> 2688.38 | BH3: =Product_Region_Monthly_Fixed_Cost[[#This Row],[25-May]]+Product_Region_Monthly_Variable_Cost[[#This Row],[25-May]] -> 5467.36 | BI3: =Product_Region_Monthly_Fixed_Cost[[#This Row],[25-Jun]]+Product_Region_Monthly_Variable_Cost[[#This Row],[25-Jun]] -> 5325.8 | BJ3: =Product_Region_Monthly_Fixed_Cost[[#This Row],[H1 Fixed Cost]]+Product_Region_Monthly_Variable_Cost[[#This Row],[H1 Variable Cost]] -> 21496.5
A4: P-FS-001 | B4: APAC | C4: =SUMIFS(Table1[Quantity],Table1[ProductID],Table33[[#This Row],[ProductID]],Table1[RegionClean_],Table33[[#This Row],[Region]],Table1[TransactionDate_Clean],">"&EOMONTH($C$1,-1),Table1[TransactionDate_Clean],"<="&EOMONTH($C$1,0)) -> 0 | D4: =SUMIFS(Table1[Quantity],Table1[ProductID],Table33[[#This Row],[ProductID]],Table1[RegionClean_],Table33[[#This Row],[Region]],Table1[TransactionDate_Clean],">"&EOMONTH($D$1,-1),Table1[TransactionDate_Clean],"<="&EOMONTH($D$1,0)) -> 0 | E4: =SUMIFS(Table1[Quantity],Table1[ProductID],Table33[[#This Row],[ProductID]],Table1[RegionClean_],Table33[[#This Row],[Region]],Table1[TransactionDate_Clean],">"&EOMONTH($E$1,-1),Table1[TransactionDate_Clean],"<="&EOMONTH($E$1,0)) -> 1 | F4: =SUMIFS(Table1[Quantity],Table1[ProductID],Table33[[#This Row],[ProductID]],Table1[RegionClean_],Table33[[#This Row],[Region]],Table1[TransactionDate_Clean],">"&EOMONTH($F$1,-1),Table1[TransactionDate_Clean],"<="&EOMONTH($F$1,0)) -> 1 | G4: =SUMIFS(Table1[Quantity],Table1[ProductID],Table33[[#This Row],[ProductID]],Table1[RegionClean_],Table33[[#This Row],[Region]],Table1[TransactionDate_Clean],">"&EOMONTH($G$1,-1),Table1[TransactionDate_Clean],"<="&EOMONTH($G$1,0)) -> 4 | H4: =SUMIFS(Table1[Quantity],Table1[ProductID],Table33[[#This Row],[ProductID]],Table1[RegionClean_],Table33[[#This Row],[Region]],Table1[TransactionDate_Clean],">"&EOMONTH($H$1,-1),Table1[TransactionDate_Clean],"<="&EOMONTH($H$1,0)) -> 2 | I4: =SUM(Table33[[#This Row],[1/1/2025]:[6/1/2025]]) -> 8 | L4: P-FS-001 | M4: APAC | N4: =SUMIFS(Table4[ActualCost_Clean],Table4[ProductID_Clean],Product_Month_Actual_Variable_Cost[[#This Row],[ProductID]],Table4[Period_Clean],Product_Month_Actual_Variable_Cost[[#Headers],[2025-01]],Table4[CostType],"Variable") -> 1126.25 | O4: =SUMIFS(Table4[ActualCost_Clean],Table4[ProductID_Clean],Product_Month_Actual_Variable_Cost[[#This Row],[ProductID]],Table4[Period_Clean],Product_Month_Actual_Variable_Cost[[#Headers],[2025-02]],Table4[CostType],"Variable") -> 1124.28 | P4: =SUMIFS(Table4[ActualCost_Clean],Table4[ProductID_Clean],Product_Month_Actual_Variable_Cost[[#This Row],[ProductID]],Table4[Period_Clean],Product_Month_Actual_Variable_Cost[[#Headers],[2025-03]],Table4[CostType],"Variable") -> 1108.08 | Q4: =SUMIFS(Table4[ActualCost_Clean],Table4[ProductID_Clean],Product_Month_Actual_Variable_Cost[[#This Row],[ProductID]],Table4[Period_Clean],Product_Month_Actual_Variable_Cost[[#Headers],[2025-04]],Table4[CostType],"Variable") -> 1123.73 | R4: =SUMIFS(Table4[ActualCost_Clean],Table4[ProductID_Clean],Product_Month_Actual_Variable_Cost[[#This Row],[ProductID]],Table4[Period_Clean],Product_Month_Actual_Variable_Cost[[#Headers],[2025-05]],Table4[CostType],"Variable") -> 1153.56 | S4: =SUMIFS(Table4[ActualCost_Clean],Table4[ProductID_Clean],Product_Month_Actual_Variable_Cost[[#This Row],[ProductID]],Table4[Period_Clean],Product_Month_Actual_Variable_Cost[[#Headers],[2025-06]],Table4[CostType],"Variable") -> 1118.05 | V4: P-FS-001 | W4: APAC | X4: =Table33[[#This Row],[1/1/2025]]*Product_Month_Actual_Variable_Cost[[#This Row],[2025-01]] -> 0 | Y4: =Table33[[#This Row],[2/1/2025]]*Product_Month_Actual_Variable_Cost[[#This Row],[2025-02]] -> 0 | Z4: =Table33[[#This Row],[3/1/2025]]*Product_Month_Actual_Variable_Cost[[#This Row],[2025-03]] -> 1108.08 | AA4: =Table33[[#This Row],[4/1/2025]]*Product_Month_Actual_Variable_Cost[[#This Row],[2025-04]] -> 1123.73 | AB4: =Table33[[#This Row],[5/1/2025]]*Product_Month_Actual_Variable_Cost[[#This Row],[2025-05]] -> 4614.24 | AC4: =Table33[[#This Row],[6/1/2025]]*Product_Month_Actual_Variable_Cost[[#This Row],[2025-06]] -> 2236.1 | AD4: =SUM(Product_Region_Monthly_Variable_Cost[[#This Row],[25-Jan]:[25-Jun]]) -> 9082.15 | AG4: P-FS-001 | AH4: APAC | AI4: =SUMIFS(Table4[ActualCost_Clean],Table4[ProductID_Clean],Product_Month_Actual_Fixed_Cost[[#This Row],[ProductID]],Table4[Period_Clean],Product_Month_Actual_Variable_Cost[[#Headers],[2025-01]],Table4[CostType],"Fixed") -> 217.99 | AJ4: =SUMIFS(Table4[ActualCost_Clean],Table4[ProductID_Clean],Product_Month_Actual_Fixed_Cost[[#This Row],[ProductID]],Table4[Period_Clean],Product_Month_Actual_Variable_Cost[[#Headers],[2025-02]],Table4[CostType],"Fixed") -> 211.2 | AK4: =SUMIFS(Table4[ActualCost_Clean],Table4[ProductID_Clean],Product_Month_Actual_Fixed_Cost[[#This Row],[ProductID]],Table4[Period_Clean],Product_Month_Actual_Variable_Cost[[#Headers],[2025-03]],Table4[CostType],"Fixed") -> 224.06 | AL4: =SUMIFS(Table4[ActualCost_Clean],Table4[ProductID_Clean],Product_Month_Actual_Fixed_Cost[[#This Row],[ProductID]],Table4[Period_Clean],Product_Month_Actual_Variable_Cost[[#Headers],[2025-04]],Table4[CostType],"Fixed") -> 220.46 | AM4: =SUMIFS(Table4[ActualCost_Clean],Table4[ProductID_Clean],Product_Month_Actual_Fixed_Cost[[#This Row],[ProductID]],Table4[Period_Clean],Product_Month_Actual_Variable_Cost[[#Headers],[2025-05]],Table4[CostType],"Fixed") -> 213.28 | AN4: =SUMIFS(Table4[ActualCost_Clean],Table4[ProductID_Clean],Product_Month_Actual_Fixed_Cost[[#This Row],[ProductID]],Table4[Period_Clean],Product_Month_Actual_Variable_Cost[[#Headers],[2025-06]],Table4[CostType],"Fixed") -> 213.4 | AQ4: P-FS-001 | AR4: APAC | AS4: =Product_Month_Actual_Fixed_Cost[[#This Row],[2025-01]]*Table33[[#This Row],[1/1/2025]] -> 0 | AT4: =Product_Month_Actual_Fixed_Cost[[#This Row],[2025-02]]*Table33[[#This Row],[2/1/2025]] -> 0 | AU4: =Product_Month_Actual_Fixed_Cost[[#This Row],[2025-03]]*Table33[[#This Row],[3/1/2025]] -> 224.06 | AV4: =Product_Month_Actual_Fixed_Cost[[#This Row],[2025-04]]*Table33[[#This Row],[4/1/2025]] -> 220.46 | AW4: =Product_Month_Actual_Fixed_Cost[[#This Row],[2025-05]]*Table33[[#This Row],[5/1/2025]] -> 853.12 | AX4: =Product_Month_Actual_Fixed_Cost[[#This Row],[2025-06]]*Table33[[#This Row],[6/1/2025]] -> 426.8 | AY4: =SUM(Product_Region_Monthly_Fixed_Cost[[#This Row],[25-Jan]:[25-Jun]]) -> 1724.44 | BB4: P-FS-001 | BC4: APAC | BD4: =Product_Region_Monthly_Fixed_Cost[[#This Row],[25-Jan]]+Product_Region_Monthly_Variable_Cost[[#This Row],[25-Jan]] -> 0 | BE4: =Product_Region_Monthly_Fixed_Cost[[#This Row],[25-Feb]]+Product_Region_Monthly_Variable_Cost[[#This Row],[25-Feb]] -> 0 | BF4: =Product_Region_Monthly_Fixed_Cost[[#This Row],[25-Mar]]+Product_Region_Monthly_Variable_Cost[[#This Row],[25-Mar]] -> 1332.14 | BG4: =Product_Region_Monthly_Fixed_Cost[[#This Row],[25-Apr]]+Product_Region_Monthly_Variable_Cost[[#This Row],[25-Apr]] -> 1344.19 | BH4: =Product_Region_Monthly_Fixed_Cost[[#This Row],[25-May]]+Product_Region_Monthly_Variable_Cost[[#This Row],[25-May]] -> 5467.36 | BI4: =Product_Region_Monthly_Fixed_Cost[[#This Row],[25-Jun]]+Product_Region_Monthly_Variable_Cost[[#This Row],[25-Jun]] -> 2662.9 | BJ4: =Product_Region_Monthly_Fixed_Cost[[#This Row],[H1 Fixed Cost]]+Product_Region_Monthly_Variable_Cost[[#This Row],[H1 Variable Cost]] -> 10806.59
A5: P-FS-001 | B5: LATIN AMERICA | C5: =SUMIFS(Table1[Quantity],Table1[ProductID],Table33[[#This Row],[ProductID]],Table1[RegionClean_],Table33[[#This Row],[Region]],Table1[TransactionDate_Clean],">"&EOMONTH($C$1,-1),Table1[TransactionDate_Clean],"<="&EOMONTH($C$1,0)) -> 2 | D5: =SUMIFS(Table1[Quantity],Table1[ProductID],Table33[[#This Row],[ProductID]],Table1[RegionClean_],Table33[[#This Row],[Region]],Table1[TransactionDate_Clean],">"&EOMONTH($D$1,-1),Table1[TransactionDate_Clean],"<="&EOMONTH($D$1,0)) -> 0 | E5: =SUMIFS(Table1[Quantity],Table1[ProductID],Table33[[#This Row],[ProductID]],Table1[RegionClean_],Table33[[#This Row],[Region]],Table1[TransactionDate_Clean],">"&EOMONTH($E$1,-1),Table1[TransactionDate_Clean],"<="&EOMONTH($E$1,0)) -> 1 | F5: =SUMIFS(Table1[Quantity],Table1[ProductID],Table33[[#This Row],[ProductID]],Table1[RegionClean_],Table33[[#This Row],[Region]],Table1[TransactionDate_Clean],">"&EOMONTH($F$1,-1),Table1[TransactionDate_Clean],"<="&EOMONTH($F$1,0)) -> 2 | G5: =SUMIFS(Table1[Quantity],Table1[ProductID],Table33[[#This Row],[ProductID]],Table1[RegionClean_],Table33[[#This Row],[Region]],Table1[TransactionDate_Clean],">"&EOMONTH($G$1,-1),Table1[TransactionDate_Clean],"<="&EOMONTH($G$1,0)) -> 0 | H5: =SUMIFS(Table1[Quantity],Table1[ProductID],Table33[[#This Row],[ProductID]],Table1[RegionClean_],Table33[[#This Row],[Region]],Table1[TransactionDate_Clean],">"&EOMONTH($H$1,-1),Table1[TransactionDate_Clean],"<="&EOMONTH($H$1,0)) -> 3 | I5: =SUM(Table33[[#This Row],[1/1/2025]:[6/1/2025]]) -> 8 | L5: P-FS-001 | M5: LATIN AMERICA | N5: =SUMIFS(Table4[ActualCost_Clean],Table4[ProductID_Clean],Product_Month_Actual_Variable_Cost[[#This Row],[ProductID]],Table4[Period_Clean],Product_Month_Actual_Variable_Cost[[#Headers],[2025-01]],Table4[CostType],"Variable") -> 1126.25 | O5: =SUMIFS(Table4[ActualCost_Clean],Table4[ProductID_Clean],Product_Month_Actual_Variable_Cost[[#This Row],[ProductID]],Table4[Period_Clean],Product_Month_Actual_Variable_Cost[[#Headers],[2025-02]],Table4[CostType],"Variable") -> 1124.28 | P5: =SUMIFS(Table4[ActualCost_Clean],Table4[ProductID_Clean],Product_Month_Actual_Variable_Cost[[#This Row],[ProductID]],Table4[Period_Clean],Product_Month_Actual_Variable_Cost[[#Headers],[2025-03]],Table4[CostType],"Variable") -> 1108.08 | Q5: =SUMIFS(Table4[ActualCost_Clean],Table4[ProductID_Clean],Product_Month_Actual_Variable_Cost[[#This Row],[ProductID]],Table4[Period_Clean],Product_Month_Actual_Variable_Cost[[#Headers],[2025-04]],Table4[CostType],"Variable") -> 1123.73 | R5: =SUMIFS(Table4[ActualCost_Clean],Table4[ProductID_Clean],Product_Month_Actual_Variable_Cost[[#This Row],[ProductID]],Table4[Period_Clean],Product_Month_Actual_Variable_Cost[[#Headers],[2025-05]],Table4[CostType],"Variable") -> 1153.56 | S5: =SUMIFS(Table4[ActualCost_Clean],Table4[ProductID_Clean],Product_Month_Actual_Variable_Cost[[#This Row],[ProductID]],Table4[Period_Clean],Product_Month_Actual_Variable_Cost[[#Headers],[2025-06]],Table4[CostType],"Variable") -> 1118.05 | V5: P-FS-001 | W5: LATIN AMERICA | X5: =Table33[[#This Row],[1/1/2025]]*Product_Month_Actual_Variable_Cost[[#This Row],[2025-01]] -> 2252.5 | Y5: =Table33[[#This Row],[2/1/2025]]*Product_Month_Actual_Variable_Cost[[#This Row],[2025-02]] -> 0 | Z5: =Table33[[#This Row],[3/1/2025]]*Product_Month_Actual_Variable_Cost[[#This Row],[2025-03]] -> 1108.08 | AA5: =Table33[[#This Row],[4/1/2025]]*Product_Month_Actual_Variable_Cost[[#This Row],[2025-04]] -> 2247.46 | AB5: =Table33[[#This Row],[5/1/2025]]*Product_Month_Actual_Variable_Cost[[#This Row],[2025-05]] -> 0 | AC5: =Table33[[#This Row],[6/1/2025]]*Product_Month_Actual_Variable_Cost[[#This Row],[2025-06]] -> 3354.15 | AD5: =SUM(Product_Region_Monthly_Variable_Cost[[#This Row],[25-Jan]:[25-Jun]]) -> 8962.19 | AG5: P-FS-001 | AH5: LATIN AMERICA | AI5: =SUMIFS(Table4[ActualCost_Clean],Table4[ProductID_Clean],Product_Month_Actual_Fixed_Cost[[#This Row],[ProductID]],Table4[Period_Clean],Product_Month_Actual_Variable_Cost[[#Headers],[2025-01]],Table4[CostType],"Fixed") -> 217.99 | AJ5: =SUMIFS(Table4[ActualCost_Clean],Table4[ProductID_Clean],Product_Month_Actual_Fixed_Cost[[#This Row],[ProductID]],Table4[Period_Clean],Product_Month_Actual_Variable_Cost[[#Headers],[2025-02]],Table4[CostType],"Fixed") -> 211.2 | AK5: =SUMIFS(Table4[ActualCost_Clean],Table4[ProductID_Clean],Product_Month_Actual_Fixed_Cost[[#This Row],[ProductID]],Table4[Period_Clean],Product_Month_Actual_Variable_Cost[[#Headers],[2025-03]],Table4[CostType],"Fixed") -> 224.06 | AL5: =SUMIFS(Table4[ActualCost_Clean],Table4[ProductID_Clean],Product_Month_Actual_Fixed_Cost[[#This Row],[ProductID]],Table4[Period_Clean],Product_Month_Actual_Variable_Cost[[#Headers],[2025-04]],Table4[CostType],"Fixed") -> 220.46 | AM5: =SUMIFS(Table4[ActualCost_Clean],Table4[ProductID_Clean],Product_Month_Actual_Fixed_Cost[[#This Row],[ProductID]],Table4[Period_Clean],Product_Month_Actual_Variable_Cost[[#Headers],[2025-05]],Table4[CostType],"Fixed") -> 213.28 | AN5: =SUMIFS(Table4[ActualCost_Clean],Table4[ProductID_Clean],Product_Month_Actual_Fixed_Cost[[#This Row],[ProductID]],Table4[Period_Clean],Product_Month_Actual_Variable_Cost[[#Headers],[2025-06]],Table4[CostType],"Fixed") -> 213.4 | AQ5: P-FS-001 | AR5: LATIN AMERICA | AS5: =Product_Month_Actual_Fixed_Cost[[#This Row],[2025-01]]*Table33[[#This Row],[1/1/2025]] -> 435.98 | AT5: =Product_Month_Actual_Fixed_Cost[[#This Row],[2025-02]]*Table33[[#This Row],[2/1/2025]] -> 0 | AU5: =Product_Month_Actual_Fixed_Cost[[#This Row],[2025-03]]*Table33[[#This Row],[3/1/2025]] -> 224.06 | AV5: =Product_Month_Actual_Fixed_Cost[[#This Row],[2025-04]]*Table33[[#This Row],[4/1/2025]] -> 440.92 | AW5: =Product_Month_Actual_Fixed_Cost[[#This Row],[2025-05]]*Table33[[#This Row],[5/1/2025]] -> 0 | AX5: =Product_Month_Actual_Fixed_Cost[[#This Row],[2025-06]]*Table33[[#This Row],[6/1/2025]] -> 640.2 | AY5: =SUM(Product_Region_Monthly_Fixed_Cost[[#This Row],[25-Jan]:[25-Jun]]) -> 1741.16 | BB5: P-FS-001 | BC5: LATIN AMERICA | BD5: =Product_Region_Monthly_Fixed_Cost[[#This Row],[25-Jan]]+Product_Region_Monthly_Variable_Cost[[#This Row],[25-Jan]] -> 2688.48 | BE5: =Product_Region_Monthly_Fixed_Cost[[#This Row],[25-Feb]]+Product_Region_Monthly_Variable_Cost[[#This Row],[25-Feb]] -> 0 | BF5: =Product_Region_Monthly_Fixed_Cost[[#This Row],[25-Mar]]+Product_Region_Monthly_Variable_Cost[[#This Row],[25-Mar]] -> 1332.14 | BG5: =Product_Region_Monthly_Fixed_Cost[[#This Row],[25-Apr]]+Product_Region_Monthly_Variable_Cost[[#This Row],[25-Apr]] -> 2688.38 | BH5: =Product_Region_Monthly_Fixed_Cost[[#This Row],[25-May]]+Product_Region_Monthly_Variable_Cost[[#This Row],[25-May]] -> 0 | BI5: =Product_Region_Monthly_Fixed_Cost[[#This Row],[25-Jun]]+Product_Region_Monthly_Variable_Cost[[#This Row],[25-Jun]] -> 3994.35 | BJ5: =Product_Region_Monthly_Fixed_Cost[[#This Row],[H1 Fixed Cost]]+Product_Region_Monthly_Variable_Cost[[#This Row],[H1 Variable Cost]] -> 10703.35
A6: P-FS-002 | B6: N. AMERICA | C6: =SUMIFS(Table1[Quantity],Table1[ProductID],Table33[[#This Row],[ProductID]],Table1[RegionClean_],Table33[[#This Row],[Region]],Table1[TransactionDate_Clean],">"&EOMONTH($C$1,-1),Table1[TransactionDate_Clean],"<="&EOMONTH($C$1,0)) -> 6 | D6: =SUMIFS(Table1[Quantity],Table1[ProductID],Table33[[#This Row],[ProductID]],Table1[RegionClean_],Table33[[#This Row],[Region]],Table1[TransactionDate_Clean],">"&EOMONTH($D$1,-1),Table1[TransactionDate_Clean],"<="&EOMONTH($D$1,0)) -> 1 | E6: =SUMIFS(Table1[Quantity],Table1[ProductID],Table33[[#This Row],[ProductID]],Table1[RegionClean_],Table33[[#This Row],[Region]],Table1[TransactionDate_Clean],">"&EOMONTH($E$1,-1),Table1[TransactionDate_Clean],"<="&EOMONTH($E$1,0)) -> 4 | F6: =SUMIFS(Table1[Quantity],Table1[ProductID],Table33[[#This Row],[ProductID]],Table1[RegionClean_],Table33[[#This Row],[Region]],Table1[TransactionDate_Clean],">"&EOMONTH($F$1,-1),Table1[TransactionDate_Clean],"<="&EOMONTH($F$1,0)) -> 2 | G6: =SUMIFS(Table1[Quantity],Table1[ProductID],Table33[[#This Row],[ProductID]],Table1[RegionClean_],Table33[[#This Row],[Region]],Table1[TransactionDate_Clean],">"&EOMONTH($G$1,-1),Table1[TransactionDate_Clean],"<="&EOMONTH($G$1,0)) -> 3 | H6: =SUMIFS(Table1[Quantity],Table1[ProductID],Table33[[#This Row],[ProductID]],Table1[RegionClean_],Table33[[#This Row],[Region]],Table1[TransactionDate_Clean],">"&EOMONTH($H$1,-1),Table1[TransactionDate_Clean],"<="&EOMONTH($H$1,0)) -> 4 | I6: =SUM(Table33[[#This Row],[1/1/2025]:[6/1/2025]]) -> 20 | L6: P-FS-002 | M6: N. AMERICA | N6: =SUMIFS(Table4[ActualCost_Clean],Table4[ProductID_Clean],Product_Month_Actual_Variable_Cost[[#This Row],[ProductID]],Table4[Period_Clean],Product_Month_Actual_Variable_Cost[[#Headers],[2025-01]],Table4[CostType],"Variable") -> 1263.71 | O6: =SUMIFS(Table4[ActualCost_Clean],Table4[ProductID_Clean],Product_Month_Actual_Variable_Cost[[#This Row],[ProductID]],Table4[Period_Clean],Product_Month_Actual_Variable_Cost[[#Headers],[2025-02]],Table4[CostType],"Variable") -> 1242.76 | P6: =SUMIFS(Table4[ActualCost_Clean],Table4[ProductID_Clean],Product_Month_Actual_Variable_Cost[[#This Row],[ProductID]],Table4[Period_Clean],Product_Month_Actual_Variable_Cost[[#Headers],[2025-03]],Table4[CostType],"Variable") -> 1218.76 | Q6: =SUMIFS(Table4[ActualCost_Clean],Table4[ProductID_Clean],Product_Month_Actual_Variable_Cost[[#This Row],[ProductID]],Table4[Period_Clean],Product_Month_Actual_Variable_Cost[[#Headers],[2025-04]],Table4[CostType],"Variable") -> 1247.48 | R6: =SUMIFS(Table4[ActualCost_Clean],Table4[ProductID_Clean],Product_Month_Actual_Variable_Cost[[#This Row],[ProductID]],Table4[Period_Clean],Product_Month_Actual_Variable_Cost[[#Headers],[2025-05]],Table4[CostType],"Variable") -> 1247.2 | S6: =SUMIFS(Table4[ActualCost_Clean],Table4[ProductID_Clean],Product_Month_Actual_Variable_Cost[[#This Row],[ProductID]],Table4[Period_Clean],Product_Month_Actual_Variable_Cost[[#Headers],[2025-06]],Table4[CostType],"Variable") -> 1271.29 | V6: P-FS-002 | W6: N. AMERICA | X6: =Table33[[#This Row],[1/1/2025]]*Product_Month_Actual_Variable_Cost[[#This Row],[2025-01]] -> 7582.26 | Y6: =Table33[[#This Row],[2/1/2025]]*Product_Month_Actual_Variable_Cost[[#This Row],[2025-02]] -> 1242.76 | Z6: =Table33[[#This Row],[3/1/2025]]*Product_Month_Actual_Variable_Cost[[#This Row],[2025-03]] -> 4875.04 | AA6: =Table33[[#This Row],[4/1/2025]]*Product_Month_Actual_Variable_Cost[[#This Row],[2025-04]] -> 2494.96 | AB6: =Table33[[#This Row],[5/1/2025]]*Product_Month_Actual_Variable_Cost[[#This Row],[2025-05]] -> 3741.6 | AC6: =Table33[[#This Row],[6/1/2025]]*Product_Month_Actual_Variable_Cost[[#This Row],[2025-06]] -> 5085.16 | AD6: =SUM(Product_Region_Monthly_Variable_Cost[[#This Row],[25-Jan]:[25-Jun]]) -> 25021.78 | AG6: P-FS-002 | AH6: N. AMERICA | AI6: =SUMIFS(Table4[ActualCost_Clean],Table4[ProductID_Clean],Product_Month_Actual_Fixed_Cost[[#This Row],[ProductID]],Table4[Period_Clean],Product_Month_Actual_Variable_Cost[[#Headers],[2025-01]],Table4[CostType],"Fixed") -> 301.18 | AJ6: =SUMIFS(Table4[ActualCost_Clean],Table4[ProductID_Clean],Product_Month_Actual_Fixed_Cost[[#This Row],[ProductID]],Table4[Period_Clean],Product_Month_Actual_Variable_Cost[[#Headers],[2025-02]],Table4[CostType],"Fixed") -> 290.14 | AK6: =SUMIFS(Table4[ActualCost_Clean],Table4[ProductID_Clean],Product_Month_Actual_Fixed_Cost[[#This Row],[ProductID]],Table4[Period_Clean],Product_Month_Actual_Variable_Cost[[#Headers],[2025-03]],Table4[CostType],"Fixed") -> 277.74 | AL6: =SUMIFS(Table4[ActualCost_Clean],Table4[ProductID_Clean],Product_Month_Actual_Fixed_Cost[[#This Row],[ProductID]],Table4[Period_Clean],Product_Month_Actual_Variable_Cost[[#Headers],[2025-04]],Table4[CostType],"Fixed") -> 290.36 | AM6: =SUMIFS(Table4[ActualCost_Clean],Table4[ProductID_Clean],Product_Month_Actual_Fixed_Cost[[#This Row],[ProductID]],Table4[Period_Clean],Product_Month_Actual_Variable_Cost[[#Headers],[2025-05]],Table4[CostType],"Fixed") -> 283.91 | AN6: =SUMIFS(Table4[ActualCost_Clean],Table4[ProductID_Clean],Product_Month_Actual_Fixed_Cost[[#This Row],[ProductID]],Table4[Period_Clean],Product_Month_Actual_Variable_Cost[[#Headers],[2025-06]],Table4[CostType],"Fixed") -> 296.85 | AQ6: P-FS-002 | AR6: N. AMERICA | AS6: =Product_Month_Actual_Fixed_Cost[[#This Row],[2025-01]]*Table33[[#This Row],[1/1/2025]] -> 1807.08 | AT6: =Product_Month_Actual_Fixed_Cost[[#This Row],[2025-02]]*Table33[[#This Row],[2/1/2025]] -> 290.14 | AU6: =Product_Month_Actual_Fixed_Cost[[#This Row],[2025-03]]*Table33[[#This Row],[3/1/2025]] -> 1110.96 | AV6: =Product_Month_Actual_Fixed_Cost[[#This Row],[2025-04]]*Table33[[#This Row],[4/1/2025]] -> 580.72 | AW6: =Product_Month_Actual_Fixed_Cost[[#This Row],[2025-05]]*Table33[[#This Row],[5/1/2025]] -> 851.73 | AX6: =Product_Month_Actual_Fixed_Cost[[#This Row],[2025-06]]*Table33[[#This Row],[6/1/2025]] -> 1187.4 | AY6: =SUM(Product_Region_Monthly_Fixed_Cost[[#This Row],[25-Jan]:[25-Jun]]) -> 5828.03 | BB6: P-FS-002 | BC6: N. AMERICA | BD6: =Product_Region_Monthly_Fixed_Cost[[#This Row],[25-Jan]]+Product_Region_Monthly_Variable_Cost[[#This Row],[25-Jan]] -> 9389.34 | BE6: =Product_Region_Monthly_Fixed_Cost[[#This Row],[25-Feb]]+Product_Region_Monthly_Variable_Cost[[#This Row],[25-Feb]] -> 1532.9 | BF6: =Product_Region_Monthly_Fixed_Cost[[#This Row],[25-Mar]]+Product_Region_Monthly_Variable_Cost[[#This Row],[25-Mar]] -> 5986 | BG6: =Product_Region_Monthly_Fixed_Cost[[#This Row],[25-Apr]]+Product_Region_Monthly_Variable_Cost[[#This Row],[25-Apr]] -> 3075.68 | BH6: =Product_Region_Monthly_Fixed_Cost[[#This Row],[25-May]]+Product_Region_Monthly_Variable_Cost[[#This Row],[25-May]] -> 4593.33 | BI6: =Product_Region_Monthly_Fixed_Cost[[#This Row],[25-Jun]]+Product_Region_Monthly_Variable_Cost[[#This Row],[25-Jun]] -> 6272.56 | BJ6: =Product_Region_Monthly_Fixed_Cost[[#This Row],[H1 Fixed Cost]]+Product_Region_Monthly_Variable_Cost[[#This Row],[H1 Variable Cost]] -> 30849.81
A7: P-FS-002 | B7: EMEA | C7: =SUMIFS(Table1[Quantity],Table1[ProductID],Table33[[#This Row],[ProductID]],Table1[RegionClean_],Table33[[#This Row],[Region]],Table1[TransactionDate_Clean],">"&EOMONTH($C$1,-1),Table1[TransactionDate_Clean],"<="&EOMONTH($C$1,0)) -> 2 | D7: =SUMIFS(Table1[Quantity],Table1[ProductID],Table33[[#This Row],[ProductID]],Table1[RegionClean_],Table33[[#This Row],[Region]],Table1[TransactionDate_Clean],">"&EOMONTH($D$1,-1),Table1[TransactionDate_Clean],"<="&EOMONTH($D$1,0)) -> 0 | E7: =SUMIFS(Table1[Quantity],Table1[ProductID],Table33[[#This Row],[ProductID]],Table1[RegionClean_],Table33[[#This Row],[Region]],Table1[TransactionDate_Clean],">"&EOMONTH($E$1,-1),Table1[TransactionDate_Clean],"<="&EOMONTH($E$1,0)) -> 1 | F7: =SUMIFS(Table1[Quantity],Table1[ProductID],Table33[[#This Row],[ProductID]],Table1[RegionClean_],Table33[[#This Row],[Region]],Table1[TransactionDate_Clean],">"&EOMONTH($F$1,-1),Table1[TransactionDate_Clean],"<="&EOMONTH($F$1,0)) -> 4 | G7: =SUMIFS(Table1[Quantity],Table1[ProductID],Table33[[#This Row],[ProductID]],Table1[RegionClean_],Table33[[#This Row],[Region]],Table1[TransactionDate_Clean],">"&EOMONTH($G$1,-1),Table1[TransactionDate_Clean],"<="&EOMONTH($G$1,0)) -> 5 | H7: =SUMIFS(Table1[Quantity],Table1[ProductID],Table33[[#This Row],[ProductID]],Table1[RegionClean_],Table33[[#This Row],[Region]],Table1[TransactionDate_Clean],">"&EOMONTH($H$1,-1),Table1[TransactionDate_Clean],"<="&EOMONTH($H$1,0)) -> 2 | I7: =SUM(Table33[[#This Row],[1/1/2025]:[6/1/2025]]) -> 14 | L7: P-FS-002 | M7: EMEA | N7: =SUMIFS(Table4[ActualCost_Clean],Table4[ProductID_Clean],Product_Month_Actual_Variable_Cost[[#This Row],[ProductID]],Table4[Period_Clean],Product_Month_Actual_Variable_Cost[[#Headers],[2025-01]],Table4[CostType],"Variable") -> 1263.71 | O7: =SUMIFS(Table4[ActualCost_Clean],Table4[ProductID_Clean],Product_Month_Actual_Variable_Cost[[#This Row],[ProductID]],Table4[Period_Clean],Product_Month_Actual_Variable_Cost[[#Headers],[2025-02]],Table4[CostType],"Variable") -> 1242.76 | P7: =SUMIFS(Table4[ActualCost_Clean],Table4[ProductID_Clean],Product_Month_Actual_Variable_Cost[[#This Row],[ProductID]],Table4[Period_Clean],Product_Month_Actual_Variable_Cost[[#Headers],[2025-03]],Table4[CostType],"Variable") -> 1218.76 | Q7: =SUMIFS(Table4[ActualCost_Clean],Table4[ProductID_Clean],Product_Month_Actual_Variable_Cost[[#This Row],[ProductID]],Table4[Period_Clean],Product_Month_Actual_Variable_Cost[[#Headers],[2025-04]],Table4[CostType],"Variable") -> 1247.48 | R7: =SUMIFS(Table4[ActualCost_Clean],Table4[ProductID_Clean],Product_Month_Actual_Variable_Cost[[#This Row],[ProductID]],Table4[Period_Clean],Product_Month_Actual_Variable_Cost[[#Headers],[2025-05]],Table4[CostType],"Variable") -> 1247.2 | S7: =SUMIFS(Table4[ActualCost_Clean],Table4[ProductID_Clean],Product_Month_Actual_Variable_Cost[[#This Row],[ProductID]],Table4[Period_Clean],Product_Month_Actual_Variable_Cost[[#Headers],[2025-06]],Table4[CostType],"Variable") -> 1271.29 | V7: P-FS-002 | W7: EMEA | X7: =Table33[[#This Row],[1/1/2025]]*Product_Month_Actual_Variable_Cost[[#This Row],[2025-01]] -> 2527.42 | Y7: =Table33[[#This Row],[2/1/2025]]*Product_Month_Actual_Variable_Cost[[#This Row],[2025-02]] -> 0 | Z7: =Table33[[#This Row],[3/1/2025]]*Product_Month_Actual_Variable_Cost[[#This Row],[2025-03]] -> 1218.76 | AA7: =Table33[[#This Row],[4/1/2025]]*Product_Month_Actual_Variable_Cost[[#This Row],[2025-04]] -> 4989.92 | AB7: =Table33[[#This Row],[5/1/2025]]*Product_Month_Actual_Variable_Cost[[#This Row],[2025-05]] -> 6236 | AC7: =Table33[[#This Row],[6/1/2025]]*Product_Month_Actual_Variable_Cost[[#This Row],[2025-06]] -> 2542.58 | AD7: =SUM(Product_Region_Monthly_Variable_Cost[[#This Row],[25-Jan]:[25-Jun]]) -> 17514.68 | AG7: P-FS-002 | AH7: EMEA | AI7: =SUMIFS(Table4[ActualCost_Clean],Table4[ProductID_Clean],Product_Month_Actual_Fixed_Cost[[#This Row],[ProductID]],Table4[Period_Clean],Product_Month_Actual_Variable_Cost[[#Headers],[2025-01]],Table4[CostType],"Fixed") -> 301.18 | AJ7: =SUMIFS(Table4[ActualCost_Clean],Table4[ProductID_Clean],Product_Month_Actual_Fixed_Cost[[#This Row],[ProductID]],Table4[Period_Clean],Product_Month_Actual_Variable_Cost[[#Headers],[2025-02]],Table4[CostType],"Fixed") -> 290.14 | AK7: =SUMIFS(Table4[ActualCost_Clean],Table4[ProductID_Clean],Product_Month_Actual_Fixed_Cost[[#This Row],[ProductID]],Table4[Period_Clean],Product_Month_Actual_Variable_Cost[[#Headers],[2025-03]],Table4[CostType],"Fixed") -> 277.74 | AL7: =SUMIFS(Table4[ActualCost_Clean],Table4[ProductID_Clean],Product_Month_Actual_Fixed_Cost[[#This Row],[ProductID]],Table4[Period_Clean],Product_Month_Actual_Variable_Cost[[#Headers],[2025-04]],Table4[CostType],"Fixed") -> 290.36 | AM7: =SUMIFS(Table4[ActualCost_Clean],Table4[ProductID_Clean],Product_Month_Actual_Fixed_Cost[[#This Row],[ProductID]],Table4[Period_Clean],Product_Month_Actual_Variable_Cost[[#Headers],[2025-05]],Table4[CostType],"Fixed") -> 283.91 | AN7: =SUMIFS(Table4[ActualCost_Clean],Table4[ProductID_Clean],Product_Month_Actual_Fixed_Cost[[#This Row],[ProductID]],Table4[Period_Clean],Product_Month_Actual_Variable_Cost[[#Headers],[2025-06]],Table4[CostType],"Fixed") -> 296.85 | AQ7: P-FS-002 | AR7: EMEA | AS7: =Product_Month_Actual_Fixed_Cost[[#This Row],[2025-01]]*Table33[[#This Row],[1/1/2025]] -> 602.36 | AT7: =Product_Month_Actual_Fixed_Cost[[#This Row],[2025-02]]*Table33[[#This Row],[2/1/2025]] -> 0 | AU7: =Product_Month_Actual_Fixed_Cost[[#This Row],[2025-03]]*Table33[[#This Row],[3/1/2025]] -> 277.74 | AV7: =Product_Month_Actual_Fixed_Cost[[#This Row],[2025-04]]*Table33[[#This Row],[4/1/2025]] -> 1161.44 | AW7: =Product_Month_Actual_Fixed_Cost[[#This Row],[2025-05]]*Table33[[#This Row],[5/1/2025]] -> 1419.55 | AX7: =Product_Month_Actual_Fixed_Cost[[#This Row],[2025-06]]*Table33[[#This Row],[6/1/2025]] -> 593.7 | AY7: =SUM(Product_Region_Monthly_Fixed_Cost[[#This Row],[25-Jan]:[25-Jun]]) -> 4054.79 | BB7: P-FS-002 | BC7: EMEA | BD7: =Product_Region_Monthly_Fixed_Cost[[#This Row],[25-Jan]]+Product_Region_Monthly_Variable_Cost[[#This Row],[25-Jan]] -> 3129.78 | BE7: =Product_Region_Monthly_Fixed_Cost[[#This Row],[25-Feb]]+Product_Region_Monthly_Variable_Cost[[#This Row],[25-Feb]] -> 0 | BF7: =Product_Region_Monthly_Fixed_Cost[[#This Row],[25-Mar]]+Product_Region_Monthly_Variable_Cost[[#This Row],[25-Mar]] -> 1496.5 | BG7: =Product_Region_Monthly_Fixed_Cost[[#This Row],[25-Apr]]+Product_Region_Monthly_Variable_Cost[[#This Row],[25-Apr]] -> 6151.36 | BH7: =Product_Region_Monthly_Fixed_Cost[[#This Row],[25-May]]+Product_Region_Monthly_Variable_Cost[[#This Row],[25-May]] -> 7655.55 | BI7: =Product_Region_Monthly_Fixed_Cost[[#This Row],[25-Jun]]+Product_Region_Monthly_Variable_Cost[[#This Row],[25-Jun]] -> 3136.28 | BJ7: =Product_Region_Monthly_Fixed_Cost[[#This Row],[H1 Fixed Cost]]+Product_Region_Monthly_Variable_Cost[[#This Row],[H1 Variable Cost]] -> 21569.47
A8: P-FS-002 | B8: APAC | C8: =SUMIFS(Table1[Quantity],Table1[ProductID],Table33[[#This Row],[ProductID]],Table1[RegionClean_],Table33[[#This Row],[Region]],Table1[TransactionDate_Clean],">"&EOMONTH($C$1,-1),Table1[TransactionDate_Clean],"<="&EOMONTH($C$1,0)) -> 3 | D8: =SUMIFS(Table1[Quantity],Table1[ProductID],Table33[[#This Row],[ProductID]],Table1[RegionClean_],Table33[[#This Row],[Region]],Table1[TransactionDate_Clean],">"&EOMONTH($D$1,-1),Table1[TransactionDate_Clean],"<="&EOMONTH($D$1,0)) -> 0 | E8: =SUMIFS(Table1[Quantity],Table1[ProductID],Table33[[#This Row],[ProductID]],Table1[RegionClean_],Table33[[#This Row],[Region]],Table1[TransactionDate_Clean],">"&EOMONTH($E$1,-1),Table1[TransactionDate_Clean],"<="&EOMONTH($E$1,0)) -> 2 | F8: =SUMIFS(Table1[Quantity],Table1[ProductID],Table33[[#This Row],[ProductID]],Table1[RegionClean_],Table33[[#This Row],[Region]],Table1[TransactionDate_Clean],">"&EOMONTH($F$1,-1),Table1[TransactionDate_Clean],"<="&EOMONTH($F$1,0)) -> 1 | G8: =SUMIFS(Table1[Quantity],Table1[ProductID],Table33[[#This Row],[ProductID]],Table1[RegionClean_],Table33[[#This Row],[Region]],Table1[TransactionDate_Clean],">"&EOMONTH($G$1,-1),Table1[TransactionDate_Clean],"<="&EOMONTH($G$1,0)) -> 7 | H8: =SUMIFS(Table1[Quantity],Table1[ProductID],Table33[[#This Row],[ProductID]],Table1[RegionClean_],Table33[[#This Row],[Region]],Table1[TransactionDate_Clean],">"&EOMONTH($H$1,-1),Table1[TransactionDate_Clean],"<="&EOMONTH($H$1,0)) -> 0 | I8: =SUM(Table33[[#This Row],[1/1/2025]:[6/1/2025]]) -> 13 | L8: P-FS-002 | M8: APAC | N8: =SUMIFS(Table4[ActualCost_Clean],Table4[ProductID_Clean],Product_Month_Actual_Variable_Cost[[#This Row],[ProductID]],Table4[Period_Clean],Product_Month_Actual_Variable_Cost[[#Headers],[2025-01]],Table4[CostType],"Variable") -> 1263.71 | O8: =SUMIFS(Table4[ActualCost_Clean],Table4[ProductID_Clean],Product_Month_Actual_Variable_Cost[[#This Row],[ProductID]],Table4[Period_Clean],Product_Month_Actual_Variable_Cost[[#Headers],[2025-02]],Table4[CostType],"Variable") -> 1242.76 | P8: =SUMIFS(Table4[ActualCost_Clean],Table4[ProductID_Clean],Product_Month_Actual_Variable_Cost[[#This Row],[ProductID]],Table4[Period_Clean],Product_Month_Actual_Variable_Cost[[#Headers],[2025-03]],Table4[CostType],"Variable") -> 1218.76 | Q8: =SUMIFS(Table4[ActualCost_Clean],Table4[ProductID_Clean],Product_Month_Actual_Variable_Cost[[#This Row],[ProductID]],Table4[Period_Clean],Product_Month_Actual_Variable_Cost[[#Headers],[2025-04]],Table4[CostType],"Variable") -> 1247.48 | R8: =SUMIFS(Table4[ActualCost_Clean],Table4[ProductID_Clean],Product_Month_Actual_Variable_Cost[[#This Row],[ProductID]],Table4[Period_Clean],Product_Month_Actual_Variable_Cost[[#Headers],[2025-05]],Table4[CostType],"Variable") -> 1247.2 | S8: =SUMIFS(Table4[ActualCost_Clean],Table4[ProductID_Clean],Product_Month_Actual_Variable_Cost[[#This Row],[ProductID]],Table4[Period_Clean],Product_Month_Actual_Variable_Cost[[#Headers],[2025-06]],Table4[CostType],"Variable") -> 1271.29 | V8: P-FS-002 | W8: APAC | X8: =Table33[[#This Row],[1/1/2025]]*Product_Month_Actual_Variable_Cost[[#This Row],[2025-01]] -> 3791.13 | Y8: =Table33[[#This Row],[2/1/2025]]*Product_Month_Actual_Variable_Cost[[#This Row],[2025-02]] -> 0 | Z8: =Table33[[#This Row],[3/1/2025]]*Product_Month_Actual_Variable_Cost[[#This Row],[2025-03]] -> 2437.52 | AA8: =Table33[[#This Row],[4/1/2025]]*Product_Month_Actual_Variable_Cost[[#This Row],[2025-04]] -> 1247.48 | AB8: =Table33[[#This Row],[5/1/2025]]*Product_Month_Actual_Variable_Cost[[#This Row],[2025-05]] -> 8730.4 | AC8: =Table33[[#This Row],[6/1/2025]]*Product_Month_Actual_Variable_Cost[[#This Row],[2025-06]] -> 0 | AD8: =SUM(Product_Region_Monthly_Variable_Cost[[#This Row],[25-Jan]:[25-Jun]]) -> 16206.53 | AG8: P-FS-002 | AH8: APAC | AI8: =SUMIFS(Table4[ActualCost_Clean],Table4[ProductID_Clean],Product_Month_Actual_Fixed_Cost[[#This Row],[ProductID]],Table4[Period_Clean],Product_Month_Actual_Variable_Cost[[#Headers],[2025-01]],Table4[CostType],"Fixed") -> 301.18 | AJ8: =SUMIFS(Table4[ActualCost_Clean],Table4[ProductID_Clean],Product_Month_Actual_Fixed_Cost[[#This Row],[ProductID]],Table4[Period_Clean],Product_Month_Actual_Variable_Cost[[#Headers],[2025-02]],Table4[CostType],"Fixed") -> 290.14 | AK8: =SUMIFS(Table4[ActualCost_Clean],Table4[ProductID_Clean],Product_Month_Actual_Fixed_Cost[[#This Row],[ProductID]],Table4[Period_Clean],Product_Month_Actual_Variable_Cost[[#Headers],[2025-03]],Table4[CostType],"Fixed") -> 277.74 | AL8: =SUMIFS(Table4[ActualCost_Clean],Table4[ProductID_Clean],Product_Month_Actual_Fixed_Cost[[#This Row],[ProductID]],Table4[Period_Clean],Product_Month_Actual_Variable_Cost[[#Headers],[2025-04]],Table4[CostType],"Fixed") -> 290.36 | AM8: =SUMIFS(Table4[ActualCost_Clean],Table4[ProductID_Clean],Product_Month_Actual_Fixed_Cost[[#This Row],[ProductID]],Table4[Period_Clean],Product_Month_Actual_Variable_Cost[[#Headers],[2025-05]],Table4[CostType],"Fixed") -> 283.91 | AN8: =SUMIFS(Table4[ActualCost_Clean],Table4[ProductID_Clean],Product_Month_Actual_Fixed_Cost[[#This Row],[ProductID]],Table4[Period_Clean],Product_Month_Actual_Variable_Cost[[#Headers],[2025-06]],Table4[CostType],"Fixed") -> 296.85 | AQ8: P-FS-002 | AR8: APAC | AS8: =Product_Month_Actual_Fixed_Cost[[#This Row],[2025-01]]*Table33[[#This Row],[1/1/2025]] -> 903.54 | AT8: =Product_Month_Actual_Fixed_Cost[[#This Row],[2025-02]]*Table33[[#This Row],[2/1/2025]] -> 0 | AU8: =Product_Month_Actual_Fixed_Cost[[#This Row],[2025-03]]*Table33[[#This Row],[3/1/2025]] -> 555.48 | AV8: =Product_Month_Actual_Fixed_Cost[[#This Row],[2025-04]]*Table33[[#This Row],[4/1/2025]] -> 290.36 | AW8: =Product_Month_Actual_Fixed_Cost[[#This Row],[2025-05]]*Table33[[#This Row],[5/1/2025]] -> 1987.37 | AX8: =Product_Month_Actual_Fixed_Cost[[#This Row],[2025-06]]*Table33[[#This Row],[6/1/2025]] -> 0 | AY8: =SUM(Product_Region_Monthly_Fixed_Cost[[#This Row],[25-Jan]:[25-Jun]]) -> 3736.75 | BB8: P-FS-002 | BC8: APAC | BD8: =Product_Region_Monthly_Fixed_Cost[[#This Row],[25-Jan]]+Product_Region_Monthly_Variable_Cost[[#This Row],[25-Jan]] -> 4694.67 | BE8: =Product_Region_Monthly_Fixed_Cost[[#This Row],[25-Feb]]+Product_Region_Monthly_Variable_Cost[[#This Row],[25-Feb]] -> 0 | BF8: =Product_Region_Monthly_Fixed_Cost[[#This Row],[25-Mar]]+Product_Region_Monthly_Variable_Cost[[#This Row],[25-Mar]] -> 2993 | BG8: =Product_Region_Monthly_Fixed_Cost[[#This Row],[25-Apr]]+Product_Region_Monthly_Variable_Cost[[#This Row],[25-Apr]] -> 1537.84 | BH8: =Product_Region_Monthly_Fixed_Cost[[#This Row],[25-May]]+Product_Region_Monthly_Variable_Cost[[#This Row],[25-May]] -> 10717.77 | BI8: =Product_Region_Monthly_Fixed_Cost[[#This Row],[25-Jun]]+Product_Region_Monthly_Variable_Cost[[#This Row],[25-Jun]] -> 0 | BJ8: =Product_Region_Monthly_Fixed_Cost[[#This Row],[H1 Fixed Cost]]+Product_Region_Monthly_Variable_Cost[[#This Row],[H1 Variable Cost]] -> 19943.28
A9: P-FS-002 | B9: LATIN AMERICA | C9: =SUMIFS(Table1[Quantity],Table1[ProductID],Table33[[#This Row],[ProductID]],Table1[RegionClean_],Table33[[#This Row],[Region]],Table1[TransactionDate_Clean],">"&EOMONTH($C$1,-1),Table1[TransactionDate_Clean],"<="&EOMONTH($C$1,0)) -> 0 | D9: =SUMIFS(Table1[Quantity],Table1[ProductID],Table33[[#This Row],[ProductID]],Table1[RegionClean_],Table33[[#This Row],[Region]],Table1[TransactionDate_Clean],">"&EOMONTH($D$1,-1),Table1[TransactionDate_Clean],"<="&EOMONTH($D$1,0)) -> 0 | E9: =SUMIFS(Table1[Quantity],Table1[ProductID],Table33[[#This Row],[ProductID]],Table1[RegionClean_],Table33[[#This Row],[Region]],Table1[TransactionDate_Clean],">"&EOMONTH($E$1,-1),Table1[TransactionDate_Clean],"<="&EOMONTH($E$1,0)) -> 0 | F9: =SUMIFS(Table1[Quantity],Table1[ProductID],Table33[[#This Row],[ProductID]],Table1[RegionClean_],Table33[[#This Row],[Region]],Table1[TransactionDate_Clean],">"&EOMONTH($F$1,-1),Table1[TransactionDate_Clean],"<="&EOMONTH($F$1,0)) -> 2 | G9: =SUMIFS(Table1[Quantity],Table1[ProductID],Table33[[#This Row],[ProductID]],Table1[RegionClean_],Table33[[#This Row],[Region]],Table1[TransactionDate_Clean],">"&EOMONTH($G$1,-1),Table1[TransactionDate_Clean],"<="&EOMONTH($G$1,0)) -> 2 | H9: =SUMIFS(Table1[Quantity],Table1[ProductID],Table33[[#This Row],[ProductID]],Table1[RegionClean_],Table33[[#This Row],[Region]],Table1[TransactionDate_Clean],">"&EOMONTH($H$1,-1),Table1[TransactionDate_Clean],"<="&EOMONTH($H$1,0)) -> 0 | I9: =SUM(Table33[[#This Row],[1/1/2025]:[6/1/2025]]) -> 4 | L9: P-FS-002 | M9: LATIN AMERICA | N9: =SUMIFS(Table4[ActualCost_Clean],Table4[ProductID_Clean],Product_Month_Actual_Variable_Cost[[#This Row],[ProductID]],Table4[Period_Clean],Product_Month_Actual_Variable_Cost[[#Headers],[2025-01]],Table4[CostType],"Variable") -> 1263.71 | O9: =SUMIFS(Table4[ActualCost_Clean],Table4[ProductID_Clean],Product_Month_Actual_Variable_Cost[[#This Row],[ProductID]],Table4[Period_Clean],Product_Month_Actual_Variable_Cost[[#Headers],[2025-02]],Table4[CostType],"Variable") -> 1242.76 | P9: =SUMIFS(Table4[ActualCost_Clean],Table4[ProductID_Clean],Product_Month_Actual_Variable_Cost[[#This Row],[ProductID]],Table4[Period_Clean],Product_Month_Actual_Variable_Cost[[#Headers],[2025-03]],Table4[CostType],"Variable") -> 1218.76 | Q9: =SUMIFS(Table4[ActualCost_Clean],Table4[ProductID_Clean],Product_Month_Actual_Variable_Cost[[#This Row],[ProductID]],Table4[Period_Clean],Product_Month_Actual_Variable_Cost[[#Headers],[2025-04]],Table4[CostType],"Variable") -> 1247.48 | R9: =SUMIFS(Table4[ActualCost_Clean],Table4[ProductID_Clean],Product_Month_Actual_Variable_Cost[[#This Row],[ProductID]],Table4[Period_Clean],Product_Month_Actual_Variable_Cost[[#Headers],[2025-05]],Table4[CostType],"Variable") -> 1247.2 | S9: =SUMIFS(Table4[ActualCost_Clean],Table4[ProductID_Clean],Product_Month_Actual_Variable_Cost[[#This Row],[ProductID]],Table4[Period_Clean],Product_Month_Actual_Variable_Cost[[#Headers],[2025-06]],Table4[CostType],"Variable") -> 1271.29 | V9: P-FS-002 | W9: LATIN AMERICA | X9: =Table33[[#This Row],[1/1/2025]]*Product_Month_Actual_Variable_Cost[[#This Row],[2025-01]] -> 0 | Y9: =Table33[[#This Row],[2/1/2025]]*Product_Month_Actual_Variable_Cost[[#This Row],[2025-02]] -> 0 | Z9: =Table33[[#This Row],[3/1/2025]]*Product_Month_Actual_Variable_Cost[[#This Row],[2025-03]] -> 0 | AA9: =Table33[[#This Row],[4/1/2025]]*Product_Month_Actual_Variable_Cost[[#This Row],[2025-04]] -> 2494.96 | AB9: =Table33[[#This Row],[5/1/2025]]*Product_Month_Actual_Variable_Cost[[#This Row],[2025-05]] -> 2494.4 | AC9: =Table33[[#This Row],[6/1/2025]]*Product_Month_Actual_Variable_Cost[[#This Row],[2025-06]] -> 0 | AD9: =SUM(Product_Region_Monthly_Variable_Cost[[#This Row],[25-Jan]:[25-Jun]]) -> 4989.36 | AG9: P-FS-002 | AH9: LATIN AMERICA | AI9: =SUMIFS(Table4[ActualCost_Clean],Table4[ProductID_Clean],Product_Month_Actual_Fixed_Cost[[#This Row],[ProductID]],Table4[Period_Clean],Product_Month_Actual_Variable_Cost[[#Headers],[2025-01]],Table4[CostType],"Fixed") -> 301.18 | AJ9: =SUMIFS(Table4[ActualCost_Clean],Table4[ProductID_Clean],Product_Month_Actual_Fixed_Cost[[#This Row],[ProductID]],Table4[Period_Clean],Product_Month_Actual_Variable_Cost[[#Headers],[2025-02]],Table4[CostType],"Fixed") -> 290.14 | AK9: =SUMIFS(Table4[ActualCost_Clean],Table4[ProductID_Clean],Product_Month_Actual_Fixed_Cost[[#This Row],[ProductID]],Table4[Period_Clean],Product_Month_Actual_Variable_Cost[[#Headers],[2025-03]],Table4[CostType],"Fixed") -> 277.74 | AL9: =SUMIFS(Table4[ActualCost_Clean],Table4[ProductID_Clean],Product_Month_Actual_Fixed_Cost[[#This Row],[ProductID]],Table4[Period_Clean],Product_Month_Actual_Variable_Cost[[#Headers],[2025-04]],Table4[CostType],"Fixed") -> 290.36 | AM9: =SUMIFS(Table4[ActualCost_Clean],Table4[ProductID_Clean],Product_Month_Actual_Fixed_Cost[[#This Row],[ProductID]],Table4[Period_Clean],Product_Month_Actual_Variable_Cost[[#Headers],[2025-05]],Table4[CostType],"Fixed") -> 283.91 | AN9: =SUMIFS(Table4[ActualCost_Clean],Table4[ProductID_Clean],Product_Month_Actual_Fixed_Cost[[#This Row],[ProductID]],Table4[Period_Clean],Product_Month_Actual_Variable_Cost[[#Headers],[2025-06]],Table4[CostType],"Fixed") -> 296.85 | AQ9: P-FS-002 | AR9: LATIN AMERICA | AS9: =Product_Month_Actual_Fixed_Cost[[#This Row],[2025-01]]*Table33[[#This Row],[1/1/2025]] -> 0 | AT9: =Product_Month_Actual_Fixed_Cost[[#This Row],[2025-02]]*Table33[[#This Row],[2/1/2025]] -> 0 | AU9: =Product_Month_Actual_Fixed_Cost[[#This Row],[2025-03]]*Table33[[#This Row],[3/1/2025]] -> 0 | AV9: =Product_Month_Actual_Fixed_Cost[[#This Row],[2025-04]]*Table33[[#This Row],[4/1/2025]] -> 580.72 | AW9: =Product_Month_Actual_Fixed_Cost[[#This Row],[2025-05]]*Table33[[#This Row],[5/1/2025]] -> 567.82 | AX9: =Product_Month_Actual_Fixed_Cost[[#This Row],[2025-06]]*Table33[[#This Row],[6/1/2025]] -> 0 | AY9: =SUM(Product_Region_Monthly_Fixed_Cost[[#This Row],[25-Jan]:[25-Jun]]) -> 1148.54 | BB9: P-FS-002 | BC9: LATIN AMERICA | BD9: =Product_Region_Monthly_Fixed_Cost[[#This Row],[25-Jan]]+Product_Region_Monthly_Variable_Cost[[#This Row],[25-Jan]] -> 0 | BE9: =Product_Region_Monthly_Fixed_Cost[[#This Row],[25-Feb]]+Product_Region_Monthly_Variable_Cost[[#This Row],[25-Feb]] -> 0 | BF9: =Product_Region_Monthly_Fixed_Cost[[#This Row],[25-Mar]]+Product_Region_Monthly_Variable_Cost[[#This Row],[25-Mar]] -> 0 | BG9: =Product_Region_Monthly_Fixed_Cost[[#This Row],[25-Apr]]+Product_Region_Monthly_Variable_Cost[[#This Row],[25-Apr]] -> 3075.68 | BH9: =Product_Region_Monthly_Fixed_Cost[[#This Row],[25-May]]+Product_Region_Monthly_Variable_Cost[[#This Row],[25-May]] -> 3062.22 | BI9: =Product_Region_Monthly_Fixed_Cost[[#This Row],[25-Jun]]+Product_Region_Monthly_Variable_Cost[[#This Row],[25-Jun]] -> 0 | BJ9: =Product_Region_Monthly_Fixed_Cost[[#This Row],[H1 Fixed Cost]]+Product_Region_Monthly_Variable_Cost[[#This Row],[H1 Variable Cost]] -> 6137.9
A10: P-FS-003 | B10: N. AMERICA | C10: =SUMIFS(Table1[Quantity],Table1[ProductID],Table33[[#This Row],[ProductID]],Table1[RegionClean_],Table33[[#This Row],[Region]],Table1[TransactionDate_Clean],">"&EOMONTH($C$1,-1),Table1[TransactionDate_Clean],"<="&EOMONTH($C$1,0)) -> 1 | D10: =SUMIFS(Table1[Quantity],Table1[ProductID],Table33[[#This Row],[ProductID]],Table1[RegionClean_],Table33[[#This Row],[Region]],Table1[TransactionDate_Clean],">"&EOMONTH($D$1,-1),Table1[TransactionDate_Clean],"<="&EOMONTH($D$1,0)) -> 0 | E10: =SUMIFS(Table1[Quantity],Table1[ProductID],Table33[[#This Row],[ProductID]],Table1[RegionClean_],Table33[[#This Row],[Region]],Table1[TransactionDate_Clean],">"&EOMONTH($E$1,-1),Table1[TransactionDate_Clean],"<="&EOMONTH($E$1,0)) -> 0 | F10: =SUMIFS(Table1[Quantity],Table1[ProductID],Table33[[#This Row],[ProductID]],Table1[RegionClean_],Table33[[#This Row],[Region]],Table1[TransactionDate_Clean],">"&EOMONTH($F$1,-1),Table1[TransactionDate_Clean],"<="&EOMONTH($F$1,0)) -> 3 | G10: =SUMIFS(Table1[Quantity],Table1[ProductID],Table33[[#This Row],[ProductID]],Table1[RegionClean_],Table33[[#This Row],[Region]],Table1[TransactionDate_Clean],">"&EOMONTH($G$1,-1),Table1[TransactionDate_Clean],"<="&EOMONTH($G$1,0)) -> 2 | H10: =SUMIFS(Table1[Quantity],Table1[ProductID],Table33[[#This Row],[ProductID]],Table1[RegionClean_],Table33[[#This Row],[Region]],Table1[TransactionDate_Clean],">"&EOMONTH($H$1,-1),Table1[TransactionDate_Clean],"<="&EOMONTH($H$1,0)) -> 4 | I10: =SUM(Table33[[#This Row],[1/1/2025]:[6/1/2025]]) -> 10 | L10: P-FS-003 | M10: N. AMERICA | N10: =SUMIFS(Table4[ActualCost_Clean],Table4[ProductID_Clean],Product_Month_Actual_Variable_Cost[[#This Row],[ProductID]],Table4[Period_Clean],Product_Month_Actual_Variable_Cost[[#Headers],[2025-01]],Table4[CostType],"Variable") -> 2111.06 | O10: =SUMIFS(Table4[ActualCost_Clean],Table4[ProductID_Clean],Product_Month_Actual_Variable_Cost[[#This Row],[ProductID]],Table4[Period_Clean],Product_Month_Actual_Variable_Cost[[#Headers],[2025-02]],Table4[CostType],"Variable") -> 2067.25 | P10: =SUMIFS(Table4[ActualCost_Clean],Table4[ProductID_Clean],Product_Month_Actual_Variable_Cost[[#This Row],[ProductID]],Table4[Period_Clean],Product_Month_Actual_Variable_Cost[[#Headers],[2025-03]],Table4[CostType],"Variable") -> 2105 | Q10: =SUMIFS(Table4[ActualCost_Clean],Table4[ProductID_Clean],Product_Month_Actual_Variable_Cost[[#This Row],[ProductID]],Table4[Period_Clean],Product_Month_Actual_Variable_Cost[[#Headers],[2025-04]],Table4[CostType],"Variable") -> 2112.37 | R10: =SUMIFS(Table4[ActualCost_Clean],Table4[ProductID_Clean],Product_Month_Actual_Variable_Cost[[#This Row],[ProductID]],Table4[Period_Clean],Product_Month_Actual_Variable_Cost[[#Headers],[2025-05]],Table4[CostType],"Variable") -> 2122.36 | S10: =SUMIFS(Table4[ActualCost_Clean],Table4[ProductID_Clean],Product_Month_Actual_Variable_Cost[[#This Row],[ProductID]],Table4[Period_Clean],Product_Month_Actual_Variable_Cost[[#Headers],[2025-06]],Table4[CostType],"Variable") -> 2152.22 | V10: P-FS-003 | W10: N. AMERICA | X10: =Table33[[#This Row],[1/1/2025]]*Product_Month_Actual_Variable_Cost[[#This Row],[2025-01]] -> 2111.06 | Y10: =Table33[[#This Row],[2/1/2025]]*Product_Month_Actual_Variable_Cost[[#This Row],[2025-02]] -> 0 | Z10: =Table33[[#This Row],[3/1/2025]]*Product_Month_Actual_Variable_Cost[[#This Row],[2025-03]] -> 0 | AA10: =Table33[[#This Row],[4/1/2025]]*Product_Month_Actual_Variable_Cost[[#This Row],[2025-04]] -> 6337.11 | AB10: =Table33[[#This Row],[5/1/2025]]*Product_Month_Actual_Variable_Cost[[#This Row],[2025-05]] -> 4244.72 | AC10: =Table33[[#This Row],[6/1/2025]]*Product_Month_Actual_Variable_Cost[[#This Row],[2025-06]] -> 8608.88 | AD10: =SUM(Product_Region_Monthly_Variable_Cost[[#This Row],[25-Jan]:[25-Jun]]) -> 21301.77 | AG10: P-FS-003 | AH10: N. AMERICA | AI10: =SUMIFS(Table4[ActualCost_Clean],Table4[ProductID_Clean],Product_Month_Actual_Fixed_Cost[[#This Row],[ProductID]],Table4[Period_Clean],Product_Month_Actual_Variable_Cost[[#Headers],[2025-01]],Table4[CostType],"Fixed") -> 424.87 | AJ10: =SUMIFS(Table4[ActualCost_Clean],Table4[ProductID_Clean],Product_Month_Actual_Fixed_Cost[[#This Row],[ProductID]],Table4[Period_Clean],Product_Month_Actual_Variable_Cost[[#Headers],[2025-02]],Table4[CostType],"Fixed") -> 415.32 | AK10: =SUMIFS(Table4[ActualCost_Clean],Table4[ProductID_Clean],Product_Month_Actual_Fixed_Cost[[#This Row],[ProductID]],Table4[Period_Clean],Product_Month_Actual_Variable_Cost[[#Headers],[2025-03]],Table4[CostType],"Fixed") -> 408.18 | AL10: =SUMIFS(Table4[ActualCost_Clean],Table4[ProductID_Clean],Product_Month_Actual_Fixed_Cost[[#This Row],[ProductID]],Table4[Period_Clean],Product_Month_Actual_Variable_Cost[[#Headers],[2025-04]],Table4[CostType],"Fixed") -> 434.23 | AM10: =SUMIFS(Table4[ActualCost_Clean],Table4[ProductID_Clean],Product_Month_Actual_Fixed_Cost[[#This Row],[ProductID]],Table4[Period_Clean],Product_Month_Actual_Variable_Cost[[#Headers],[2025-05]],Table4[CostType],"Fixed") -> 393.61 | AN10: =SUMIFS(Table4[ActualCost_Clean],Table4[ProductID_Clean],Product_Month_Actual_Fixed_Cost[[#This Row],[ProductID]],Table4[Period_Clean],Product_Month_Actual_Variable_Cost[[#Headers],[2025-06]],Table4[CostType],"Fixed") -> 393.65 | AQ10: P-FS-003 | AR10: N. AMERICA | AS10: =Product_Month_Actual_Fixed_Cost[[#This Row],[2025-01]]*Table33[[#This Row],[1/1/2025]] -> 424.87 | AT10: =Product_Month_Actual_Fixed_Cost[[#This Row],[2025-02]]*Table33[[#This Row],[2/1/2025]] -> 0 | AU10: =Product_Month_Actual_Fixed_Cost[[#This Row],[2025-03]]*Table33[[#This Row],[3/1/2025]] -> 0 | AV10: =Product_Month_Actual_Fixed_Cost[[#This Row],[2025-04]]*Table33[[#This Row],[4/1/2025]] -> 1302.69 | AW10: =Product_Month_Actual_Fixed_Cost[[#This Row],[2025-05]]*Table33[[#This Row],[5/1/2025]] -> 787.22 | AX10: =Product_Month_Actual_Fixed_Cost[[#This Row],[2025-06]]*Table33[[#This Row],[6/1/2025]] -> 1574.6 | AY10: =SUM(Product_Region_Monthly_Fixed_Cost[[#This Row],[25-Jan]:[25-Jun]]) -> 4089.38 | BB10: P-FS-003 | BC10: N. AMERICA | BD10: =Product_Region_Monthly_Fixed_Cost[[#This Row],[25-Jan]]+Product_Region_Monthly_Variable_Cost[[#This Row],[25-Jan]] -> 2535.93 | BE10: =Product_Region_Monthly_Fixed_Cost[[#This Row],[25-Feb]]+Product_Region_Monthly_Variable_Cost[[#This Row],[25-Feb]] -> 0 | BF10: =Product_Region_Monthly_Fixed_Cost[[#This Row],[25-Mar]]+Product_Region_Monthly_Variable_Cost[[#This Row],[25-Mar]] -> 0 | BG10: =Product_Region_Monthly_Fixed_Cost[[#This Row],[25-Apr]]+Product_Region_Monthly_Variable_Cost[[#This Row],[25-Apr]] -> 7639.8 | BH10: =Product_Region_Monthly_Fixed_Cost[[#This Row],[25-May]]+Product_Region_Monthly_Variable_Cost[[#This Row],[25-May]] -> 5031.94 | BI10: =Product_Region_Monthly_Fixed_Cost[[#This Row],[25-Jun]]+Product_Region_Monthly_Variable_Cost[[#This Row],[25-Jun]] -> 10183.48 | BJ10: =Product_Region_Monthly_Fixed_Cost[[#This Row],[H1 Fixed Cost]]+Product_Region_Monthly_Variable_Cost[[#This Row],[H1 Variable Cost]] -> 25391.15
A11: P-FS-003 | B11: EMEA | C11: =SUMIFS(Table1[Quantity],Table1[ProductID],Table33[[#This Row],[ProductID]],Table1[RegionClean_],Table33[[#This Row],[Region]],Table1[TransactionDate_Clean],">"&EOMONTH($C$1,-1),Table1[TransactionDate_Clean],"<="&EOMONTH($C$1,0)) -> 0 | D11: =SUMIFS(Table1[Quantity],Table1[ProductID],Table33[[#This Row],[ProductID]],Table1[RegionClean_],Table33[[#This Row],[Region]],Table1[TransactionDate_Clean],">"&EOMONTH($D$1,-1),Table1[TransactionDate_Clean],"<="&EOMONTH($D$1,0)) -> 0 | E11: =SUMIFS(Table1[Quantity],Table1[ProductID],Table33[[#This Row],[ProductID]],Table1[RegionClean_],Table33[[#This Row],[Region]],Table1[TransactionDate_Clean],">"&EOMONTH($E$1,-1),Table1[TransactionDate_Clean],"<="&EOMONTH($E$1,0)) -> 2 | F11: =SUMIFS(Table1[Quantity],Table1[ProductID],Table33[[#This Row],[ProductID]],Table1[RegionClean_],Table33[[#This Row],[Region]],Table1[TransactionDate_Clean],">"&EOMONTH($F$1,-1),Table1[TransactionDate_Clean],"<="&EOMONTH($F$1,0)) -> 3 | G11: =SUMIFS(Table1[Quantity],Table1[ProductID],Table33[[#This Row],[ProductID]],Table1[RegionClean_],Table33[[#This Row],[Region]],Table1[TransactionDate_Clean],">"&EOMONTH($G$1,-1),Table1[TransactionDate_Clean],"<="&EOMONTH($G$1,0)) -> 0 | H11: =SUMIFS(Table1[Quantity],Table1[ProductID],Table33[[#This Row],[ProductID]],Table1[RegionClean_],Table33[[#This Row],[Region]],Table1[TransactionDate_Clean],">"&EOMONTH($H$1,-1),Table1[TransactionDate_Clean],"<="&EOMONTH($H$1,0)) -> 2 | I11: =SUM(Table33[[#This Row],[1/1/2025]:[6/1/2025]]) -> 7 | L11: P-FS-003 | M11: EMEA | N11: =SUMIFS(Table4[ActualCost_Clean],Table4[ProductID_Clean],Product_Month_Actual_Variable_Cost[[#This Row],[ProductID]],Table4[Period_Clean],Product_Month_Actual_Variable_Cost[[#Headers],[2025-01]],Table4[CostType],"Variable") -> 2111.06 | O11: =SUMIFS(Table4[ActualCost_Clean],Table4[ProductID_Clean],Product_Month_Actual_Variable_Cost[[#This Row],[ProductID]],Table4[Period_Clean],Product_Month_Actual_Variable_Cost[[#Headers],[2025-02]],Table4[CostType],"Variable") -> 2067.25 | P11: =SUMIFS(Table4[ActualCost_Clean],Table4[ProductID_Clean],Product_Month_Actual_Variable_Cost[[#This Row],[ProductID]],Table4[Period_Clean],Product_Month_Actual_Variable_Cost[[#Headers],[2025-03]],Table4[CostType],"Variable") -> 2105 | Q11: =SUMIFS(Table4[ActualCost_Clean],Table4[ProductID_Clean],Product_Month_Actual_Variable_Cost[[#This Row],[ProductID]],Table4[Period_Clean],Product_Month_Actual_Variable_Cost[[#Headers],[2025-04]],Table4[CostType],"Variable") -> 2112.37 | R11: =SUMIFS(Table4[ActualCost_Clean],Table4[ProductID_Clean],Product_Month_Actual_Variable_Cost[[#This Row],[ProductID]],Table4[Period_Clean],Product_Month_Actual_Variable_Cost[[#Headers],[2025-05]],Table4[CostType],"Variable") -> 2122.36 | S11: =SUMIFS(Table4[ActualCost_Clean],Table4[ProductID_Clean],Product_Month_Actual_Variable_Cost[[#This Row],[ProductID]],Table4[Period_Clean],Product_Month_Actual_Variable_Cost[[#Headers],[2025-06]],Table4[CostType],"Variable") -> 2152.22 | V11: P-FS-003 | W11: EMEA | X11: =Table33[[#This Row],[1/1/2025]]*Product_Month_Actual_Variable_Cost[[#This Row],[2025-01]] -> 0 | Y11: =Table33[[#This Row],[2/1/2025]]*Product_Month_Actual_Variable_Cost[[#This Row],[2025-02]] -> 0 | Z11: =Table33[[#This Row],[3/1/2025]]*Product_Month_Actual_Variable_Cost[[#This Row],[2025-03]] -> 4210 | AA11: =Table33[[#This Row],[4/1/2025]]*Product_Month_Actual_Variable_Cost[[#This Row],[2025-04]] -> 6337.11 | AB11: =Table33[[#This Row],[5/1/2025]]*Product_Month_Actual_Variable_Cost[[#This Row],[2025-05]] -> 0 | AC11: =Table33[[#This Row],[6/1/2025]]*Product_Month_Actual_Variable_Cost[[#This Row],[2025-06]] -> 4304.44 | AD11: =SUM(Product_Region_Monthly_Variable_Cost[[#This Row],[25-Jan]:[25-Jun]]) -> 14851.55 | AG11: P-FS-003 | AH11: EMEA | AI11: =SUMIFS(Table4[ActualCost_Clean],Table4[ProductID_Clean],Product_Month_Actual_Fixed_Cost[[#This Row],[ProductID]],Table4[Period_Clean],Product_Month_Actual_Variable_Cost[[#Headers],[2025-01]],Table4[CostType],"Fixed") -> 424.87 | AJ11: =SUMIFS(Table4[ActualCost_Clean],Table4[ProductID_Clean],Product_Month_Actual_Fixed_Cost[[#This Row],[ProductID]],Table4[Period_Clean],Product_Month_Actual_Variable_Cost[[#Headers],[2025-02]],Table4[CostType],"Fixed") -> 415.32 | AK11: =SUMIFS(Table4[ActualCost_Clean],Table4[ProductID_Clean],Product_Month_Actual_Fixed_Cost[[#This Row],[ProductID]],Table4[Period_Clean],Product_Month_Actual_Variable_Cost[[#Headers],[2025-03]],Table4[CostType],"Fixed") -> 408.18 | AL11: =SUMIFS(Table4[ActualCost_Clean],Table4[ProductID_Clean],Product_Month_Actual_Fixed_Cost[[#This Row],[ProductID]],Table4[Period_Clean],Product_Month_Actual_Variable_Cost[[#Headers],[2025-04]],Table4[CostType],"Fixed") -> 434.23 | AM11: =SUMIFS(Table4[ActualCost_Clean],Table4[ProductID_Clean],Product_Month_Actual_Fixed_Cost[[#This Row],[ProductID]],Table4[Period_Clean],Product_Month_Actual_Variable_Cost[[#Headers],[2025-05]],Table4[CostType],"Fixed") -> 393.61 | AN11: =SUMIFS(Table4[ActualCost_Clean],Table4[ProductID_Clean],Product_Month_Actual_Fixed_Cost[[#This Row],[ProductID]],Table4[Period_Clean],Product_Month_Actual_Variable_Cost[[#Headers],[2025-06]],Table4[CostType],"Fixed") -> 393.65 | AQ11: P-FS-003 | AR11: EMEA | AS11: =Product_Month_Actual_Fixed_Cost[[#This Row],[2025-01]]*Table33[[#This Row],[1/1/2025]] -> 0 | AT11: =Product_Month_Actual_Fixed_Cost[[#This Row],[2025-02]]*Table33[[#This Row],[2/1/2025]] -> 0 | AU11: =Product_Month_Actual_Fixed_Cost[[#This Row],[2025-03]]*Table33[[#This Row],[3/1/2025]] -> 816.36 | AV11: =Product_Month_Actual_Fixed_Cost[[#This Row],[2025-04]]*Table33[[#This Row],[4/1/2025]] -> 1302.69 | AW11: =Product_Month_Actual_Fixed_Cost[[#This Row],[2025-05]]*Table33[[#This Row],[5/1/2025]] -> 0 | AX11: =Product_Month_Actual_Fixed_Cost[[#This Row],[2025-06]]*Table33[[#This Row],[6/1/2025]] -> 787.3 | AY11: =SUM(Product_Region_Monthly_Fixed_Cost[[#This Row],[25-Jan]:[25-Jun]]) -> 2906.35 | BB11: P-FS-003 | BC11: EMEA | BD11: =Product_Region_Monthly_Fixed_Cost[[#This Row],[25-Jan]]+Product_Region_Monthly_Variable_Cost[[#This Row],[25-Jan]] -> 0 | BE11: =Product_Region_Monthly_Fixed_Cost[[#This Row],[25-Feb]]+Product_Region_Monthly_Variable_Cost[[#This Row],[25-Feb]] -> 0 | BF11: =Product_Region_Monthly_Fixed_Cost[[#This Row],[25-Mar]]+Product_Region_Monthly_Variable_Cost[[#This Row],[25-Mar]] -> 5026.36 | BG11: =Product_Region_Monthly_Fixed_Cost[[#This Row],[25-Apr]]+Product_Region_Monthly_Variable_Cost[[#This Row],[25-Apr]] -> 7639.8 | BH11: =Product_Region_Monthly_Fixed_Cost[[#This Row],[25-May]]+Product_Region_Monthly_Variable_Cost[[#This Row],[25-May]] -> 0 | BI11: =Product_Region_Monthly_Fixed_Cost[[#This Row],[25-Jun]]+Product_Region_Monthly_Variable_Cost[[#This Row],[25-Jun]] -> 5091.74 | BJ11: =Product_Region_Monthly_Fixed_Cost[[#This Row],[H1 Fixed Cost]]+Product_Region_Monthly_Variable_Cost[[#This Row],[H1 Variable Cost]] -> 17757.9
A12: P-FS-003 | B12: APAC | C12: =SUMIFS(Table1[Quantity],Table1[ProductID],Table33[[#This Row],[ProductID]],Table1[RegionClean_],Table33[[#This Row],[Region]],Table1[TransactionDate_Clean],">"&EOMONTH($C$1,-1),Table1[TransactionDate_Clean],"<="&EOMONTH($C$1,0)) -> 1 | D12: =SUMIFS(Table1[Quantity],Table1[ProductID],Table33[[#This Row],[ProductID]],Table1[RegionClean_],Table33[[#This Row],[Region]],Table1[TransactionDate_Clean],">"&EOMONTH($D$1,-1),Table1[TransactionDate_Clean],"<="&EOMONTH($D$1,0)) -> 0 | E12: =SUMIFS(Table1[Quantity],Table1[ProductID],Table33[[#This Row],[ProductID]],Table1[RegionClean_],Table33[[#This Row],[Region]],Table1[TransactionDate_Clean],">"&EOMONTH($E$1,-1),Table1[TransactionDate_Clean],"<="&EOMONTH($E$1,0)) -> 3 | F12: =SUMIFS(Table1[Quantity],Table1[ProductID],Table33[[#This Row],[ProductID]],Table1[RegionClean_],Table33[[#This Row],[Region]],Table1[TransactionDate_Clean],">"&EOMONTH($F$1,-1),Table1[TransactionDate_Clean],"<="&EOMONTH($F$1,0)) -> 0 | G12: =SUMIFS(Table1[Quantity],Table1[ProductID],Table33[[#This Row],[ProductID]],Table1[RegionClean_],Table33[[#This Row],[Region]],Table1[TransactionDate_Clean],">"&EOMONTH($G$1,-1),Table1[TransactionDate_Clean],"<="&EOMONTH($G$1,0)) -> 1 | H12: =SUMIFS(Table1[Quantity],Table1[ProductID],Table33[[#This Row],[ProductID]],Table1[RegionClean_],Table33[[#This Row],[Region]],Table1[TransactionDate_Clean],">"&EOMONTH($H$1,-1),Table1[TransactionDate_Clean],"<="&EOMONTH($H$1,0)) -> 2 | I12: =SUM(Table33[[#This Row],[1/1/2025]:[6/1/2025]]) -> 7 | L12: P-FS-003 | M12: APAC | N12: =SUMIFS(Table4[ActualCost_Clean],Table4[ProductID_Clean],Product_Month_Actual_Variable_Cost[[#This Row],[ProductID]],Table4[Period_Clean],Product_Month_Actual_Variable_Cost[[#Headers],[2025-01]],Table4[CostType],"Variable") -> 2111.06 | O12: =SUMIFS(Table4[ActualCost_Clean],Table4[ProductID_Clean],Product_Month_Actual_Variable_Cost[[#This Row],[ProductID]],Table4[Period_Clean],Product_Month_Actual_Variable_Cost[[#Headers],[2025-02]],Table4[CostType],"Variable") -> 2067.25 | P12: =SUMIFS(Table4[ActualCost_Clean],Table4[ProductID_Clean],Product_Month_Actual_Variable_Cost[[#This Row],[ProductID]],Table4[Period_Clean],Product_Month_Actual_Variable_Cost[[#Headers],[2025-03]],Table4[CostType],"Variable") -> 2105 | Q12: =SUMIFS(Table4[ActualCost_Clean],Table4[ProductID_Clean],Product_Month_Actual_Variable_Cost[[#This Row],[ProductID]],Table4[Period_Clean],Product_Month_Actual_Variable_Cost[[#Headers],[2025-04]],Table4[CostType],"Variable") -> 2112.37 | R12: =SUMIFS(Table4[ActualCost_Clean],Table4[ProductID_Clean],Product_Month_Actual_Variable_Cost[[#This Row],[ProductID]],Table4[Period_Clean],Product_Month_Actual_Variable_Cost[[#Headers],[2025-05]],Table4[CostType],"Variable") -> 2122.36 | S12: =SUMIFS(Table4[ActualCost_Clean],Table4[ProductID_Clean],Product_Month_Actual_Variable_Cost[[#This Row],[ProductID]],Table4[Period_Clean],Product_Month_Actual_Variable_Cost[[#Headers],[2025-06]],Table4[CostType],"Variable") -> 2152.22 | V12: P-FS-003 | W12: APAC | X12: =Table33[[#This Row],[1/1/2025]]*Product_Month_Actual_Variable_Cost[[#This Row],[2025-01]] -> 2111.06 | Y12: =Table33[[#This Row],[2/1/2025]]*Product_Month_Actual_Variable_Cost[[#This Row],[2025-02]] -> 0 | Z12: =Table33[[#This Row],[3/1/2025]]*Product_Month_Actual_Variable_Cost[[#This Row],[2025-03]] -> 6315 | AA12: =Table33[[#This Row],[4/1/2025]]*Product_Month_Actual_Variable_Cost[[#This Row],[2025-04]] -> 0 | AB12: =Table33[[#This Row],[5/1/2025]]*Product_Month_Actual_Variable_Cost[[#This Row],[2025-05]] -> 2122.36 | AC12: =Table33[[#This Row],[6/1/2025]]*Product_Month_Actual_Variable_Cost[[#This Row],[2025-06]] -> 4304.44 | AD12: =SUM(Product_Region_Monthly_Variable_Cost[[#This Row],[25-Jan]:[25-Jun]]) -> 14852.86 | AG12: P-FS-003 | AH12: APAC | AI12: =SUMIFS(Table4[ActualCost_Clean],Table4[ProductID_Clean],Product_Month_Actual_Fixed_Cost[[#This Row],[ProductID]],Table4[Period_Clean],Product_Month_Actual_Variable_Cost[[#Headers],[2025-01]],Table4[CostType],"Fixed") -> 424.87 | AJ12: =SUMIFS(Table4[ActualCost_Clean],Table4[ProductID_Clean],Product_Month_Actual_Fixed_Cost[[#This Row],[ProductID]],Table4[Period_Clean],Product_Month_Actual_Variable_Cost[[#Headers],[2025-02]],Table4[CostType],"Fixed") -> 415.32 | AK12: =SUMIFS(Table4[ActualCost_Clean],Table4[ProductID_Clean],Product_Month_Actual_Fixed_Cost[[#This Row],[ProductID]],Table4[Period_Clean],Product_Month_Actual_Variable_Cost[[#Headers],[2025-03]],Table4[CostType],"Fixed") -> 408.18 | AL12: =SUMIFS(Table4[ActualCost_Clean],Table4[ProductID_Clean],Product_Month_Actual_Fixed_Cost[[#This Row],[ProductID]],Table4[Period_Clean],Product_Month_Actual_Variable_Cost[[#Headers],[2025-04]],Table4[CostType],"Fixed") -> 434.23 | AM12: =SUMIFS(Table4[ActualCost_Clean],Table4[ProductID_Clean],Product_Month_Actual_Fixed_Cost[[#This Row],[ProductID]],Table4[Period_Clean],Product_Month_Actual_Variable_Cost[[#Headers],[2025-05]],Table4[CostType],"Fixed") -> 393.61 | AN12: =SUMIFS(Table4[ActualCost_Clean],Table4[ProductID_Clean],Product_Month_Actual_Fixed_Cost[[#This Row],[ProductID]],Table4[Period_Clean],Product_Month_Actual_Variable_Cost[[#Headers],[2025-06]],Table4[CostType],"Fixed") -> 393.65 | AQ12: P-FS-003 | AR12: APAC | AS12: =Product_Month_Actual_Fixed_Cost[[#This Row],[2025-01]]*Table33[[#This Row],[1/1/2025]] -> 424.87 | AT12: =Product_Month_Actual_Fixed_Cost[[#This Row],[2025-02]]*Table33[[#This Row],[2/1/2025]] -> 0 | AU12: =Product_Month_Actual_Fixed_Cost[[#This Row],[2025-03]]*Table33[[#This Row],[3/1/2025]] -> 1224.54 | AV12: =Product_Month_Actual_Fixed_Cost[[#This Row],[2025-04]]*Table33[[#This Row],[4/1/2025]] -> 0 | AW12: =Product_Month_Actual_Fixed_Cost[[#This Row],[2025-05]]*Table33[[#This Row],[5/1/2025]] -> 393.61 | AX12: =Product_Month_Actual_Fixed_Cost[[#This Row],[2025-06]]*Table33[[#This Row],[6/1/2025]] -> 787.3 | AY12: =SUM(Product_Region_Monthly_Fixed_Cost[[#This Row],[25-Jan]:[25-Jun]]) -> 2830.32 | BB12: P-FS-003 | BC12: APAC | BD12: =Product_Region_Monthly_Fixed_Cost[[#This Row],[25-Jan]]+Product_Region_Monthly_Variable_Cost[[#This Row],[25-Jan]] -> 2535.93 | BE12: =Product_Region_Monthly_Fixed_Cost[[#This Row],[25-Feb]]+Product_Region_Monthly_Variable_Cost[[#This Row],[25-Feb]] -> 0 | BF12: =Product_Region_Monthly_Fixed_Cost[[#This Row],[25-Mar]]+Product_Region_Monthly_Variable_Cost[[#This Row],[25-Mar]] -> 7539.54 | BG12: =Product_Region_Monthly_Fixed_Cost[[#This Row],[25-Apr]]+Product_Region_Monthly_Variable_Cost[[#This Row],[25-Apr]] -> 0 | BH12: =Product_Region_Monthly_Fixed_Cost[[#This Row],[25-May]]+Product_Region_Monthly_Variable_Cost[[#This Row],[25-May]] -> 2515.97 | BI12: =Product_Region_Monthly_Fixed_Cost[[#This Row],[25-Jun]]+Product_Region_Monthly_Variable_Cost[[#This Row],[25-Jun]] -> 5091.74 | BJ12: =Product_Region_Monthly_Fixed_Cost[[#This Row],[H1 Fixed Cost]]+Product_Region_Monthly_Variable_Cost[[#This Row],[H1 Variable Cost]] -> 17683.18
